Workbook

Sheet _Output
B1: in scope | C1: type | D1: answer | E1: importance | F1: NIST mapping (CSF 1.1) | G1: NIST in scope (CSF 1.1) | H1: factor (SUM = MIN score) | I1: total score | J1: MAX score | K1: final score | L1: remarks
A2: SOC-CMM - Business Domain
A3: B1 - Business Drivers
A4: B 1.1 | B4: 1 | C4: M | D4: 0 | E4: 3 | F4: ID.BE-5 | G4: =IF(B4=1,F4,"") -> ID.BE-5 | H4: =VLOOKUP(E4,'_Score matrix'!$B$31:$C$35,2,FALSE) -> 1 | I4: =D4*H4 -> 0 | J4: =5*H4 -> 5 | K4: =IF(ROUND(100*(I4-H4)/(J4-H4),2) < 0, 0, ROUND(100*(I4-H4)/(J4-H4),2)) -> 0
A5: B 1.2 | B5: 1 | C5: M | D5: 0 | E5: 3 | F5: ID.BE-5 | G5: =IF(B5=1,F5,"") -> ID.BE-5 | H5: =VLOOKUP(E5,'_Score matrix'!$B$31:$C$35,2,FALSE) -> 1 | I5: =D5*H5 -> 0 | J5: =5*H5 -> 5 | K5: =IF(ROUND(100*(I5-H5)/(J5-H5),2) < 0, 0, ROUND(100*(I5-H5)/(J5-H5),2)) -> 0
A6: B 1.3 | B6: 1 | C6: M | D6: 0 | E6: 3 | F6: ID.BE-5 | G6: =IF(B6=1,F6,"") -> ID.BE-5 | H6: =VLOOKUP(E6,'_Score matrix'!$B$31:$C$35,2,FALSE) -> 1 | I6: =D6*H6 -> 0 | J6: =5*H6 -> 5 | K6: =IF(ROUND(100*(I6-H6)/(J6-H6),2) < 0, 0, ROUND(100*(I6-H6)/(J6-H6),2)) -> 0
A7: B 1.4 | B7: 1 | C7: M | D7: 0 | E7: 3 | F7: ID.BE-5 | G7: =IF(B7=1,F7,"") -> ID.BE-5 | H7: =VLOOKUP(E7,'_Score matrix'!$B$31:$C$35,2,FALSE) -> 1 | I7: =D7*H7 -> 0 | J7: =5*H7 -> 5 | K7: =IF(ROUND(100*(I7-H7)/(J7-H7),2) < 0, 0, ROUND(100*(I7-H7)/(J7-H7),2)) -> 0
A8: B 1.5 | B8: 1 | C8: M | D8: 0 | E8: 3 | F8: ID.BE-4 | G8: =IF(B8=1,F8,"") -> ID.BE-4 | H8: =VLOOKUP(E8,'_Score matrix'!$B$31:$C$35,2,FALSE) -> 1 | I8: =D8*H8 -> 0 | J8: =5*H8 -> 5 | K8: =IF(ROUND(100*(I8-H8)/(J8-H8),2) < 0, 0, ROUND(100*(I8-H8)/(J8-H8),2)) -> 0
A9: SUM | D9: =SUMIFS(D:D,$A:$A,"B 1*",$B:$B,1,$C:$C,"M",$L:$L,"<>NIST MAPPING") -> 0 | E9: =SUMIFS(E:E,$A:$A,"B 1*",$B:$B,1,$C:$C,"M",$L:$L,"<>NIST MAPPING") -> 15 | F9: =SUMIFS(F:F,$A:$A,"B 1*",$B:$B,1,$C:$C,"M",$L:$L,"<>NIST MAPPING") -> 0 | G9: =SUMIFS(G:G,$A:$A,"B 1*",$B:$B,1,$C:$C,"M",$L:$L,"<>NIST MAPPING") -> 0 | H9: =SUMIFS(H:H,$A:$A,"B 1*",$B:$B,1,$C:$C,"M",$L:$L,"<>NIST MAPPING") -> 5 | I9: =SUMIFS(I:I,$A:$A,"B 1*",$B:$B,1,$C:$C,"M",$L:$L,"<>NIST MAPPING") -> 0 | J9: =SUMIFS(J:J,$A:$A,"B 1*",$B:$B,1,$C:$C,"M",$L:$L,"<>NIST MAPPING") -> 25 | K9: =IF(ROUND(100*(I9-H9)/(J9-H9),2) < 0, 0, ROUND(100*(I9-H9)/(J9-H9),2)) -> 0
A11: B2 - Customers
A12: B 2.1 | B12: 1 | C12: M | D12: 0 | E12: 3 | F12: ID.AM-6 | G12: =IF(B12=1,F12,"") -> ID.AM-6 | H12: =VLOOKUP(E12,'_Score matrix'!$B$31:$C$35,2,FALSE) -> 1 | I12: =D12*H12 -> 0 | J12: =5*H12 -> 5
A13: B 2.2 | L13: not used in calculations, but to determine 2.1
A14: B 2.2.1 | D14: 1
A15: B 2.2.2 | D15: 1
A16: B 2.2.3 | D16: 1
A17: B 2.2.4 | D17: 1
A18: B 2.2.5 | D18: 1
A19: B 2.2.6 | D19: 1
A20: B 2.2.7 | D20: 1
A21: B 2.2.8
A22: B 2.3 | B22: 1 | C22: M | D22: 0 | E22: 3 | F22: ID.AM-6 | G22: =IF(B22=1,F22,"") -> ID.AM-6 | H22: =VLOOKUP(E22,'_Score matrix'!$B$31:$C$35,2,FALSE) -> 1 | I22: =D22*H22 -> 0 | J22: =5*H22 -> 5
A23: B 2.4 | B23: 1 | C23: M | D23: 0 | E23: 3 | F23: ID.AM-6 | G23: =IF(B23=1,F23,"") -> ID.AM-6 | H23: =VLOOKUP(E23,'_Score matrix'!$B$31:$C$35,2,FALSE) -> 1 | I23: =D23*H23 -> 0 | J23: =5*H23 -> 5
A24: B 2.5 | B24: 1 | C24: M | D24: 0 | E24: 3 | F24: ID.AM-6 | G24: =IF(B24=1,F24,"") -> ID.AM-6 | H24: =VLOOKUP(E24,'_Score matrix'!$B$31:$C$35,2,FALSE) -> 1 | I24: =D24*H24 -> 0 | J24: =5*H24 -> 5
A25: B 2.6 | B25: 1 | C25: M | D25: 0 | E25: 3 | F25: ID.AM-6 | G25: =IF(B25=1,F25,"") -> ID.AM-6 | H25: =VLOOKUP(E25,'_Score matrix'!$B$31:$C$35,2,FALSE) -> 1 | I25: =D25*H25 -> 0 | J25: =5*H25 -> 5
A26: B 2.7 | B26: 1 | C26: M | D26: 0 | E26: 3 | F26: ID.AM-6 | G26: =IF(B26=1,F26,"") -> ID.AM-6 | H26: =VLOOKUP(E26,'_Score matrix'!$B$31:$C$35,2,FALSE) -> 1 | I26: =D26*H26 -> 0 | J26: =5*H26 -> 5
A27: SUM | D27: =SUMIFS(D:D,$A:$A,"B 2*",$B:$B,1,$C:$C,"M",$L:$L,"<>NIST MAPPING") -> 0 | E27: =SUMIFS(E:E,$A:$A,"B 2*",$B:$B,1,$C:$C,"M",$L:$L,"<>NIST MAPPING") -> 18 | F27: =SUMIFS(F:F,$A:$A,"B 2*",$B:$B,1,$C:$C,"M",$L:$L,"<>NIST MAPPING") -> 0 | G27: =SUMIFS(G:G,$A:$A,"B 2*",$B:$B,1,$C:$C,"M",$L:$L,"<>NIST MAPPING") -> 0 | H27: =SUMIFS(H:H,$A:$A,"B 2*",$B:$B,1,$C:$C,"M",$L:$L,"<>NIST MAPPING") -> 6 | I27: =SUMIFS(I:I,$A:$A,"B 2*",$B:$B,1,$C:$C,"M",$L:$L,"<>NIST MAPPING") -> 0 | J27: =SUMIFS(J:J,$A:$A,"B 2*",$B:$B,1,$C:$C,"M",$L:$L,"<>NIST MAPPING") -> 30 | K27: =IF(ROUND(100*(I27-H27)/(J27-H27),2) < 0, 0, ROUND(100*(I27-H27)/(J27-H27),2)) -> 0
A29: B3 - SOC Charter
A30: B 3.1 | B30: 1 | C30: M | D30: 0 | E30: 3 | F30: ID.BE-3 | G30: =IF(B30=1,F30,"") -> ID.BE-3 | H30: =VLOOKUP(E30,'_Score matrix'!$B$31:$C$35,2,FALSE) -> 1 | I30: =D30*H30 -> 0 | J30: =5*H30 -> 5
A31: B 3.2 | D31: ='Business - CHT'!L23 -> Incomplete | L31: not used in calculations, but to determine 3.1
A32: B 3.2.1 | D32: 1
A33: B 3.2.2 | D33: 1
A34: B 3.2.3 | D34: 1
A35: B 3.2.4 | D35: 1
A36: B 3.2.5 | D36: 1
A37: B 3.2.6 | D37: 1
A38: B 3.2.7 | D38: 1
A39: B 3.2.8 | D39: 1
A40: B 3.2.9 | D40: 1
A41: B 3.2.10 | D41: 1
A42: B 3.2.11 | D42: 1
A43: B 3.3 | B43: 1 | C43: M | D43: 0 | E43: 3 | F43: ID.BE-3 | G43: =IF(B43=1,F43,"") -> ID.BE-3 | H43: =VLOOKUP(E43,'_Score matrix'!$B$31:$C$35,2,FALSE) -> 1 | I43: =D43*H43 -> 0 | J43: =5*H43 -> 5
A44: B 3.4 | B44: 1 | C44: M | D44: 0 | E44: 3 | F44: ID.BE-3 | G44: =IF(B44=1,F44,"") -> ID.BE-3 | H44: =VLOOKUP(E44,'_Score matrix'!$B$31:$C$35,2,FALSE) -> 1 | I44: =D44*H44 -> 0 | J44: =5*H44 -> 5
A45: B 3.5 | B45: 1 | C45: M | D45: 0 | E45: 3 | F45: ID.BE-3 | G45: =IF(B45=1,F45,"") -> ID.BE-3 | H45: =VLOOKUP(E45,'_Score matrix'!$B$31:$C$35,2,FALSE) -> 1 | I45: =D45*H45 -> 0 | J45: =5*H45 -> 5
A46: SUM | D46: =SUMIFS(D:D,$A:$A,"B 3*",$B:$B,1,$C:$C,"M",$L:$L,"<>NIST MAPPING") -> 0 | E46: =SUMIFS(E:E,$A:$A,"B 3*",$B:$B,1,$C:$C,"M",$L:$L,"<>NIST MAPPING") -> 12 | F46: =SUMIFS(F:F,$A:$A,"B 3*",$B:$B,1,$C:$C,"M",$L:$L,"<>NIST MAPPING") -> 0 | G46: =SUMIFS(G:G,$A:$A,"B 3*",$B:$B,1,$C:$C,"M",$L:$L,"<>NIST MAPPING") -> 0 | H46: =SUMIFS(H:H,$A:$A,"B 3*",$B:$B,1,$C:$C,"M",$L:$L,"<>NIST MAPPING") -> 4 | I46: =SUMIFS(I:I,$A:$A,"B 3*",$B:$B,1,$C:$C,"M",$L:$L,"<>NIST MAPPING") -> 0 | J46: =SUMIFS(J:J,$A:$A,"B 3*",$B:$B,1,$C:$C,"M",$L:$L,"<>NIST MAPPING") -> 20 | K46: =IF(ROUND(100*(I46-H46)/(J46-H46),2) < 0, 0, ROUND(100*(I46-H46)/(J46-H46),2)) -> 0
A48: B4 - Governance
A49: B 4.1 | B49: 1 | C49: M | D49: 0 | E49: 3 | F49: ID.GV-3 | G49: =IF(B49=1,F49,"") -> ID.GV-3 | H49: =VLOOKUP(E49,'_Score matrix'!$B$31:$C$35,2,FALSE) -> 1 | I49: =D49*H49 -> 0 | J49: =5*H49 -> 5
A50: B 4.2 | B50: 1 | C50: M | D50: 0 | E50: 3 | F50: ID.GV-1 | G50: =IF(B50=1,F50,"") -> ID.GV-1 | H50: =VLOOKUP(E50,'_Score matrix'!$B$31:$C$35,2,FALSE) -> 1 | I50: =D50*H50 -> 0 | J50: =5*H50 -> 5
A51: B 4.3 | D51: ='Business - GOV'!L27 -> Fully complete | L51: not used in calculations, but to determine 4.2
A52: B 4.3.1 | D52: 2
A53: B 4.3.2 | D53: 2
A54: B 4.3.3 | D54: 2
A55: B 4.3.4 | D55: 2
A56: B 4.3.5 | D56: 2
A57: B 4.3.6 | D57: 2
A58: B 4.3.7 | D58: 2
A59: B 4.3.8 | D59: 2
A60: B 4.3.9 | D60: 2
A61: B 4.3.10 | D61: 2
A62: B 4.3.11 | D62: 2
A63: B 4.3.12 | D63: 2
... A65: B 4.3.14 | D65: 2
A66: B 4.4 | B66: 1 | C66: M | D66: 0 | E66: 3 | H66: =VLOOKUP(E66,'_Score matrix'!$B$31:$C$35,2,FALSE) -> 1 | I66: =D66*H66 -> 0 | J66: =5*H66 -> 5
A67: B 4.5 | D67: ='Business - GOV'!L38 -> Incomplete
A68: B 4.5.1 | D68: 1
A69: B 4.5.2 | D69: 1
A70: B 4.5.3 | D70: 1
A71: B 4.5.4 | D71: 1
A72: B 4.5.5 | D72: 1
A73: B 4.5.6 | D73: 1
A74: B 4.5.7 | D74: 1
A75: B 4.5.8 | D75: 1
A76: B 4.8 | B76: 1 | C76: M | D76: 0 | E76: 3 | F76: ID.GV-1 | G76: =IF(B76=1,F76,"") -> ID.GV-1 | H76: =VLOOKUP(E76,'_Score matrix'!$B$31:$C$35,2,FALSE) -> 1 | I76: =D76*H76 -> 0 | J76: =5*H76 -> 5
A77: B 4.9 | B77: 1 | C77: M | D77: 0 | E77: 3 | F77: ID.GV-3 | G77: =IF(B77=1,F77,"") -> ID.GV-3 | H77: =VLOOKUP(E77,'_Score matrix'!$B$31:$C$35,2,FALSE) -> 1 | I77: =D77*H77 -> 0 | J77: =5*H77 -> 5
A78: B 4.10 | B78: 1 | C78: M | D78: 0 | E78: 3 | F78: ID.GV-2 | G78: =IF(B78=1,F78,"") -> ID.GV-2 | H78: =VLOOKUP(E78,'_Score matrix'!$B$31:$C$35,2,FALSE) -> 1 | I78: =D78*H78 -> 0 | J78: =5*H78 -> 5
A79: B 4.11 | B79: 1 | C79: M | D79: 0 | E79: 3 | F79: ID.GV-4 | G79: =IF(B79=1,F79,"") -> ID.GV-4 | H79: =VLOOKUP(E79,'_Score matrix'!$B$31:$C$35,2,FALSE) -> 1 | I79: =D79*H79 -> 0 | J79: =5*H79 -> 5
A80: Maturity SUM | D80: =SUMIFS(D:D,$A:$A,"B 4*",$B:$B,1,$C:$C,"M",$L:$L,"<>NIST MAPPING") -> 0 | E80: =SUMIFS(E:E,$A:$A,"B 4*",$B:$B,1,$C:$C,"M",$L:$L,"<>NIST MAPPING") -> 27 | F80: =SUMIFS(F:F,$A:$A,"B 4*",$B:$B,1,$C:$C,"M",$L:$L,"<>NIST MAPPING") -> 0 | G80: =SUMIFS(G:G,$A:$A,"B 4*",$B:$B,1,$C:$C,"M",$L:$L,"<>NIST MAPPING") -> 0 | H80: =SUMIFS(H:H,$A:$A,"B 4*",$B:$B,1,$C:$C,"M",$L:$L,"<>NIST MAPPING") -> 9 | I80: =SUMIFS(I:I,$A:$A,"B 4*",$B:$B,1,$C:$C,"M",$L:$L,"<>NIST MAPPING") -> 0 | J80: =SUMIFS(J:J,$A:$A,"B 4*",$B:$B,1,$C:$C,"M",$L:$L,"<>NIST MAPPING") -> 45 | K80: =IF(ROUND(100*(I80-H80)/(J80-H80),2) < 0, 0, ROUND(100*(I80-H80)/(J80-H80),2)) -> 0
A82: B5 - Privacy & Policy
A83: B 5.6 | B83: 1 | C83: M | D83: 0 | E83: 3 | F83: ID.GV-3 | G83: =IF(B83=1,F83,"") -> ID.GV-3 | H83: =VLOOKUP(E83,'_Score matrix'!$B$31:$C$35,2,FALSE) -> 1 | I83: =D83*H83 -> 0 | J83: =5*H83 -> 5
A84: B 5.7 | B84: 1 | C84: M | D84: 0 | E84: 3 | F84: ID.GV-3 | G84: =IF(B84=1,F84,"") -> ID.GV-3 | H84: =VLOOKUP(E84,'_Score matrix'!$B$31:$C$35,2,FALSE) -> 1 | I84: =D84*H84 -> 0 | J84: =5*H84 -> 5
A85: =A84 -> B 5.7 | B85: =B84 -> 1 | C85: =C84 -> M | D85: =D84 -> 0 | E85: =E84 -> 3 | F85: PR.IP-6 | G85: =IF(B85=1,F85,"") -> PR.IP-6 | H85: =H84 -> 1 | I85: =I84 -> 0 | J85: =J84 -> 5 | L85: NIST MAPPING
A86: =A85 -> B 5.7 | B86: =B85 -> 1 | C86: =C85 -> M | D86: =D85 -> 0 | E86: =E85 -> 3 | F86: PR.DS-5 | G86: =IF(B86=1,F86,"") -> PR.DS-5 | H86: =H85 -> 1 | I86: =I85 -> 0 | J86: =J85 -> 5 | L86: NIST MAPPING
A87: B 5.8 | B87: 1 | C87: M | D87: 0 | E87: 3 | F87: ID.GV-3 | G87: =IF(B87=1,F87,"") -> ID.GV-3 | H87: =VLOOKUP(E87,'_Score matrix'!$B$31:$C$35,2,FALSE) -> 1 | I87: =D87*H87 -> 0 | J87: =5*H87 -> 5
A88: B 5.9 | B88: 1 | C88: M | D88: 0 | E88: 3 | F88: ID.GV-3 | G88: =IF(B88=1,F88,"") -> ID.GV-3 | H88: =VLOOKUP(E88,'_Score matrix'!$B$31:$C$35,2,FALSE) -> 1 | I88: =D88*H88 -> 0 | J88: =5*H88 -> 5
A89: B 5.10 | B89: 1 | C89: M | D89: 0 | E89: 3 | F89: ID.GV-3 | G89: =IF(B89=1,F89,"") -> ID.GV-3 | H89: =VLOOKUP(E89,'_Score matrix'!$B$31:$C$35,2,FALSE) -> 1 | I89: =D89*H89 -> 0 | J89: =5*H89 -> 5
A90: B 5.11 | B90: 1 | C90: M | D90: 0 | E90: 3 | F90: ID.GV-3 | G90: =IF(B90=1,F90,"") -> ID.GV-3 | H90: =VLOOKUP(E90,'_Score matrix'!$B$31:$C$35,2,FALSE) -> 1 | I90: =D90*H90 -> 0 | J90: =5*H90 -> 5
A91: Maturity SUM | D91: =SUMIFS(D:D,$A:$A,"B 5*",$B:$B,1,$C:$C,"M",$L:$L,"<>NIST MAPPING") -> 0 | E91: =SUMIFS(E:E,$A:$A,"B 5*",$B:$B,1,$C:$C,"M",$L:$L,"<>NIST MAPPING") -> 30 | F91: =SUMIFS(F:F,$A:$A,"B 5*",$B:$B,1,$C:$C,"M",$L:$L,"<>NIST MAPPING") -> 0 | G91: =SUMIFS(G:G,$A:$A,"B 5*",$B:$B,1,$C:$C,"M",$L:$L,"<>NIST MAPPING") -> 0 | H91: =SUMIFS(H:H,$A:$A,"B 5*",$B:$B,1,$C:$C,"M",$L:$L,"<>NIST MAPPING") -> 10 | I91: =SUMIFS(I:I,$A:$A,"B 5*",$B:$B,1,$C:$C,"M",$L:$L,"<>NIST MAPPING") -> 0 | J91: =SUMIFS(J:J,$A:$A,"B 5*",$B:$B,1,$C:$C,"M",$L:$L,"<>NIST MAPPING") -> 50 | K91: =IF(ROUND(100*(I91-H91)/(J91-H91),2) < 0, 0, ROUND(100*(I91-H91)/(J91-H91),2)) -> 0
A93: SOC-CMM - People Domain
A94: P1 - SOC Employees
A95: P 1.1 | D95: ='People - EMP'!L10 -> 0
A96: P 1.2 | D96: 1
A97: P 1.2.1 | D97: 0
A98: P 1.3 | B98: 1 | C98: M | D98: 0 | E98: 3 | H98: =VLOOKUP(E98,'_Score matrix'!$B$31:$C$35,2,FALSE) -> 1 | I98: =D98*H98 -> 0 | J98: =5*H98 -> 5
A99: P 1.4 | B99: 1 | C99: M | D99: 0 | E99: 3 | H99: =VLOOKUP(E99,'_Score matrix'!$B$31:$C$35,2,FALSE) -> 1 | I99: =D99*H99 -> 0 | J99: =5*H99 -> 5
A100: P 1.5 | B100: 1 | C100: M | D100: 0 | E100: 3 | H100: =VLOOKUP(E100,'_Score matrix'!$B$31:$C$35,2,FALSE) -> 1 | I100: =D100*H100 -> 0 | J100: =5*H100 -> 5
A101: P 1.6 | B101: 1 | C101: M | D101: 0 | E101: 3 | H101: =VLOOKUP(E101,'_Score matrix'!$B$31:$C$35,2,FALSE) -> 1 | I101: =D101*H101 -> 0 | J101: =5*H101 -> 5
A102: P 1.7 | B102: 1 | C102: M | D102: 0 | E102: 3 | H102: =VLOOKUP(E102,'_Score matrix'!$B$31:$C$35,2,FALSE) -> 1 | I102: =D102*H102 -> 0 | J102: =5*H102 -> 5
A103: P 1.8 | B103: 1 | C103: M | D103: 0 | E103: 3 | H103: =VLOOKUP(E103,'_Score matrix'!$B$31:$C$35,2,FALSE) -> 1 | I103: =D103*H103 -> 0 | J103: =5*H103 -> 5
A104: Maturity SUM | D104: =SUMIFS(D:D,$A:$A,"P 1*",$B:$B,1,$C:$C,"M",$L:$L,"<>NIST MAPPING") -> 0 | E104: =SUMIFS(E:E,$A:$A,"P 1*",$B:$B,1,$C:$C,"M",$L:$L,"<>NIST MAPPING") -> 24 | F104: =SUMIFS(F:F,$A:$A,"P 1*",$B:$B,1,$C:$C,"M",$L:$L,"<>NIST MAPPING") -> 0 | G104: =SUMIFS(G:G,$A:$A,"P 1*",$B:$B,1,$C:$C,"M",$L:$L,"<>NIST MAPPING") -> 0 | H104: =SUMIFS(H:H,$A:$A,"P 1*",$B:$B,1,$C:$C,"M",$L:$L,"<>NIST MAPPING") -> 8 | I104: =SUMIFS(I:I,$A:$A,"P 1*",$B:$B,1,$C:$C,"M",$L:$L,"<>NIST MAPPING") -> 0 | J104: =SUMIFS(J:J,$A:$A,"P 1*",$B:$B,1,$C:$C,"M",$L:$L,"<>NIST MAPPING") -> 40 | K104: =IF(ROUND(100*(I104-H104)/(J104-H104),2) < 0, 0, ROUND(100*(I104-H104)/(J104-H104),2)) -> 0
A106: P2 - SOC Roles and Hierarchy
A107: P 2.1 | B107: 1 | C107: M | D107: 0 | E107: 3 | F107: ID.AM-6 | G107: =IF(B107=1,F107,"") -> ID.AM-6 | H107: =VLOOKUP(E107,'_Score matrix'!$B$31:$C$35,2,FALSE) -> 1 | I107: =D107*H107 -> 0 | J107: =5*H107 -> 5
...

Sheet Index
B1: Index
B3: Index
B9: Click on any section name to proceed directly to that part of the assessment
B10: Domain | D10: Section | I10: Questions remaining
B11: Introduction | D11: 1. Introduction | I11: N/A
D12: 2. Usage | I12: N/A
D13: 3. Change notes | J13: N/A
I14: Questions remaining
B15: General | D15: 1. Profile | I15: N/A
D16: 2. Scope | I16: N/A
I17: Questions remaining
B18: Business | D18: 1. Business drivers | I18: =CONCATENATE(COUNTIFS(_Output!A:A,"B 1*",_Output!B:B,1,_Output!L:L,"<>NIST MAPPING",_Output!D:D, 0,_Output!E:E, ">1"),"/", COUNTIFS(_Output!A:A,"B 1*",_Output!B:B,1,_Output!L:L,"<>NIST MAPPING",_Output!E:E, ">1")) -> 5/5
D19: 2. Customers | I19: =CONCATENATE(COUNTIFS(_Output!A:A,"B 2*",_Output!B:B,1,_Output!L:L,"<>NIST MAPPING",_Output!D:D, 0,_Output!E:E, ">1"),"/",COUNTIFS(_Output!A:A,"B 2*",_Output!B:B,1,_Output!L:L,"<>NIST MAPPING",_Output!E:E, ">1")) -> 6/6
D20: 3. Charter | I20: =CONCATENATE(COUNTIFS(_Output!A:A,"B 3*",_Output!B:B,1,_Output!L:L,"<>NIST MAPPING",_Output!D:D, 0,_Output!E:E, ">1"),"/", COUNTIFS(_Output!A:A,"B 3*",_Output!B:B,1,_Output!L:L,"<>NIST MAPPING",_Output!E:E, ">1")) -> 4/4
D21: 4. Governance | I21: =CONCATENATE(COUNTIFS(_Output!A:A,"B 4*",_Output!B:B,1,_Output!L:L,"<>NIST MAPPING",_Output!D:D, 0,_Output!E:E, ">1"),"/",COUNTIFS(_Output!A:A,"B 4*",_Output!B:B,1,_Output!L:L,"<>NIST MAPPING",_Output!E:E, ">1")) -> 9/9
D22: 5. Privacy & Policy | I22: =CONCATENATE(COUNTIFS(_Output!A:A,"B 5*",_Output!B:B,1,_Output!L:L,"<>NIST MAPPING",_Output!D:D, 0,_Output!E:E, ">1"),"/",COUNTIFS(_Output!A:A,"B 5*",_Output!B:B,1,_Output!L:L,"<>NIST MAPPING",_Output!E:E, ">1")) -> 10/10
I23: Questions remaining
B24: People | D24: 1. Employees | I24: =CONCATENATE(COUNTIFS(_Output!A:A,"P 1*",_Output!B:B,1,_Output!L:L,"<>NIST MAPPING",_Output!D:D, 0,_Output!E:E, ">1"),"/",COUNTIFS(_Output!A:A,"P 1*",_Output!B:B,1,_Output!L:L,"<>NIST MAPPING",_Output!E:E, ">1")) -> 8/8
D25: 2. Roles and Hierarchy | I25: =CONCATENATE(COUNTIFS(_Output!A:A,"P 2*",_Output!B:B,1,_Output!L:L,"<>NIST MAPPING",_Output!D:D, 0,_Output!E:E, ">1"),"/",COUNTIFS(_Output!A:A,"P 2*",_Output!B:B,1,_Output!L:L,"<>NIST MAPPING",_Output!E:E, ">1")) -> 8/8
D26: 3. People Management | I26: =CONCATENATE(COUNTIFS(_Output!A:A,"P 3*",_Output!B:B,1,_Output!L:L,"<>NIST MAPPING",_Output!D:D, 0,_Output!E:E, ">1"),"/",COUNTIFS(_Output!A:A,"P 3*",_Output!B:B,1,_Output!L:L,"<>NIST MAPPING",_Output!E:E, ">1")) -> 14/14
D27: 4. Knowledge Management | I27: =CONCATENATE(COUNTIFS(_Output!A:A,"P 4*",_Output!B:B,1,_Output!L:L,"<>NIST MAPPING",_Output!D:D, 0,_Output!E:E, ">1"),"/",COUNTIFS(_Output!A:A,"P 4*",_Output!B:B,1,_Output!L:L,"<>NIST MAPPING",_Output!E:E, ">1")) -> 8/8
D28: 5. Training & Education | I28: =CONCATENATE(COUNTIFS(_Output!A:A,"P 5*",_Output!B:B,1,_Output!L:L,"<>NIST MAPPING",_Output!D:D, 0,_Output!E:E, ">1"),"/",COUNTIFS(_Output!A:A,"P 5*",_Output!B:B,1,_Output!L:L,"<>NIST MAPPING",_Output!E:E, ">1")) -> 7/7
I29: Questions remaining
B30: Process | D30: 1. SOC Management | I30: =CONCATENATE(COUNTIFS(_Output!A:A,"M 1*",_Output!B:B,1,_Output!L:L,"<>NIST MAPPING",_Output!D:D, 0,_Output!E:E, ">1"),"/",COUNTIFS(_Output!A:A,"M 1*",_Output!B:B,1,_Output!L:L,"<>NIST MAPPING",_Output!E:E, ">1")) -> 9/9
D31: 2. Operations and Facilities | I31: =CONCATENATE(COUNTIFS(_Output!A:A,"M 2*",_Output!B:B,1,_Output!L:L,"<>NIST MAPPING",_Output!D:D, 0,_Output!E:E, ">1"),"/",COUNTIFS(_Output!A:A,"M 2*",_Output!B:B,1,_Output!L:L,"<>NIST MAPPING",_Output!E:E, ">1")) -> 31/31
D32: 3. Reporting & Communication | I32: =CONCATENATE(COUNTIFS(_Output!A:A,"M 3*",_Output!B:B,1,_Output!L:L,"<>NIST MAPPING",_Output!D:D, 0,_Output!E:E, ">1"),"/", COUNTIFS(_Output!A:A,"M 3*",_Output!B:B,1,_Output!L:L,"<>NIST MAPPING",_Output!E:E, ">1")) -> 17/17
D33: 4. Use Case Management | I33: =CONCATENATE(COUNTIFS(_Output!A:A,"M 4*",_Output!B:B,1,_Output!L:L,"<>NIST MAPPING",_Output!D:D, 0,_Output!E:E, ">1"),"/",COUNTIFS(_Output!A:A,"M 4*",_Output!B:B,1,_Output!L:L,"<>NIST MAPPING",_Output!E:E, ">1")) -> 20/20
D34: 5. Detection Engineering & Validation | I34: =CONCATENATE(COUNTIFS(_Output!A:A,"M 5*",_Output!B:B,1,_Output!L:L,"<>NIST MAPPING",_Output!D:D, 0, _Output!E:E, ">1"),"/",COUNTIFS(_Output!A:A,"M 5*",_Output!B:B,1,_Output!L:L,"<>NIST MAPPING", _Output!E:E, ">1")) -> 18/18
I35: Questions remaining
B36: Technology | D36: 1. SIEM / UEBA | I36: =CONCATENATE(COUNTIFS(_Output!A:A,"T 1*",_Output!B:B,1,_Output!L:L,"<>NIST MAPPING",_Output!D:D, 0, _Output!E:E, ">1"),"/",COUNTIFS(_Output!A:A,"T 1*",_Output!B:B,1,_Output!L:L,"<>NIST MAPPING", _Output!E:E, ">1")) -> 60/60
D37: 2. NDR | I37: =CONCATENATE(COUNTIFS(_Output!A:A,"T 2*",_Output!B:B,1,_Output!L:L,"<>NIST MAPPING",_Output!D:D, 0, _Output!E:E, ">1"),"/",COUNTIFS(_Output!A:A,"T 2*",_Output!B:B,1,_Output!L:L,"<>NIST MAPPING",_Output!E:E, ">1")) -> 56/56
D38: 3. EDR | I38: =CONCATENATE(COUNTIFS(_Output!A:A,"T 3*",_Output!B:B,1,_Output!L:L,"<>NIST MAPPING",_Output!D:D, 0, _Output!E:E, ">1"),"/",COUNTIFS(_Output!A:A,"T 3*",_Output!B:B,1,_Output!L:L,"<>NIST MAPPING", _Output!E:E, ">1")) -> 72/72
D39: 4. SOAR | I39: =CONCATENATE(COUNTIFS(_Output!A:A,"T 4*",_Output!B:B,1,_Output!L:L,"<>NIST MAPPING",_Output!D:D, 0,_Output!E:E, ">1"),"/",COUNTIFS(_Output!A:A,"T 4*",_Output!B:B,1,_Output!L:L,"<>NIST MAPPING",_Output!E:E, ">1")) -> 46/46
I40: Questions remaining
B41: Services | D41: 1. Security Monitoring | I41: =CONCATENATE(COUNTIFS(_Output!A:A,"S 1*",_Output!B:B,1,_Output!L:L,"<>NIST MAPPING",_Output!D:D, 0, _Output!E:E, ">1"),"/",COUNTIFS(_Output!A:A,"S 1*",_Output!B:B,1,_Output!L:L,"<>NIST MAPPING",_Output!E:E, ">1")) -> 40/40
D42: 2. Security Incident Management | I42: =CONCATENATE(COUNTIFS(_Output!A:A,"S 2*",_Output!B:B,1,_Output!L:L,"<>NIST MAPPING",_Output!D:D, 0, _Output!E:E, ">1"),"/",COUNTIFS(_Output!A:A,"S 2*",_Output!B:B,1,_Output!L:L,"<>NIST MAPPING", _Output!E:E, ">1")) -> 49/49
D43: 3. Security Analysis and Forensics | I43: =CONCATENATE(COUNTIFS(_Output!A:A,"S 3*",_Output!B:B,1,_Output!L:L,"<>NIST MAPPING",_Output!D:D, 0, _Output!E:E, ">1"),"/",COUNTIFS(_Output!A:A,"S 3*",_Output!B:B,1,_Output!L:L,"<>NIST MAPPING", _Output!E:E, ">1")) -> 38/38
D44: 4. Threat Intelligence | I44: =CONCATENATE(COUNTIFS(_Output!A:A,"S 4*",_Output!B:B,1,_Output!L:L,"<>NIST MAPPING",_Output!D:D, 0, _Output!E:E, ">1"),"/",COUNTIFS(_Output!A:A,"S 4*",_Output!B:B,1,_Output!L:L,"<>NIST MAPPING", _Output!E:E, ">1")) -> 44/44
D45: 5. Threat Hunting | I45: =CONCATENATE(COUNTIFS(_Output!A:A,"S 5*",_Output!B:B,1,_Output!L:L,"<>NIST MAPPING",_Output!D:D, 0, _Output!E:E, ">1"),"/",COUNTIFS(_Output!A:A,"S 5*",_Output!B:B,1,_Output!L:L,"<>NIST MAPPING",_Output!E:E, ">1")) -> 35/35
D46: 6. Vulnerability Management | I46: =CONCATENATE(COUNTIFS(_Output!A:A,"S 6*",_Output!B:B,1,_Output!L:L,"<>NIST MAPPING",_Output!D:D, 0, _Output!E:E, ">1"),"/",COUNTIFS(_Output!A:A,"S 6*",_Output!B:B,1,_Output!L:L,"<>NIST MAPPING", _Output!E:E, ">1")) -> 33/33
D47: 7. Log Management | I47: =CONCATENATE(COUNTIFS(_Output!A:A,"S 7*",_Output!B:B,1,_Output!L:L,"<>NIST MAPPING",_Output!D:D, 0, _Output!E:E, ">1"),"/",COUNTIFS(_Output!A:A,"S 7*",_Output!B:B,1,_Output!L:L,"<>NIST MAPPING", _Output!E:E, ">1")) -> 33/33
I48: Questions remaining
B49: Results | D49: 1. Results | I49: N/A
D50: 2. NIST CSF 1.1 Scoring | J50: N/A
I51: Questions remaining
B52: Next steps | D52: 1. Next steps | I52: N/A

Sheet Introduction - INT
B1: Introduction
B3: 1. Introduction
B4: 2. Usage
B5: 3. Change notes
B19: General information
B20: Author | G20: Rob van Os
B21: Site | G21: https://www.soc-cmm.com/
B22: Contact | G22: info@SOC-CMM.com
B23: Version | G23: 2.3.2, advanced version
B24: Date | G24: September 20, 2023
B26: Background
B27: The SOC-CMM is a capability maturity model that can be used to perform a self-assessment of your Security Operations Center (SOC). The model is based on review conducted on literature regarding SOC setup and existing SOC models as well as literature on specific elements within a SOC. The literature analysis was then validated by questioning several Security Operations Centers in different sectors and on different maturity levels to determine which elements were actually in place. The output from the survey, combined with the initial analysis is the basis for this self-assessment. For more information regarding the scientific background and the literature used to create the SOC-CMM self-assessment tool, please refer to the thesis document as available through: https://www.soc-cmm.com/ If you have any questions or comments regarding the contents of this document, please use the above information to contact me. There is also a SOC-CMM community where you can post your questions or suggestions for improvement or extension of the SOC-CMM.
B36: Purpose and intended audience
B37: The purpose of the SOC-CMM is to gain insight into the strengths and weaknesses of the SOC. This enables the SOC management to make informed decisions about which elements of the SOC require additional attention and/or budget. By regularly assessing the SOC for maturity and capability, progress can be monitored. Besides the primary purpose of performing an assessment of the SOC, the assessment can also be used for extensive discussions about the SOC and can thus provide valuable insights. This tool is intended for use by SOC and security managers, experts within the SOC and SOC consultants.
B44: Navigation
B45: Navigation through this tool is done using the navigation bar at the top of each page. Each of the numbered sections can be clicked to proceed directly to that section. Furthermore, the icons can be used to navigate through sections within a domain and between domains. The icons are as follows:
C47: navigate to previous domain | H47: navigate to previous section within the domain
C49: navigate to index | H49: navigate to next section within the domain
C51: navigate to next domain | H51: navigate directly to results
B53: Assessment Model
B54: The assessment model consists of 5 domains and 25 aspects. All domains are evaluated for maturity (blue), only technology and services are evaluated for both maturity and capability (purple)
B74: Maturity Levels
B75: CMMI defines maturity as a means for an organization "to characterize its performance" for a specific entity (here: the SOC). The SOC-CMM calculates a maturity score using 6 maturity levels: - Level 0: non-existent - Level 1: initial - Level 2: managed - Level 3: defined - Level 4: quantitatively managed - Level 5: optimizing These maturity levels are measured across 5 domains: business, people, process, technology and services. The maturity levels as implemented in this tool are not staged with pre-requisites for each level. Instead, every element adds individually to the maturity score: a continuous maturity model.
B84: Capability Levels
B85: Capabilities are indicators of completeness. In essence, capabilities can support maturity. The SOC-CMM calculates a capability score using 4 capability levels, similar to CMMi: - Level 0: incomplete - Level 1: performed - Level 2: managed - Level 3: defined These capability levels have a strong technical focus and are measured across 2 domains: technology and services. Similar to maturity levels, progress to a higher capability level is continuous. There are no prerequisites for advancing to a higher level, thus the capability growth is continuous as well.
B93: Disclaimer
B94: The SOC-CMM is provided without warranty of any kind. The author of the document cannot assure its accuracy and is not liable for any cost as a result of decisions based on the output of this tool. The usage of this tool does not in any way entitle the user to support or consultancy. By using this tool, you agree to these conditions.
B97: License
B98: Copyright (C) 2021 - SOC-CMM The SOC-CMM advanced version is part of the SOC-CMM. The SOC-CMM is free software, released under the CC SA-BY license: https://creativecommons.org/licenses/by-sa/4.0/ You are free to: Share — copy and redistribute the material in any medium or format Adapt — remix, transform, and build upon the material for any purpose, even commercially. Under the following terms: Attribution — You must give appropriate credit, provide a link to the license, and indicate if changes were made. You may do so in any reasonable manner, but not in any way that suggests the licensor endorses you or your use. ShareAlike — If you remix, transform, or build upon the material, you must distribute your contributions under the same license as the original. No additional restrictions — You may not apply legal terms or technological measures that legally restrict others from doing anything the license permits. This license is acceptable for Free Cultural Works. The licensor cannot revoke these freedoms as long as you follow the license terms. This program is distributed in the hope that it will be useful, but WITHOUT ANY WARRANTY; without even the implied warranty of MERCHANTABILITY or FITNESS FOR A PARTICULAR PURPOSE.

Sheet Introduction - USG
B1: Introduction
B3: 1. Introduction
B4: 2. Usage
B5: 3. Change notes
B9: How to use the SOC-CMM
B10: The SOC-CMM has an embedded workflow that guides the assessment. First, the profile sheet is filled in and the scope for assessment is selected. Then, the 5 domains of the SOC-CMM (i.e. Business, People, Process, Technology and Services) are each evaluated in separate sections of this tool. The evaluation is based on questions that can be answered using a drop-down that presents a 5-point scale. This scale relates to the maturity level as explained below under 'Scoring mechanism'. This tool should be used by assessing each sheet in order. When all domains are completed, the sheet 'Results' will provide you with the total scoring and detailed scoring for each domain. A sheet 'Next steps' is also included to provide pointers for follow-up. In the advanced version only, there is also a weighing mechanism in place. For each question, the importance of that element can be changed. The standard importance is 'normal', which means that the score is not modified. Changing to importance to 'low' will cause the element to have less impact on the score. Changing it to 'High' or 'Critical' will cause the element to have more impact on the score. Setting it to 'none' will ignore the element in scoring entirely, as explained under 'Weighing mechanism'. This feature should be used with care. Some additional remarks regarding the usage of the SOC-CMM: 1. Some elements are not used directly for scoring (this is also indicated), but are a guideline for answering other questions. These elements have a lighter color. For example, question 3.1 (part of maturity score) can be answered by using the elements in 3.2 (not part of maturity score) as a guideline. 2. Elements with a green color are calculated fields. These will be filled in automatically by filling in those parts of the assessment. 3. The services and Technology domains evaluate both maturity and capability. These capabilities do not have a 5-point scale and an importance, but use a 6-point scale instead. This is to reduce the amount of clicks and answers. The sixth element in the scale is 'not required'. Use this if you do not feel like you need that particular capability and to exclude it from scoring. 4. Every sheet has a part where you can fill in some comments or remarks. Discussing the questions in this self-assessments will likely uncover some improvements. This is added value for a self-assessment, so it is worthwhile to create notes. 5. The weighing mechanisms allows for manipulation of the maturity score. Therefore, it is important to strongly consider and possibly document why you wish to deviate from the standard. The goal of the SOC-CMM is to provide insight into strengths and weaknesses and to improve the SOC, not to obtain the highest score possible. 6. The NIST score is calculated automatically as explained below 7. Performing a full SOC-CMM assessment can take a significant amount of time, depending on the level of detail you put into the assessment. Before you start, ensure that you have allocated sufficient time. A way to reduce effort is to have a single knowledgeable SOC employee perform a quick scan and subsequently focus on areas that are debatable. Also, reducing scope for an initial assessment is a way to reduce the assessment effort.
B31: Scoring mechanism
B32: Each question that is part of the maturity scoring can be answered by selecting one of 5 options. These options vary based on the type of question. For example, for questions regarding completeness, the following applies: - Incomplete, score: 0 - Partially complete, score: 1,25 - Averagely complete, score: 2,5 - Mostly complete, score: 3,75 - Fully complete, score: 5 As indicated, the score can be modified by using the weighing mechanism (use with care)
B39: Guidance
B40: For each of the maturity questions, guidance is available. When a value is selected from the dropdown box, guidance for that value is show under the guidance column. This guidance can be used to help determine the correct level. Note that this is truly meant as guidance on interpretation and scoring, not as mandatory and prescriptive.
B43: Weighing mechanism (advanced version only)
B44: The weighing mechanism in the tool works by applying a factor to the element score as follows: - Importance 'None', factor = 0 (not included in scoring) - Importance 'Low', factor = 0.5 (score divided by 2) - Importance 'Normal', factor = 1 (score not affected) - Importance 'High', factor = 2 (score doubled) - Importance 'Critical', factor = 4 (score quadrupled)
... B53: The SOC-CMM is built using standard Excel features without macros. The sheets are not locked or password protected. Therefore, adding colums and rows and applying other changes such as changing guidance or adding elements is possible. To show columns and rows, go to 'View' --> 'Show' and check 'Headings'. To show all the tabs underlying the SOC-CMM, go top 'File' --> 'Options' --> 'Advanced' --> 'Display options' and check 'Show sheet tabs'. Customizing calculations will require understanding of the calculations done in the '_Output' sheet. However, guidance for this type of customization is not provided, as it requires an understanding of the way the SOC-CMM sheets are connected.

Sheet Introduction - CHG
B1: Introduction
B3: 1. Introduction | G3: Version 2.3
B4: 2. Usage | G4: Version 2.2
B5: 3. Change notes
B9: Version 2.3 (scroll down or click top links for previous versions)
B11: Business domain:
C12: Governance
D13: 4.3.13: included SOC risk management into governance elements
D14: 4.7: Added question on governance meetings
D15: 4.7 - 4.10: renumbered to 4.8 - 4.11
C16: Privacy & Policy:
D17: 5.2: SOC policy added as a new question, 5.3 outlines the elements in the policy
D18: 5.4 - 5.11: renumbered from 5.2 - 5.9
B19: People domain:
C20: Roles & hierarchy
D21: 2.2.3: changed security specialist to forensic analyst
D22: 2.2.12: added detection engineer
D23: 2.2.13: added automation engineer
C25: Knowledge management:
D26: Skill matrix questions aggregated into two questions
D27: Knowledge matrix questions aggregated into two questions
D28: Renumbering applied to section
B30: Process domain:
C31: SOC management:
D32: 1.2: guidance updated for this question
D33: 1.6: added a question on continuous improvement
D34: 1.7: added a question on quality assurance
D35: 1.8: added 3 questions on SOC architecture
C37: Operations and facilities:
D38: 2.1: security operations exercises turned into a separate section, additional questions inserted
D39: 2.1.1: renumbered to 2.1.3
D40: 2.1.2 - 2.5.2: renumbered to 2.2.1 - 2.6.2
C42: Reporting & Communication
D43: Report types aggregated into a single question
D44: Metrics types aggregated into a single question
D45: 3.9 - 3.12: renumbered to 3.11 - 3.14
C47: Detection Engineering & Validation:
D48: 5.2.1: changed wording, guidance and remark for this question. Added some example resources
D49: 5.2.7 - 5.2.8: added questions on validation of integrity of data ingestion and log source coverage
B51: Technology domain:
C52: All technologies: confidentiality section changed to access control
C53: All technologies: break glass procedure added to access control
C54: All technologies: maintenance (x.4) updated to 'maintenance & configuration', question x.4.3 updated to reflect this change
C56: SIEM / UEBA (formerly: SIEM)
D57: Aggregated Security Analytics (v2.2) and SIEM (v2.2) capabilities into a single SIEM/UEBA technology
D58: Capabilities restructured
C60: NDR (formerly: IDPS)
D61: Completely reworked all capabilities
C63: EDR (new)
D64: New section for the SOC-CMM
C66: SOAR
D67: Capabilities restructured
D68: Capabilities from previous version renumbered and re-ordered
B70: Services domain:
C71: All services: removed CMMI level references, as they were somewhat confusing and did not add any value
C72: Security incident response
D73: 2.17.6: change questions from 'password reset procedure' to more generic 'incident containment procedures', including a reference to RE&CT framework
B75: Navigation improvements
C76: Scrolling error fixed for sheets that did not allow scrolling with the scroll wheel
C77: Clicking on SOC-CMM elements in the results section navigates directly to that section
C78: Added lines in each comments section to document the rationale for choosing a certain value
B80: Backend improvements:
C81: Index calculations improved to exclude questions with importance set to 'none' and provide a better overview of remaining questions
C82: Guidance added for new questions
C83: Generic guidance modified to better reflect capability levels
B85: Bug fixes & typos:
C86: Conditional formatting errors fixed
C87: Scrolling error fixed for sheets that did not allow scrolling with the scroll wheel
C88: Fixed guidance for several questions
C89: Fixed answer selection for several questions
C90: Fixed 'questions remaining' showing for questions set to importance 'none'
C91: Fixed calculation error for section Reporting/Communication
B93: Version 2.2
B95: Business domain:
C96: Governance
D97: question 4.10 added (external SOC cooperation)
C98: Privacy & Policy:
D99: questions 5.1, 5.2 and 5.3 added (security policy)
D100: question 5.4: additional NIST mapping applied
B101: People domain:
C102: Employees:
D103: questions 1.9 and 1.10 added (KSAOs)
C104: People management:
D105: questions 3.5 and 3.6 added, renumbering applied (team goals and tracking of goals)
D106: questions 3.13 and 3.14 added (multi-team systems and team performance)
C107: Knowledge management:
D108: question 4.4.1 added, renumbering applied (employee abilities)
B110: Process domain:
C111: Operations and facilities:
D112: question 2.1.6 added (OPSEC program)
D113: questions 2.3.2, 2.3.5, 2.3.9 added, renumbering applied (war room, physical storage, remote working)
D114: question 2.4.2 added, renumbering applied (viligance)
C115: Reporting: (changed to reporting & communication)
D116: question 3.8.6 added (proactive & reactive metrics)
D117: questions 3.10.1 and 3.10.2 added (education & awareness)
D118: question 3.11 added (communication)
C119: Use case management:
D120: question 4.1.9 (testing use cases) moved to detection engineering, renumbering applied
D121: section 4.2 added (MITRE ATT&CK®)
D122: section 4.3 added (visbility)
...

Sheet General - PRO
B1: Profile
B3: 1. Profile
B4: 2. Scope
B8: Please fill in the information below to create a short profile of the SOC and the assessment
B10: Assessment Details
B11: Date of assessment
B12: Name(s)
B16: Department(s)
B17: Intended purpose of the assessment
B21: Scope
B26: Organisation & SOC Profile
B27: Business size
... B30: Number of FTE's
B31: SOC model | K31: Follow the sun, hybrid (partially outsourced), centralized, multiple individual SOCs, multi-tiered SOC model
B32: Geographic operation | K32: Regional, National, Continental, Global
B34: Target Maturity (optional)
B35: Target maturity level business domain | G35: 3 | K35: Indicate a score from 1 to 5. Decimals can be used
B36: Target maturity level people domain | G36: 3 | K36: Indicate a score from 1 to 5. Decimals can be used
B37: Target maturity level process domain | G37: 3 | K37: Indicate a score from 1 to 5. Decimals can be used
B38: Target maturity level technology domain | G38: 3 | K38: Indicate a score from 1 to 5. Decimals can be used
B39: Target maturity level services domain | G39: 3 | K39: Indicate a score from 1 to 5. Decimals can be used
B40: Target overall maturity level | G40: =IFERROR(SUM(G35:J39)/5, 0) -> 3
B42: Target Capability (optional)
B43: Target capability level technology domain | G43: 2 | K43: Indicate a score from 1 to 3. Decimals can be used
B44: Target capability level services domain | G44: 2 | K44: Indicate a score from 1 to 3. Decimals can be used
B45: Target overall capability level | G45: =IFERROR(SUM(G43:J44)/COUNT(G43:J44), 0) -> 2
B47: Notes or comments

Sheet General - SCP
B1: Profile
B3: 1. Profile
B4: 2. Scope
B8: Please select the services and technologies that should be included into the assessment. Excluding a service or technology here will exclude it from scoring. Note: changes to these values take some time to process
B10: SOC Tooling (Technology domain) | J10: Remarks
B11: SIEM / UEBA | J11: Security Information and Event management tooling. Used to gather logging information from company assets and correlate events. Also includes User and Entity Behavior Analytics (UEBA)
B12: NDR | J12: Network security solution, used detect network exploits and anomalous network activity and perform network forensics
B13: EDR | J13: End-point security solution, used to prevent, detect en respond to threats on end-points
B14: SOAR | J14: Used to automate workflows and SOC actions, support incident response and orchestrate between different security products
B16: SOC Services (services domain) | J16: Remarks
B17: Security Monitoring | J17: The security monitoring service aims at detecting security incidents and events
B18: Security Incident Management | J18: The security incident management service aims at responding to security incidents in a timely, accurate and organized fashion
B19: Security Analysis | J19: The security analysis service supports security monitoring and security incident management. Analysis includes event analysis and forensic analysis
B20: Threat Intelligence | J20: The threat intelligence service provides information about potential threats that can be used in security monitoring, security incident response, security analysis and threat hunting
B21: Threat Hunting | J21: The hunting service takes a proactive approach to finding threats in the infrastructure. Threat intelligence is often used to guide hunting efforts
B22: Vulnerability Management | J22: The vulnerability management service is used to detect vulnerabilities in assets by discovery and actively scanning assets for known vulnerabilities
B23: Log Management | J23: The log management service is used to collect, store and retain logging. Can be used for compliance purposes as well as investigation purposes

Sheet Business - BSD
B1: Business
B3: 1. Business Drivers | G3: 5. Privacy & Policy
B4: 2. Customers
B5: 3. Charter
B6: 4. Governance
A9: 1 | B9: Business Drivers | L9: Answer | N9: Importance | P9: Guidance | Q9: Remarks
B10: 1.1 | C10: Have you identified the main business drivers? | P10: =VLOOKUP(_Output!D4,_Guidance!B4:C9,2,FALSE) | Q10: Example business drivers: cyber crime prevention, risk reduction, law / regulation, audit / compliance, business continuity
B11: 1.2 | C11: Have you documented the main business drivers? | P11: =VLOOKUP(_Output!D5,_Guidance!B10:C15,2,FALSE) | Q11: Documentation of business drivers is important for demonstrable business alignment
B12: 1.3 | C12: Do you use business drivers in the decision making process? | P12: =VLOOKUP(_Output!D6,_Guidance!B16:C21,2,FALSE) | Q12: e.g. to determine priorities or make decisions regarding the on-boarding of new services or operations
B13: 1.4 | C13: Do you regularly check if the current service catalogue is aligned with business drivers? | P13: =VLOOKUP(_Output!D7,_Guidance!B22:C27,2,FALSE) | Q13: i.e. do you check for services or operations that outside the scope of business drivers?
B14: 1.5 | C14: Have the business drivers been validated with business stakeholders? | P14: =VLOOKUP(_Output!D8,_Guidance!B28:C33,2,FALSE) | Q14: Business stakeholders can be C-level management
B16: Comments and/or Remarks
B17: 1.6 | C17: Specify rationale for chosen values or any additional comments | L17: 1.1
L18: 1.2
L19: 1.3
L20: 1.4
L21: 1.5

Sheet Business - CST
B1: Business
B3: 1. Business Drivers | G3: 5. Privacy & Policy
B4: 2. Customers
B5: 3. Charter
B6: 4. Governance
A9: 2 | B9: Customers | L9: Answer | N9: Importance | P9: Guidance | Q9: Remarks
B10: 2.1 | C10: Have you identified the SOC customers? | P10: =VLOOKUP(_Output!D12,_Guidance!B35:C40,2,FALSE) | Q10: Types of customers, customer requirements / expectations, etc.
B11: 2.2 | C11: Please specify your customers: | Q11: Use this a guideline for answering 2.1 This is also potentially useful for insights and comparison with previous assessments
B12: 2.2.1 | C12: Legal | Q12: Legal department, may be a stakeholder for privacy, or may request forensic investigation to the SOC
B13: 2.2.2 | C13: Audit | Q13: The audit department can be supported by logging provided by the SOC
B14: 2.2.3 | C14: Engineering / R&D | Q14: The engineering departments deal with Intellectual Property that may require additional access monitoring
B15: 2.2.4 | C15: IT | Q15: IT departments can be supported by monitoring for anomalies in their infrastructure and systems
B16: 2.2.5 | C16: Business | Q16: Business should be the most important customer, as all SOC activities ultimately support business processes
B17: 2.2.6 | C17: External customers | Q17: External customers mostly apply to managed service providers
B18: 2.2.7 | C18: (Senior) Management | Q18: Senior management may be a direct SOC customer, depending on organization hierarchy
B19: 2.2.8 | C19: Other customers: | Q19: Specify any additional customers
B20: 2.3 | C20: Have you documented the main SOC customers? | P20: =VLOOKUP(_Output!D22,_Guidance!B41:C46,2,FALSE) | Q20: Formal registration of customer contact details, place in the organization, geolocation, etc.
B21: 2.4 | C21: Do you differentiate output towards these specific customers? | P21: =VLOOKUP(_Output!D23,_Guidance!B47:C52,2,FALSE) | Q21: For example, are communication style and contents to Business customers different than that to IT?
B22: 2.5 | C22: Do you have service level agreements with these customers? | P22: =VLOOKUP(_Output!D24,_Guidance!B53:C58,2,FALSE) | Q22: Service level agreements are used to provide standardized services operating within known boundaries
B23: 2.6 | C23: Do you regularly send updates to your customers? | P23: =VLOOKUP(_Output!D25,_Guidance!B59:C64,2,FALSE) | Q23: For example: changes in service scope or delivery. Can also be reports, dashboards, etc.
B24: 2.7 | C24: Do you actively measure and manage customer satisfaction? | P24: =VLOOKUP(_Output!D26,_Guidance!B65:C70,2,FALSE) | Q24: Understanding customer satisfaction will help to better align with business needs
B26: Comments and/or Remarks
B27: 2.8 | C27: Specify rationale for chosen values or any additional comments | L27: 2.1
L28: 2.3
L29: 2.4
L30: 2.5
L31: 2.6
L32: 2.7

Sheet Business - CHT
B1: Business
B3: 1. Business Drivers | G3: 5. Privacy & Policy
B4: 2. Customers
B5: 3. Charter
B6: 4. Governance
A9: 3 | B9: Charter | L9: Answer | N9: Importance | P9: Guidance | Q9: Remarks
B10: 3.1 | C10: Does the SOC have a formal charter document in place? | P10: =VLOOKUP(_Output!D30,_Guidance!B72:C77,2,FALSE) | Q10: See 3.2 for charter document elements
B11: 3.2 | C11: Please specify elements of the charter document:
B12: 3.2.1 | C12: Mission | Q12: A SOC mission should be established to provide insight into the reason for existence of the SOC
B13: 3.2.2 | C13: Vision | Q13: A vision should be created to determine long-term goals for the SOC
B14: 3.2.3 | C14: Strategy | Q14: A strategy should be in place to show how to meet goals and targets set by mission and vision
B15: 3.2.4 | C15: Service Scope | Q15: Service scope is documented to provide insight into SOC service delivery
B16: 3.2.5 | C16: Deliverables | Q16: The output provided by the SOC, for example: reports, incidents, investigations, advisories, etc.
B17: 3.2.6 | C17: Responsibilities | Q17: Responsibilities of the SOC
B18: 3.2.7 | C18: Accountability | Q18: Accountability for the SOC for actions taken
B19: 3.2.8 | C19: Operational Hours | Q19: Operational hours of the SOC
B20: 3.2.9 | C20: Stakeholders | Q20: All relevant stakeholders for the SOC
B21: 3.2.10 | C21: Objectives / Goals | Q21: Objectives and goals should be concrete and measurable so that they are fit for reporting purposes
B22: 3.2.11 | C22: Statement of success | Q22: A statement of success is used to determine when the SOC is successful. Should be aligned with goals and objectives
C23: Completeness | L23: =VLOOKUP(SUM(_Output!D32:D42),_SUM_Completeness!A3:B14,2,FALSE) -> Incomplete | Q23: Use this outcome as a guideline to determine the score for 3.1
B24: 3.3 | C24: Is the SOC charter document regularly updated? | P24: =VLOOKUP(_Output!D43,_Guidance!B78:C83,2,FALSE) | Q24: Regularity should be matched to your own internal policy. At least yearly is recommended
B25: 3.4 | C25: Is the SOC charter document approved by the business / CISO? | P25: =VLOOKUP(_Output!D44,_Guidance!B84:C89,2,FALSE) | Q25: Approval from the relevant stakeholders will aid in business support for SOC operations
B26: 3.5 | C26: Are all stakeholders familiar with the SOC charter document contents? | P26: =VLOOKUP(_Output!D45,_Guidance!B90:C95,2,FALSE) | Q26: Making stakeholders aware of the contents helps in getting organizational support for security operations
B28: Comments and/or Remarks
B29: 3.6 | C29: Specify rationale for chosen values or any additional comments | L29: 3.1
L30: 3.3
L31: 3.4
L32: 3.5

Sheet Business - GOV
B1: Business
B3: 1. Business Drivers | G3: 5. Privacy & Policy
B4: 2. Customers
B5: 3. Charter
B6: 4. Governance
A9: 4 | B9: Governance | L9: Answer | N9: Importance | P9: Guidance | Q9: Remarks
B10: 4.1 | C10: Does the SOC have a governance process in place? | P10: =VLOOKUP(_Output!D49,_Guidance!B97:C102,2,FALSE) | Q10: A governance process is required to determine the way the SOC should be managed
B11: 4.2 | C11: Have all governance elements been identified? | P11: =VLOOKUP(_Output!D50,_Guidance!B103:C108,2,FALSE) | Q11: Possible governance elements can be found in under 4.3
B12: 4.3 | C12: Please specify identified governance elements
B13: 4.3.1 | C13: Business Alignment | Q13: Aligning SOC operations to business needs
B14: 4.3.2 | C14: Accountability | Q14: Note that this can be part of the SOC charter document. This does not automatically make it part of the governance process
B15: 4.3.3 | C15: Sponsorship | Q15: Can be part of stakeholder management
B16: 4.3.4 | C16: Mandate | Q16: Mandate for the SOC should be established so that the SOC can take action in crisis situations
B17: 4.3.5 | C17: Relationships & Third Party Management | Q17: Both management of internal and external relationships
B18: 4.3.6 | C18: Vendor Engagement | Q18: For example: active involvement of vendors in the creation of a vision and strategy for the SOC
B19: 4.3.7 | C19: Service Commitment | Q19: For example: service level agreements and IT controls
B20: 4.3.8 | C20: Project / Program Management | Q20: Project management for individual projects within the SOC / program management for larger transitions
B21: 4.3.9 | C21: Continual Improvement | Q21: Improvement of the SOC and of SOC management
B22: 4.3.10 | C22: Span of control / federation governance | Q22: Especially important for SOC setups where multiple SOCs exist within the same company
B23: 4.3.11 | C23: Outsourced service management | Q23: Especially important for hybrid SOC setups. When using outsourcing, SLAs and oversight should be in place
B24: 4.3.12 | C24: SOC KPIs & Metrics | Q24: These are discussed in more detail in the Process section regarding reporting
... B26: 4.3.14 | C26: Customer Engagement / Satisfaction | Q26: Are customers an integral part of your security operations? Is their satisfaction of SOC services every inquired about?
C27: Completeness | L27: =VLOOKUP(SUM(_Output!D52:D65),_SUM_Completeness!A17:B31,2,FALSE) -> Fully complete | Q27: Use this outcome as a guideline to determine the score for 4.2
B28: 4.4 | C28: Is cost management in place? | P28: =VLOOKUP(_Output!D66,_Guidance!B109:C114,2,FALSE) | Q28: Managing costs is required to justify budget allocation for the SOC and ensure continued service delivery in the future
B29: 4.5 | C29: Please specify cost management elements
B30: 4.5.1 | C30: People cost | Q30: Costs associated with employees. Should be managed to prove FTE requirements to stakeholders
B31: 4.5.2 | C31: Process cost | Q31: Cost associated with processes. Should be managed to ensure process elements can be delivered
B32: 4.5.3 | C32: Technology cost | Q32: Cost associated with technology. Should be managed to prove budget requirements for new technology or replacement
B33: 4.5.4 | C33: Services cost | Q33: Cost associated with service delivery. Especially important for managed service providers to ensure a healthy business model
B34: 4.5.5 | C34: Facility cost | Q34: Cost associated with facilities used by the SOC
B35: 4.5.6 | C35: Budget forecasting | Q35: Forecasting of required budget over time. Should be aligned with business needs; increased spending must be justified
B36: 4.5.7 | C36: Budget alignment | Q36: Alignment of budget with business requirements and drivers to ensure balanced spending on the SOC
B37: 4.5.8 | C37: Return on investment | Q37: Prove the return on investment to stakeholders to ensure continued budget allocation
C38: Completeness | L38: =VLOOKUP(SUM(_Output!D68:D75),_SUM_Completeness!A34:B42,2,FALSE) -> Incomplete | Q38: Use this outcome as a guideline to determine the score for 4.4
B39: 4.6 | C39: Are all governance elements formally documented? | P39: =VLOOKUP(_Output!D76,_Guidance!B115:C120,2,FALSE) | Q39: Formal documentation should be signed off and stored in a quality management system
B40: 4.7 | C40: Are SOC governance meetings regularly held? | P40: =VLOOKUP(_Output!D1077,_Guidance!B121:C126,2,FALSE) | Q40: SOC governance meetings at different levels (operational, tactical, strategic) should be formalised in Terms of Reference (ToR)
B41: 4.8 | C41: Is the governance process regularly reviewed? | P41: =VLOOKUP(_Output!D77,_Guidance!B127:C132,2,FALSE) | Q41: Regularity should be matched to your own internal policy. At least yearly is recommended
B42: 4.9 | C42: Is the governance process aligned with all stakeholders? | P42: =VLOOKUP(_Output!D78,_Guidance!B133:C138,2,FALSE) | Q42: Alignment will help the SOC obtain required mandate, budget and management support
B43: 4.10 | C43: Is the SOC regularly audited or subjected to external assessments? | P43: =VLOOKUP(_Output!D79,_Guidance!B139:C144,2,FALSE) | Q43: Frequency should be matched to your own internal policy. At least yearly is recommended
B44: 4.11 | C44: Is there an active cooperation with other SOCs (external)? | P44: =VLOOKUP(_Output!D984,_Guidance!B145:C150,2,FALSE) | Q44: Exchange of best practices, intelligence and actions on threats with other SOCs is vital for improving cyber defence
B46: Comments and/or Remarks
B47: 4.12 | C47: Specify rationale for chosen values or any additional comments | L47: 4.1
L48: 4.2
L49: 4.4
L50: 4.6
L51: 4.7
L52: 4.8
L53: 4.9
L54: 4.10
L55: 4.11

Sheet Business - PRV
B1: Business
B3: 1. Business Drivers | G3: 5. Privacy & Policy
B4: 2. Customers
B5: 3. Charter
B6: 4. Governance
A9: 5 | B9: Privacy & Policy | L9: Answer | N9: Importance | P9: Guidance | Q9: Remarks
B10: 5.1 | C10: Is there an information security policy in place that supports the SOC activities? | P10: =VLOOKUP(_Output!D986,_Guidance!B152:C157,2,FALSE) | Q10: A clear security policy that supports SOC operations provides guidance and helps to enforce mandate for the SOC in the organisation
B11: 5.2 | C11: Has a SOC policy been created? | P11: =VLOOKUP(_Output!D1078,_Guidance!B158:C163,2,FALSE) | Q11: A SOC policy is to outline the rules to which SOC personnel and SOC management needs to adhere
B12: 5.3 | C12: Please specify elements of the SOC policy
B13: 5.3.1 | C13: Code of conduct | Q13: How to behave in the SOC, mandatory and optional meetings, SOC culture, repercussions for non-compliance, etc.
B14: 5.3.2 | C14: Rules of engagement & responsibilities | Q14: What activities can and can not be performed as part of the job
B15: 5.3.3 | C15: Review frequency of documentation | Q15: What documentation is subjected to review and how often that documentation needs to be reviewed
B16: 5.3.4 | C16: SOC assessment frequency and type | Q16: How often the SOC is assessed and in what manner (self-assessment, audit, external assessment, etc.)
B17: 5.3.5 | C17: Knowledge exchange and maintenance | Q17: The means (meetings and platforms) for knowledge exchange and rules for maintenance of knowledge bases
B18: 5.3.6 | C18: Exercise frequency | Q18: Frequency and type (table top, cyber range, red team, etc.) of exercises in the SOC
B19: 5.3.7 | C19: Usage of TLP | Q19: Information exchange protocols. Especially important for collaborations outside the organisation
B20: 5.3.8 | C20: Working agreements | Q20: Agreements on length of meetings, length of agile sprints, transparency of completed work, etc.
C21: Completeness | L21: =VLOOKUP(SUM(_Output!D1080:D1087),_SUM_Completeness!A155:B163,2,FALSE) -> Incomplete | Q21: Use this outcome as a guideline to determine the score for 5.2
B22: 5.4 | C22: Is the SOC consulted in the creation and updates of operational security policy? | P22: =VLOOKUP(_Output!D988,_Guidance!B164:C169,2,FALSE) | Q22: Consulting the SOC in the creation of security policy will ensure that SOC activities are properly mentioned and enforceable
B23: 5.5 | C23: Is a reporting policy for security incidents in place? | P23: =VLOOKUP(_Output!D990,_Guidance!B170:C175,2,FALSE) | Q23: A reporting policy for security incidents will aid the SOC in identifying incidents and threats in the organization
B24: 5.6 | C24: Is a privacy policy regarding security monitoring of employees in place? | P24: =VLOOKUP(_Output!D83,_Guidance!B176:C181,2,FALSE) | Q24: A privacy policy should state that monitoring of employees is possible within acceptable limits
B25: 5.7 | C25: Does the SOC operate in compliance with all applicable privacy laws and regulations? | P25: =VLOOKUP(_Output!D84,_Guidance!B182:C187,2,FALSE) | Q25: Local laws and regulations as well as company policy may apply and should all be considered
B26: 5.8 | C26: Does the SOC cooperate with legal departments regarding privacy matters? | P26: =VLOOKUP(_Output!D87,_Guidance!B188:C193,2,FALSE) | Q26: Cooperation will ensure that the SOC is enabled to perform activities, rather than blocked
B27: 5.9 | C27: Are specific procedures in place for dealing with privacy related investigations? | P27: =VLOOKUP(_Output!D88,_Guidance!B194:C199,2,FALSE) | Q27: Privacy related issues require careful examination, especially those potentially leading to court cases
B28: 5.10 | C28: Is the SOC aware of all information that it processes and is subject to privacy regulations? | P28: =VLOOKUP(_Output!D89,_Guidance!B200:C205,2,FALSE) | Q28: Such information includes IP addresses, customer identifiers, user names, host names (for personally owned devices), etc.
B29: 5.11 | C29: Is a Privacy Impact Assessment (PIA) regularly conducted? | P29: =VLOOKUP(_Output!D90,_Guidance!B206:C211,2,FALSE) | Q29: Can be used to determine the impact of monitoring on privacy, and can help uncover potential violations
B31: Comments and/or Remarks
B32: 5.10 | C32: Specify rationale for chosen values or any additional comments | L32: 5.1
L33: 5.2
L34: 5.4
L35: 5.5
L36: 5.6
L37: 5.7
L38: 5.8
L39: 5.9

Sheet People - EMP
B1: People
B3: 1. Employees | G3: 5. Training & Education
B4: 2. Roles and Hierarchy
B5: 3. People Management
B6: 4. Knowledge Management
A9: 1 | B9: Employees | L9: Answer | N9: Importance | P9: Guidance | Q9: Remarks
B10: 1.1 | C10: How many FTE’s are in your SOC? | Q10: Include both internal and external FTE's
B11: 1.2 | C11: Do you use external employees / contractors in your SOC? | Q11: External employees can be hired experts to fill in vacant positions or perform project activities
B12: 1.2.1 | C12: If yes, specify the number of external FTE's | Q12: =IFERROR(CONCATENATE("Current ratio: ", ROUND(L12/L10*100, 2), "%"),"Current ratio: 0%") -> Current ratio: 0%
B13: 1.3 | C13: Does the current size of the SOC meet FTE requirements? | P13: =VLOOKUP(_Output!D98,_Guidance!B215:C220,2,FALSE) | Q13: i.e. is the SOC size sufficient to realize business goals?
B14: 1.4 | C14: Does the SOC meet requirements for internal to external employee FTE ratio? | P14: =VLOOKUP(_Output!D99,_Guidance!B221:C226,2,FALSE) | Q14: Note: requirements do not need to be explicit. Set importance to 'None' if you have no external employees.
B15: 1.5 | C15: Does the SOC meet requirements for internal to external employee skillset? | P15: =VLOOKUP(_Output!D100,_Guidance!B227:C232,2,FALSE) | Q15: i.e. Are there any crucial skills amongst external employees? Set importance to 'None' if you have no external employees
B16: 1.6 | C16: Are all positions filled? | P16: =VLOOKUP(_Output!D101,_Guidance!B233:C238,2,FALSE) | Q16: Unfilled positions may be due to deficiencies in the recruitment process
B17: 1.7 | C17: Do you have a recruitment process in place? | P17: =VLOOKUP(_Output!D102,_Guidance!B239:C244,2,FALSE) | Q17: A recruitment process is required to obtain new employees in a market where talent is scarce [1]
B18: 1.8 | C18: Do you have a talent acquisition process in place? | P18: =VLOOKUP(_Output!D103,_Guidance!B245:C250,2,FALSE) | Q18: Talent recruitment can be vital for SOC success, but talent retaining is equally important
B19: 1.9 | C19: Do you have specific KSAOs established for SOC personnel? | P19: =VLOOKUP(_Output!D994,_Guidance!B251:C256,2,FALSE) | Q19: Knowledge, Skills, Abilities and Other attributes (KSAOs) should be in place: technical, cognitive, social and character [2], [3]
B20: 1.10 | C20: Do you actively seek to create a psychologically safe environment for SOC personnel? | P20: =VLOOKUP(_Output!D995,_Guidance!B257:C262,2,FALSE) | Q20: A psychologically safe environment is an environment where everyone is able to speak their mind and feel valued
B22: Comments and/or Remarks
B23: 1.11 | C23: Specify rationale for chosen values or any additional comments | L23: 1.3
L24: 1.4
L25: 1.5
L26: 1.6
L27: 1.7
L28: 1.8
B29: [1] See the CSIRT social maturity handbook, pages 134-135 | L29: 1.9
B30: [2] See the CSIRT social maturity handbook, pages 41-42 | L30: 1.10
B31: [3] See the NIST NICE framework, specifically the Cyber Defense Analyst and Incident Responder roles:
C32: https://www.nist.gov/itl/applied-cybersecurity/nice/nice-framework-resource-center/nice-framework-supplemental-material

Sheet People - R&H
B1: People
B3: 1. Employees | G3: 5. Training & Education
B4: 2. Roles and Hierarchy
B5: 3. People Management
B6: 4. Knowledge Management
A9: 2 | B9: Roles and Hierarchy | L9: Answer | N9: Importance | P9: Guidance | Q9: Remarks
B10: 2.1 | C10: Do you formally differentiate roles within the SOC? | P10: =VLOOKUP(_Output!D107,_Guidance!B264:C269,2,FALSE) | Q10: Use the roles in 2.2 to determine if you have all roles required in the SOC
B11: 2.2 | C11: Which of the following roles are present in your SOC?
B12: 2.2.1 | C12: Security Analyst | Q12: Primarily responsible for triage and analysis of security alerts
B13: 2.2.2 | C13: Security / Systems Engineer | Q13: Primarily responsible for technical / functional maintenance of security systems
B14: 2.2.3 | C14: Forensic Analyst | Q14: Primarily responsible for in-depth analysis and security projects
B15: 2.2.4 | C15: Security Architect | Q15: Primarily responsible for technical architecture for security systems used within the SOC
B16: 2.2.5 | C16: Threat Intelligence Analyst | Q16: Primarily responsible for analysis of threat intelligence
B17: 2.2.6 | C17: Data Scientist | Q17: Primarily responsible for big data security analytics
B18: 2.2.7 | C18: SOC Manager | Q18: Primarily responsible for managing SOC services
B19: 2.2.8 | C19: Team Leader | Q19: Primarily responsible for leading a team of other, for example, analysts and engineers
B20: 2.2.9 | C20: Incident Handler | Q20: Primarily responsible for executing security incident management workflows
B21: 2.2.10 | C21: Incident Manager | Q21: Primarily responsible for ensuring correct and timely management and escalation of security incidents
B22: 2.2.11 | C22: Penetration Tester | Q22: Primarily responsible for testing applications and systems for security weaknesses
B23: 2.2.12 | C23: Detection engineer | Q23: Primarily responsible for creating and updating detection analytics
... B25: 2.2.14 | C25: Others, specify: | Q25: Specify any additional roles
B26: 2.3 | C26: Do you differentiate tiers within these roles? | P26: =VLOOKUP(_Output!D123,_Guidance!B270:C275,2,FALSE) | Q26: If you have no tiers, and you feel this is not a restriction, select importance 'None'
B27: 2.4 | C27: Are all roles sufficiently staffed? | P27: =VLOOKUP(_Output!D125,_Guidance!B276:C281,2,FALSE) | Q27: Consider the staffing levels (desired FTE count) as well as knowledge and experience for all roles
B28: 2.5 | C28: Is there a role-based hierarchy in your SOC? | P28: =VLOOKUP(_Output!D127,_Guidance!B282:C287,2,FALSE) | Q28: If you have no hierarchy, and you feel this is not a restriction, select importance 'None'
B29: 2.6 | C29: Have you formally documented all SOC roles? | P29: =VLOOKUP(_Output!D128,_Guidance!B288:C293,2,FALSE) | Q29: Possible documentation elements can be found in under 2.7
B30: 2.7 | C30: Please specify elements in the role documentation:
B31: 2.7.1 | C31: Role description | Q31: A formal description of the role
B32: 2.7.2 | C32: Role tasks | Q32: A description of tasks that are part of the role
B33: 2.7.3 | C33: Role responsibilities | Q33: The responsibilities of the role
B34: 2.7.4 | C34: Role expectations | Q34: This is an extension of responsibilities. Example expectation: take a pro-active leading role in case of security incidents
B35: 2.7.5 | C35: Required technical skills | Q35: e.g. experience with specific technologies or products
B36: 2.7.6 | C36: Required soft skills | Q36: e.g. communication skills, presentation skills
B37: 2.7.7 | C37: Required educational level | Q37: e.g. university college, university
B38: 2.7.8 | C38: Required or preferred certifications | Q38: e.g. technical security certifications or security management certifications
C39: Completeness | L39: =VLOOKUP(SUM(_Output!D132:D139),_SUM_Completeness!A58:B66,2,FALSE) -> Incomplete | Q39: Use this outcome as a guideline to determine the score for 2.6
B40: 2.8 | C40: Are responsibilities for each role understood? | P40: =VLOOKUP(_Output!D140,_Guidance!B294:C299,2,FALSE) | Q40: Responsibilities for each role should be clearly understood by all SOC personnel
B41: 2.9 | C41: Have you documented career progression requirements for each of these roles? | P41: =VLOOKUP(_Output!D143,_Guidance!B300:C305,2,FALSE) | Q41: Career progression for roles can be documented through training, certification, experience and soft skills requirements
B42: 2.10 | C42: Do you regularly revise or update the role descriptions? | P42: =VLOOKUP(_Output!D144,_Guidance!B306:C311,2,FALSE) | Q42: To revise is to review and verify whether to documentation is still correct or requires an update
B44: Comments and/or Remarks
B45: 2.11 | C45: Specify rationale for chosen values or any additional comments | L45: 2.1
L46: 2.3
L47: 2.4
L48: 2.5
L49: 2.6
L50: 2.8
L51: 2.9
L52: 2.10

Sheet People - PEM
B1: People
B3: 1. Employees | G3: 5. Training & Education
B4: 2. Roles and Hierarchy
B5: 3. People Management
B6: 4. Knowledge Management
A9: 3 | B9: People Management | L9: Answer | N9: Importance | P9: Guidance | Q9: Remarks
B10: 3.1 | C10: Do you have a job rotation plan in place? | P10: =VLOOKUP(_Output!D148,_Guidance!B314:C319,2,FALSE) | Q10: Job rotation can be used to train employees in a variety of tasks and avoid too much routine
B11: 3.2 | C11: Do you have a career progression process in place? | P11: =VLOOKUP(_Output!D149,_Guidance!B320:C325,2,FALSE) | Q11: Career development, promotion, etc.
B12: 3.3 | C12: Do you have a talent management process in place? | P12: =VLOOKUP(_Output!D150,_Guidance!B326:C331,2,FALSE) | Q12: Talent should be adequately managed to retain such staff and fully develop their potential.
B13: 3.4 | C13: Do you have team diversity goals? | P13: =VLOOKUP(_Output!D151,_Guidance!B332:C337,2,FALSE) | Q13: e.g. background diversity, ethnic diversity, gender diversity, etc.
B14: 3.5 | C14: Have you established team goals? | P14: =VLOOKUP(_Output!D996,_Guidance!B338:C343,2,FALSE) | Q14: Team goals help to bring focus to the team and monitor progress
B15: 3.6 | C15: Do you document and track individual team member goals? | P15: =VLOOKUP(_Output!D997,_Guidance!B344:C349,2,FALSE) | Q15: Individual team member goals should be set to help grow the employee to full potential
B16: 3.7 | C16: Do you periodically evaluate SOC employees? | P16: =VLOOKUP(_Output!D152,_Guidance!B350:C355,2,FALSE) | Q16: Can also be included in the regular organization evaluation process
B17: 3.8 | C17: Do you have a 'new hire' process in place? | P17: =VLOOKUP(_Output!D153,_Guidance!B356:C361,2,FALSE) | Q17: i.e. a defined process to quickly let new employees find their place and perform well in the SOC
B18: 3.9 | C18: Are all SOC employees subjected to screening? | P18: =VLOOKUP(_Output!D154,_Guidance!B362:C367,2,FALSE) | Q18: Personnel screening is performed to avoid infiltration or misbehavior by SOC employees
B19: 3.10 | C19: Do you measure employee satisfaction for improving the SOC? | P19: =VLOOKUP(_Output!D155,_Guidance!B368:C373,2,FALSE) | Q19: Employee satisfaction should be taken seriously as lack of satisfaction may lead to key personnel leaving
B20: 3.11 | C20: Are there regular 1-on-1 meetings between the SOC manager and the employees? | P20: =VLOOKUP(_Output!D156,_Guidance!B374:C379,2,FALSE) | Q20: Such informal 1-on-1 conversations are used to coach employees and help the SOC manager gain insight in personal challenges
B21: 3.12 | C21: Do you perform regular teambuilding exercises? | P21: =VLOOKUP(_Output!D157,_Guidance!B380:C385,2,FALSE) | Q21: Teambuilding exercises are used to promote collaboration between individuals in the team and to raise team spirit
B22: 3.13 | C22: Do you perform regular teambuilding exercises with other teams relevant to the SOC? | P22: =VLOOKUP(_Output!D998,_Guidance!B386:C391,2,FALSE) | Q22: In multi-team systems (MTS), the SOC collaborates with other teams. Use cross-team teambuilding to maximize performance
B23: 3.14 | C23: Do you periodically evaluate team performance? | P23: =VLOOKUP(_Output!D999,_Guidance!B392:C397,2,FALSE) | Q23: Besides individual performance, team performance and dynamics are also important to measure and improve on
B25: Comments and/or Remarks
B26: 3.15 | C26: Specify rationale for chosen values or any additional comments | L26: 3.1
L27: 3.2
L28: 3.3
L29: 3.4
L30: 3.5
L31: 3.6
L32: 3.7
L33: 3.8
L34: 3.9
L35: 3.10
L36: 3.11
L37: 3.12
L38: 3.13
L39: 3.14

Sheet People - KNM
B1: People
B3: 1. Employees | G3: 5. Training & Education
B4: 2. Roles and Hierarchy
B5: 3. People Management
B6: 4. Knowledge Management
A9: 4 | B9: Knowledge Management | L9: Answer | N9: Importance | P9: Guidance | Q9: Remarks
B10: 4.1 | C10: Do you have a formal knowledge management process in place? | P10: =VLOOKUP(_Output!D161,_Guidance!B400:C405,2,FALSE) | Q10: Formal knowledge management helps to optimize knowledge creation and distribution
B11: 4.2 | C11: Do you have a skill matrix in place? | P11: =VLOOKUP(_Output!D1091,_Guidance!B406:C411,2,FALSE) | Q11: A matrix may consist of: SOC skills, SOC employees and skill levels (novice, intermediate, expert)
B12: 4.3 | C12: Please specify elements of the skilll matrix:
B13: 4.3.1 | C13: All SOC employees | Q13: The skill matrix should cover all SOC employees, both internal and external
B14: 4.3.2 | C14: Hard skills | Q14: e.g. ability to effectively use analysis tools
B15: 4.3.3 | C15: Soft skills | Q15: e.g. communication skills
B16: 4.3.4 | C16: Skill levels (novice, intermediate, expert) | Q16: Determining and documenting skill levels helps to identify areas where limited expertise is available
C17: Completeness | L17: =VLOOKUP(SUM(_Output!D1092:D1095),_SUM_Completeness!A195:B199,2,FALSE) -> Incomplete | Q17: Use this outcome as a guideline to determine the score for 4.2
B18: 4.4 | C18: Is the skill matrix actively used for team and personal improvement? | P18: =VLOOKUP(_Output!D1096,_Guidance!B412:C417,2,FALSE) | Q18: Personal improvement is essential, team improvement requires insight in team dynamics and skill distribution
B19: 4.5 | C19: Do you have a knowledge matrix in place? | P19: =VLOOKUP(_Output!D1097,_Guidance!B418:C423,2,FALSE)
B20: 4.6 | C20: Please specify elements of the knowledge matrix:
B21: 4.6.1 | C21: All SOC employees | Q21: The knowledge matrix should cover all SOC employees, both internal and external
B22: 4.6.2 | C22: All relevant knowledge areas | Q22: Knowledge for service delivery: technical (i.e. support), functional (i.e. configuration) and foundational (e.g. networking, encryption)
B23: 4.6.3 | C23: Knowledge levels (novice, intermediate, expert) | Q23: Determining and documenting knowledge levels helps to identify areas where limited expertise is available
C24: Completeness | L24: =VLOOKUP(SUM(_Output!D1098:D1100),_SUM_Completeness!A202:B205,2,FALSE) -> Incomplete | Q24: Use this outcome as a guideline to determine the score for 4.5
B25: 4.7 | C25: Is the knowledge matrix acively used to determine training and education needs? | P25: =VLOOKUP(_Output!D1101,_Guidance!B424:C429,2,FALSE) | Q25: The matrix should be used as a means to identify and resolve knowledge gaps
B26: 4.8 | C26: Have you documented SOC team member abilities? | P26: =VLOOKUP(_Output!D1000,_Guidance!B430:C435,2,FALSE) | Q26: Besides knowledge and skills, team member abilities are also important to document
B27: 4.9 | C27: Do you regularly assess and revise the knowledge management process? | P27: =VLOOKUP(_Output!D175,_Guidance!B436:C441,2,FALSE) | Q27: This refers to the knowledge management process as a whole
B28: 4.10 | C28: Is there effective tooling in place to support knowledge documentation and distribution? | P28: =VLOOKUP(_Output!D176,_Guidance!B442:C447,2,FALSE) | Q28: Such tooling can help to avoid investigation similar issues multiple times by integrating into the security monitoring process
B30: Comments and/or Remarks
B31: 4.11 | C31: Specify rationale for chosen values or any additional comments | L31: 4.1
L32: 4.2
L33: 4.4
L34: 4.5
L35: 4.7
L36: 4.8
L37: 4.9
L38: 4.10

Sheet People - T&E
B1: People
B3: 1. Employees | G3: 5. Training & Education
B4: 2. Roles and Hierarchy
B5: 3. People Management
B6: 4. Knowledge Management
A9: 5 | B9: Training and Education | L9: Answer | N9: Importance | P9: Guidance | Q9: Remarks
B10: 5.1 | C10: Do you have a training program in place? | P10: =VLOOKUP(_Output!D180,_Guidance!B450:C455,2,FALSE) | Q10: A training program is used to ensure a minimal level of knowledge for employees
B11: 5.2 | C11: Please specify elements of the training program:
B12: 5.2.1 | C12: Training on the Job | Q12: Training on the job can be done internally by senior employees or using external consultants
B13: 5.2.2 | C13: Product-specific training | Q13: Product-specific training may be required for new technologies or complex solutions
B14: 5.2.3 | C14: Internal company training | Q14: e.g. training on internal policies
B15: 5.2.4 | C15: Role-based specific training | Q15: For example: security analysis training for the security analyst role
B16: 5.2.5 | C16: Soft-skill training | Q16: To complement hard skills, soft skills should be trained as well
B17: 5.2.6 | C17: Formal education | Q17: Formal education may be university or university college degrees
C18: Completeness | L18: =VLOOKUP(SUM(_Output!D182:D187),_SUM_Completeness!A69:B75,2,FALSE) -> Incomplete | Q18: Use this outcome as a guideline to determine the score for 5.1
B19: 5.3 | C19: Do you have a certification program in place? | P19: =VLOOKUP(_Output!D188,_Guidance!B456:C461,2,FALSE) | Q19: A certification program is used to provide a demonstrable minimum level of knowledge and skills
B20: 5.4 | C20: Please specify elements of the certification program:
B21: 5.4.1 | C21: Internal certification track | Q21: Internal certifications may be in place to demonstrate knowledge of company processes and policies
B22: 5.4.2 | C22: External certification track | Q22: Certification track with external certification organizations (e.g. ISACA, (ISC)2, SANS
B23: 5.4.3 | C23: Re-certification track (continuous education) | Q23: Permanent education (PE) may be part of the certification itself
C24: Completeness | L24: =VLOOKUP(SUM(_Output!D190:D192),_SUM_Completeness!A78:B81,2,FALSE) -> Incomplete | Q24: Use this outcome as a guideline to determine the score for 5.3
B25: 5.5 | C25: Is the training and certification program connected to evaluation and career progression? | P25: =VLOOKUP(_Output!D193,_Guidance!B462:C467,2,FALSE) | Q25: e.g. certain training and certifications are required to grow from a junior level function to a more senior level function
B26: 5.6 | C26: Is there a reserved budget for education and training? | P26: =VLOOKUP(_Output!D194,_Guidance!B468:C473,2,FALSE) | Q26: i.e. a fixed percentage of the total SOC budget that is allocated for education and cannot be used for other purposes
B27: 5.7 | C27: Is there a reserved amount of time for education and training? | P27: =VLOOKUP(_Output!D195,_Guidance!B474:C479,2,FALSE) | Q27: This is an extension of education budget
B28: 5.8 | C28: Do you have regular workshops for knowledge development? | P28: =VLOOKUP(_Output!D196,_Guidance!B480:C485,2,FALSE) | Q28: Workshops are an informal way of distributing knowledge
B29: 5.9 | C29: Do you regularly revise and update the training and certification programs? | P29: =VLOOKUP(_Output!D197,_Guidance!B486:C491,2,FALSE) | Q29: Training and certification must be a relevant reflection of SOC knowledge and skill requirements
B31: Comments and/or Remarks
B32: 5.10 | C32: Specify rationale for chosen values or any additional comments | L32: 5.1
L33: 5.3
L34: 5.5
L35: 5.6
L36: 5.7
L37: 5.8
L38: 5.9

Sheet Process - MGT
B1: Process
B3: 1. SOC Management | G3: 5. Detection Engineering & Validation
B4: 2. Operations & Facilities
B5: 3. Reporting & Communication
B6: 4. Use Case Management
A9: 1 | B9: Management | L9: Answer | N9: Importance | P9: Guidance | R9: Remarks
B10: 1.1 | C10: Is there a SOC management process in place? | P10: =VLOOKUP(_Output!D202,_Guidance!B495:C500,2,FALSE) | R10: A SOC management process is used to manage all aspects SOC service delivery and quality
B11: 1.2 | C11: Are SOC management elements formally identified and documented? | P11: =VLOOKUP(_Output!D203,_Guidance!B501:C506,2,FALSE) | R11: Possible SOC management elements can be found in under 1.3
B12: 1.3 | C12: Please specify identified SOC management elements:
B13: 1.3.1 | C13: Internal relationship management | R13: Relationship management within the organization
B14: 1.3.2 | C14: External relationship management | R14: Relationship management outside of the organization
B15: 1.3.3 | C15: Vendor management | R15: Relationship management with relevant vendors for SOC technologies
B16: 1.3.4 | C16: Continuous service improvement | R16: A methodology for continuously improving on SOC service delivery and internal processes supporting service delivery
B17: 1.3.5 | C17: Project methodology | R17: For example: LEAN or agile project approach
B18: 1.3.6 | C18: Process documentation and diagrams | R18: Any documentation on SOC processes or services. May contains diagrams explaining relationships between processes
B19: 1.3.7 | C19: RACI matrix | R19: A description of all SOC responsibilities, accountabilities and cases in which the SOC is informed or consulted
B20: 1.3.8 | C20: Service Catalogue | R20: A description of all SOC services and service levels
B21: 1.3.9 | C21: Service on-boarding procedure | R21: Procedure for intake, evaluation and move-to-production for requests for new services or customers
B22: 1.3.10 | C22: Service off-loading procedure | R22: Procedure to remove existing services and customers from service delivery
C23: Completeness | L23: =VLOOKUP(SUM(_Output!D205:D214),_SUM_Completeness!A45:B55,2,FALSE) -> Incomplete | R23: Use this outcome as a guideline to determine the score for 1.2
B24: 1.4 | C24: Is the SOC management process regularly reviewed? | P24: =VLOOKUP(_Output!D215,_Guidance!B507:C512,2,FALSE) | R24: Regular review of the SOC management process ensures optimal performance
B25: 1.5 | C25: Is the SOC management process aligned with all stakeholders? | P25: =VLOOKUP(_Output!D216,_Guidance!B513:C518,2,FALSE) | R25: Alignment with stakeholders will ensure the SOC delivers services that meet customer expectations
B26: 1.6 | C26: Have you implemented a process for continuous improvement (CI)? | P26: =VLOOKUP(_Output!D1103,_Guidance!B519:C524,2,FALSE) | R26: Continuous improvement is a vital process for SOCs to evolve their capabilities
B27: 1.7 | C27: Have you implemented a process to manage SOC quality assurance (QA)? | P27: =VLOOKUP(_Output!D1104,_Guidance!B525:C530,2,FALSE) | R27: Quality assurance is aimed at ensuring SOC processes, technology and services meet their quality requirements
B28: 1.8 | C28: SOC architecture
B29: 1.8.1 | C29: Is a SOC process architecture in place? | R29: A process architecture outlines the different processes within the SOC and how they interact / integrate
B30: 1.8.2 | C30: Is a SOC technology architecture in place? | R30: A technology architecture outlines the different technologies used within the SOC and how they interact / integrate
B31: 1.8.3 | C31: Is a SOC service architecture in place? | R31: A service architecture outlines the different services used within the SOC and how they interact / integrate
B33: Comments and/or Remarks
B34: 1.8 | C34: Specify rationale for chosen values or any additional comments | L34: 1.1
L35: 1.2
L36: 1.4
L37: 1.5
L38: 1.6
L39: 1.7
L40: 1.8.1
L41: 1.8.2
L42: 1.8.3

Sheet Process - O&F
B1: Process
B3: 1. SOC Management | G3: 5. Detection Engineering & Validation
B4: 2. Operations & Facilities
B5: 3. Reporting & Communication
B6: 4. Use Case Management
A9: 2 | B9: Operations and Facilities | L9: Answer | N9: Importance | P9: Guidance | R9: Remarks
B10: 2.1 | C10: Security operations exercises
B11: 2.1.1 | C11: Do you have a documented exercise plan? | P11: =VLOOKUP(_Output!D1108,_Guidance!B533:C538,2,FALSE) | R11: An exercise plan lists the type of exercises to be conducted, the frequency and the exercise goals
B12: 2.1.2 | C12: Please specify types of exercises included in the plan
B13: 2.1.2.1 | C13: Table-top exercises
B14: 2.1.2.2 | C14: Playbook drills
B15: 2.1.2.3 | C15: Cyber range
B16: 2.1.2.4 | C16: Capture the flag
B17: 2.1.2.5 | C17: Purple/Red/Black team exercises
B18: 2.1.2.6 | C18: Public exercises [1]
C19: Completeness | L19: =VLOOKUP(SUM(_Output!D1109:D1114),_SUM_Completeness!A166:B172,2,FALSE) -> Incomplete | R19: Use this outcome as a guideline to determine the score for 1.2
B20: 2.1.3 | C20: Do you perform security operations exercises regularly? | P20: =VLOOKUP(_Output!D221,_Guidance!B539:C544,2,FALSE) | R20: Regularity should be matched to your own internal policy
B21: 2.1.4 | C21: Are the results from exercises documented? | P21: =VLOOKUP(_Output!D1115,_Guidance!B545:C550,2,FALSE) | R21: Results from exercisess should be structurally documented for future reference and identification of improvements
B22: 2.1.5 | C22: Is the output from exercises actively used to improve security operations? | P22: =VLOOKUP(_Output!D1116,_Guidance!B551:C556,2,FALSE) | R22: Exercise output should be used to structurally improve security operations
B23: 2.2 | C23: Service delivery standardization
B24: 2.2.1 | C24: Do you have standard operating procedures? | P24: =VLOOKUP(_Output!D222,_Guidance!B557:C562,2,FALSE) | R24: Standard operating procedures are used to provide consistent output
B25: 2.2.2 | C25: Do you use checklists for recurring activities? | P25: =VLOOKUP(_Output!D223,_Guidance!B563:C568,2,FALSE) | R25: Checklists can be useful to avoid recurring activities from being overlooked
B26: 2.2.3 | C26: Do you use documented workflows? | P26: =VLOOKUP(_Output!D224,_Guidance!B569:C574,2,FALSE) | R26: Workflows are used to standardize steps in, for example, security analysis
B27: 2.2.4 | C27: Do you have a SOC operational handbook? | P27: =VLOOKUP(_Output!D225,_Guidance!B575:C580,2,FALSE) | R27: A SOC operational handbook contains an overview of SOC tasks, as well as rules of engagement and expected behavior
B28: 2.2.5 | C28: Have you established an Operational Security (OPSEC) program? | P28: =VLOOKUP(_Output!D1002,_Guidance!B581:C586,2,FALSE) | R28: An OPSEC program dictates security rules to ensure the integrity and confidentiality of SOC processes, tools and information
B29: 2.3 | C29: Process integration
B30: 2.3.1 | C30: Is the configuration management process integrated in the SOC? | P30: =VLOOKUP(_Output!D227,_Guidance!B587:C592,2,FALSE) | R30: SOC services and procedures should be aligned and integrated with the organization's configuration management process
B31: 2.3.2 | C31: Is the change management process integrated in the SOC? | P31: =VLOOKUP(_Output!D228,_Guidance!B593:C598,2,FALSE) | R31: SOC services and procedures should be aligned and integrated with the organization's change management process
B32: 2.3.3 | C32: Is the problem management process integrated in the SOC? | P32: =VLOOKUP(_Output!D229,_Guidance!B599:C604,2,FALSE) | R32: SOC services and procedures should be aligned and integrated with the organization's problem management process
B33: 2.3.4 | C33: Is the incident management process integrated in the SOC? | P33: =VLOOKUP(_Output!D230,_Guidance!B605:C610,2,FALSE) | R33: SOC services and procedures should be aligned and integrated with the organization's incident management process
B34: 2.3.5 | C34: Is the asset management process integrated in the SOC? | P34: =VLOOKUP(_Output!D231,_Guidance!B611:C616,2,FALSE) | R34: SOC services and procedures should be aligned and integrated with the organization's asset management process
B35: 2.4 | C35: SOC Facilities
B36: 2.4.1 | C36: Do you have a dedicated physical SOC location? | P36: =VLOOKUP(_Output!D233,_Guidance!B617:C622,2,FALSE) | R36: A dedicated physical location decreases likelihood of unauthorized access and provides confidentiality for security incidents
B37: 2.4.2 | C37: Do you have a war room for the SOC? | P37: =VLOOKUP(_Output!D1003,_Guidance!B623:C628,2,FALSE) | R37: A dedicated facility for coordination of major security incidents
B38: 2.4.3 | C38: Do you have a dedicated network for the SOC? | P38: =VLOOKUP(_Output!D234,_Guidance!B629:C634,2,FALSE) | R38: Given the confidentiality of the SOC and the importance of monitoring, it is recommended to use a separate network
B39: 2.4.4 | C39: Do you have physical access control to the SOC location? | P39: =VLOOKUP(_Output!D235,_Guidance!B635:C640,2,FALSE) | R39: e.g. key cards (badges) for access with access logging
B40: 2.4.5 | C40: Do you have a secure physical storage location? | P40: =VLOOKUP(_Output!D1004,_Guidance!B641:C646,2,FALSE) | R40: Secure storage facilities can be used to store evidence collected during investigations or other operational security purposes
B41: 2.4.6 | C41: Do you have a video wall for monitoring purposes? | P41: =VLOOKUP(_Output!D236,_Guidance!B647:C652,2,FALSE) | R41: A video wall can be used to display the real-time security status and can be used for decision making as well as PR
B42: 2.4.7 | C42: Do you have a call-center capability for the SOC? | P42: =VLOOKUP(_Output!D237,_Guidance!B653:C658,2,FALSE) | R42: Since communication and coordination are important features of a SOC, call-center capability may be required
B43: 2.4.8 | C43: Do you have specialized analyst workstations? | P43: =VLOOKUP(_Output!D238,_Guidance!B659:C664,2,FALSE) | R43: e.g. multiple screen setup, virtual machines, etc.
B44: 2.4.9 | C44: Have you optimized secure remote working capabilities for SOC employees? | P44: =VLOOKUP(_Output!D1005,_Guidance!B665:C670,2,FALSE) | R44: Secure working enabled means secure access (MFA, encryption, etc.), secure working facilitated also means equipped and performing
B45: 2.5 | C45: Operational shifts
B46: 2.5.1 | C46: Do you use shift schedules? | P46: =VLOOKUP(_Output!D240,_Guidance!B671:C676,2,FALSE) | R46: Shift schedules are used to ensure full shift coverage
B47: 2.5.2 | C47: Have schedules been created to optimize vigilance during shifts? | P47: =VLOOKUP(_Output!D1006,_Guidance!B677:C682,2,FALSE) | R47: Schedules should be created to optimize vigilance. Thus, shift should include mandatory breaks and not be too long
B48: 2.5.3 | C48: Do you have a shift log? | P48: =VLOOKUP(_Output!D241,_Guidance!B683:C688,2,FALSE) | R48: A shift log covers all exceptions found during the shift, running investigations, etc.
B49: 2.5.4 | C49: Do you have a formally described shift turnover procedure? | P49: =VLOOKUP(_Output!D242,_Guidance!B689:C694,2,FALSE) | R49: i.e. a procedure for handing over a shift and exchanging information regarding running tasks or issues for further follow-up
B50: 2.5.5 | C50: Do you have a daily SOC operational stand-up? | P50: =VLOOKUP(_Output!D243,_Guidance!B695:C700,2,FALSE) | R50: This can also be a call in case physical attendance is not possible for all attendees
B51: 2.5.6 | C51: Do you have stand-by arrangements with employees within the SOC? | P51: =VLOOKUP(_Output!D244,_Guidance!B701:C706,2,FALSE) | R51: i.e. is there a formal stand-by function that obligates employees to be able to be reached within a certain time?
B52: 2.6 | C52: Knowledge & document management
B53: 2.6.1 | C53: Do you have a Document Management System in place? | P53: =VLOOKUP(_Output!D246,_Guidance!B707:C712,2,FALSE) | R53: The system should support different file types, authorizations and version management; possibly even encryption
B54: 2.6.2 | C54: Do you have a knowledge & collaboration platform in place? | P54: =VLOOKUP(_Output!D247,_Guidance!B713:C718,2,FALSE) | R54: e.g. a wiki space or SharePoint that allows collaboration and supports team efforts
B56: Comments and/or Remarks
B57: 2.6 | C57: Specify rationale for chosen values or any additional comments | L57: 2.1.1
L58: 2.1.3
C59: [1] public exercises may include exercises like: | L59: 2.1.4
C60: - FS-ISAC CAPS (payment systems) | L60: 2.1.5
C61: https://www.fsisac.com/resilience/exercises | L61: 2.2.1
C62: - ENISA Cyber Europe | L62: 2.2.2
C63: https://www.enisa.europa.eu/topics/training-and-exercises/cyber-exercises/ | L63: 2.2.3
C64: - CISA Cyber Storm | L64: 2.2.4
C65: https://www.cisa.gov/cyber-storm-securing-cyber-space | L65: 2.2.5
L66: 2.3.1
L67: 2.3.2
L68: 2.3.3
L69: 2.3.4
L70: 2.3.5
L71: 2.4.1
L72: 2.4.2
L73: 2.4.3
L74: 2.4.4
L75: 2.4.5
L76: 2.4.6
L77: 2.4.7
... L87: 2.6.2

Sheet Process - RPT
B1: Process
B3: 1. SOC Management | G3: 5. Detection Engineering & Validation
B4: 2. Operations & Facilities
B5: 3. Reporting & Communication
B6: 4. Use Case Management
A9: 3 | B9: Reporting & communication | L9: Answer | N9: Importance | P9: Guidance | R9: Remarks
B10: 3.1 | C10: Do you regularly provide reports? | P10: =VLOOKUP(_Output!D251,_Guidance!B721:C726,2,FALSE) | R10: Regular reports help to keep customers informed of SOC activities
B11: 3.2 | C11: Are these reports tailored to the recipients? | P11: =VLOOKUP(_Output!D252,_Guidance!B727:C732,2,FALSE) | R11: e.g. management reports for senior management, technical reports for the IT organization
B12: 3.3 | C12: Are the report contents approved by or reviewed by the recipients? | P12: =VLOOKUP(_Output!D253,_Guidance!B733:C738,2,FALSE) | R12: formal sign-off can be part of a larger service delivery sign-off
B13: 3.4 | C13: Do you have established reporting lines within the organization? | P13: =VLOOKUP(_Output!D254,_Guidance!B739:C744,2,FALSE) | R13: e.g. reporting lines could be: SOC management, IT management, senior management
B14: 3.5 | C14: Do you regularly revise and update the report templates? | P14: =VLOOKUP(_Output!D255,_Guidance!B745:C750,2,FALSE) | R14: Report templates should be regularly optimized to ensure continued
B15: 3.6 | C15: Do you have formal agreements with the recipients regarding reports? | P15: =VLOOKUP(_Output!D256,_Guidance!B751:C756,2,FALSE) | R15: For example: timelines of delivery, report contents, etc.
B16: 3.7 | C16: Do you provide different types of reports to your recipients? | P16: =VLOOKUP(_Output!D1117,_Guidance!B757:C762,2,FALSE) | R16: Different types of reports provide more insight into security operations
B17: 3.8 | C17: Please specify SOC report types:
B18: 3.8.1 | C18: Technical security reports | R18: i.e. reports regarding technical issues or technical solutions to security issues
B19: 3.8.2 | C19: Executive security reports | R19: i.e. reports aimed at senior executives to inform them of SOC services
B20: 3.8.3 | C20: Operational reports | R20: i.e. reports regarding security operations in general
B21: 3.8.4 | C21: Incident reports | R21: Ad-hoc reports created to provide insight into incidents. This can also be part of incident management
B22: 3.8.5 | C22: Newsletter or digest | R22: A newsletter can be an informal way to provide updates to the organization
B23: 3.8.6 | C23: KPI reports | R23: KPI reports are used to measure service performance
B24: 3.8.7 | C24: Trend reports | R24: Trend reports can be used to determine changes over time
B25: 3.8.8 | C25: Real-time reporting dashboards | R25: Real-time reporting dashboards provide immediate insight into the current performance level
C26: Completeness | L26: =VLOOKUP(SUM(_Output!D1118:D1125),_SUM_Completeness!A175:B183,2,FALSE) -> Incomplete | R26: Use this outcome as a guideline to determine the score for 3.7
B27: 3.9 | C27: Do you use different types of metrics in your reports? | P27: =VLOOKUP(_Output!D1126,_Guidance!B763:C768,2,FALSE) | R27: Different types of metrics provide more insight into security operations
B28: 3.10 | C28: Please specify SOC metric types[1]
B29: 3.10.1 | C29: Are quantitative metrics used in reports? | R29: Event count, false-positive rate, number of service requests, etc.
B30: 3.10.2 | C30: Are qualitative metrics used in reports? | R30: i.e. risk level, customer satisfaction
B31: 3.10.3 | C31: Are incident & case metrics used in reports? | R31: e.g. the number of cases and incidents, number of incidents detected by SOC, average cost per incident, etc.
B32: 3.10.4 | C32: Are timing metrics used in reports? | R32: Time to detect, time to contain, time to eradicate
B33: 3.10.5 | C33: Are metrics regarding SLAs used in reports? | R33: e.g. service availability, incidents handled within agreed time period, etc.
B34: 3.10.6 | C34: Are proactive and reactive metrics used in reports? | R34: Proactive metrics can help to show how the team is actively preventing incidents from occurring
C35: Completeness | L35: =VLOOKUP(SUM(_Output!D1127:D1132),_SUM_Completeness!A186:B192,2,FALSE) -> Incomplete | R35: Use this outcome as a guideline to determine the score for 3.9
B36: 3.11 | C36: Advisories
B37: 3.11.1 | C37: Do you provide advisories to the organization regarding threats and vulnerabilities? | P37: =VLOOKUP(_Output!D273,_Guidance!B769:C774,2,FALSE) | R37: Advisories are used to inform customers of security threats and vulnerabilities
B38: 3.11.2 | C38: Do you perform risk / impact assessments of these advisories? | P38: =VLOOKUP(_Output!D274,_Guidance!B775:C780,2,FALSE) | R38: i.e. do you add organizational context to these advisories?
B39: 3.11.3 | C39: Do you perform follow-up of these advisories? | P39: =VLOOKUP(_Output!D275,_Guidance!B781:C786,2,FALSE) | R39: i.e. do you assist in coordination when required?
B40: 3.12 | C40: Education and Awareness
B41: 3.12.1 | C41: Do you provide education and awareness to the organization? | P41: =VLOOKUP(_Output!D1008,_Guidance!B787:C792,2,FALSE) | R41: The system should support different file types, authorizations and version management; possibly even encryption
B42: 3.12.2 | C42: Do you measure the effect of education and awareness efforts? | P42: =VLOOKUP(_Output!D1009,_Guidance!B793:C798,2,FALSE) | R42: e.g. a wiki space or SharePoint that allows collaboration and supports team efforts
B43: 3.13 | C43: Communication
B44: 3.13.1 | C44: Do you use communication templates? | P44: =VLOOKUP(_Output!D1010,_Guidance!B799:C804,2,FALSE) | R44: Communication templates help to standardize and professionalize SOC communication to stakeholders
B45: 3.13.2 | C45: Do you have a communication matrix in place? | P45: =VLOOKUP(_Output!D1011,_Guidance!B805:C810,2,FALSE) | R45: A communication matrix can be used to decide when, how and with whom to communicate
B46: 3.13.3 | C46: Is communication training (verbal/written) available for SOC personnel? | P46: =VLOOKUP(_Output!D1012,_Guidance!B811:C816,2,FALSE) | R46: Communication training helps SOC personnel to communicate effectively
B47: 3.13.4 | C47: Are communication skills element of SOC role descriptions? | P47: =VLOOKUP(_Output!D1013,_Guidance!B817:C822,2,FALSE) | R47: Communication skills are important for analysts to explain their findings and recommendations
B49: Comments and/or Remarks
B50: 3.14 | C50: Specify rationale for chosen values or any additional comments | L50: 3.1
L51: 3.2
B52: [1] the SOC-CMM does not contain a KPI metrics library. Some resources that may be interesting: | L52: 3.3
B53: - Library of Cyber Resilience Metrics: | L53: 3.4
C54: https://www.betaalvereniging.nl/wp-content/uploads/Library-of-Cyber-Resilience-Metrics-Shared-Research-Program-Cybersecurity.pdf | L54: 3.5
L55: 3.6
B56: - CIS Controls metrics (v7) | L56: 3.7
C57: https://www.cisecurity.org/white-papers/cis-controls-v7-measures-metrics/ | L57: 3.9
L58: 3.11.1
L59: 3.11.2
L60: 3.11.3
L61: 3.12.1
L62: 3.12.2
L63: 3.13.1
L64: 3.13.2
L65: 3.13.3
L66: 3.13.4

Sheet Process - UCM
B1: Process
B3: 1. SOC Management | G3: 5. Detection Engineering & Validation
B4: 2. Operations & Facilities
B5: 3. Reporting & Communication
B6: 4. Use Case Management
A9: 4 | B9: Use Case Management | L9: Answer | N9: Importance | P9: Guidance | R9: Remarks
B10: 4.1 Use Case Management
B11: 4.1.1 | C11: Is there a use case management process or framework in place? | P11: =VLOOKUP(_Output!D279,_Guidance!B825:C830,2,FALSE) | R11: A framework, such as MaGMa UCF[1], can be used to guide use case lifecycle and document use case in a standardized format
B12: 4.1.2 | C12: Are use cases formally documented? | P12: =VLOOKUP(_Output!D282,_Guidance!B831:C836,2,FALSE) | R12: Formal documentation may include use case documentation templates
B13: 4.1.3 | C13: Are use cases approved by relevant stakeholders? | P13: =VLOOKUP(_Output!D285,_Guidance!B837:C842,2,FALSE) | R13: e.g. business stakeholders, IT stakeholders, CISOs, audit & compliance, risk management, etc.
B14: 4.1.4 | C14: Is the use case management process aligned with other important processes? | P14: =VLOOKUP(_Output!D288,_Guidance!B843:C848,2,FALSE) | R14: e.g. integration with the threat / risk management process to revise use cases when the threat landscape changes
B15: 4.1.5 | C15: Are use cases created using a standardized process? | P15: =VLOOKUP(_Output!D292,_Guidance!B849:C854,2,FALSE) | R15: i.e. a standardized approach to derive use cases from threats or business requirements
B16: 4.1.6 | C16: Are use cases created using a top-down approach? | P16: =VLOOKUP(_Output!D295,_Guidance!B855:C860,2,FALSE) | R16: e.g. use cases can be derived from business requirements, risk assessments, threat management / intelligence
B17: 4.1.7 | C17: Can use cases be traced from high-level drivers to low-level implementation? | P17: =VLOOKUP(_Output!D298,_Guidance!B861:C866,2,FALSE) | R17: Top-down traceability is important to determine completeness of implementation and demonstrable risk reduction
B18: 4.1.8 | C18: Can use cases be traced from low-level implementation to high-level drivers? | P18: =VLOOKUP(_Output!D301,_Guidance!B867:C872,2,FALSE) | R18: Bottom-up traceability is important for contextualizing use case output and business alignment
B19: 4.1.9 | C19: Are use cases measured for implementation and effectiveness? | P19: =VLOOKUP(_Output!D307,_Guidance!B873:C878,2,FALSE) | R19: Metrics can be applied to use cases to determine growth and maturity by measuring effectiveness and implementation
B20: 4.1.10 | C20: Are use cases scored and prioritized based on risk levels? | P20: =VLOOKUP(_Output!D310,_Guidance!B879:C884,2,FALSE) | R20: Risks can be (cyber)threats, but also non-compliance or penalties (laws & regulations)
B21: 4.1.11 | C21: Are use cases regularly revised and updated? | P21: =VLOOKUP(_Output!D313,_Guidance!B885:C890,2,FALSE) | R21: Use cases should be subjected to life cycle management and may require updates or may be outdated and decommissioned
B23: 4.2 Mitre ATT&CK® / Threat Intelligence
B24: 4.2.1 | C24: Do you measure use cases against the MITRE ATT&CK® framework for gap analysis purposes? | P24: =VLOOKUP(_Output!D1014,_Guidance!B891:C896,2,FALSE) | R24: By measuring use cases against MITRE ATT&CK®, it is possible to determine strengths and weaknesses in your layered detection approach
B25: 4.2.2 | C25: Are monitoring rules tagged with MITRE ATT&CK® framework identifiers? | P25: =VLOOKUP(_Output!D1015,_Guidance!B897:C902,2,FALSE) | R25: Tagging monitoring rules with MITRE ATT&CK® identifiers allows for reporting on sightings of attack techniques
B26: 4.2.3 | C26: Have you created a MITRE ATT&CK® risk profile for your organization? | P26: =VLOOKUP(_Output!D1016,_Guidance!B903:C908,2,FALSE) | R26: The creation of a risk profile in MITRE ATT&CK® can help to identify relevant attack techniques
B27: 4.2.4 | C27: Have you prioritized MITRE ATT&CK® techniques for relevance? | P27: =VLOOKUP(_Output!D1017,_Guidance!B909:C914,2,FALSE) | R27: Using organizational context (protection and detection mechanisms), ATT&CK® techniques can be prioritized
B28: 4.2.5 | C28: Is use case output (alerts) used in threat intelligence activities? | P28: =VLOOKUP(_Output!D1018,_Guidance!B915:C920,2,FALSE) | R28: Using MITRE ATT&CK®, it is possible to connect alerts to specific threat actors, or potentially even active campaigns
B29: 4.2.6 | C29: Is threat intelligence used for the creation and updates of use cases? | P29: =VLOOKUP(_Output!D1019,_Guidance!B921:C926,2,FALSE) | R29: Threat intelligence can provide input into security monitoring, especially when using MITRE ATT&CK® to connect both
B31: 4.3 Visibility
B32: 4.3.1 | C32: Do you determine and document visibility requirements for each use case? | P32: =VLOOKUP(_Output!D1020,_Guidance!B927:C932,2,FALSE) | R32: Data source requirements should be part of use case design
B33: 4.3.2 | C33: Do you measure visibility status for your use cases for gap analysis purposes? | P33: =VLOOKUP(_Output!D1021,_Guidance!B933:C938,2,FALSE) | R33: Measuring visibility status of use cases will help to identify use cases that require additional data sources for detection optimization
B34: 4.3.3 | C34: Do you map data source visibility to the MITRE ATT&CK® framework? [2] | P34: =VLOOKUP(_Output!D1022,_Guidance!B939:C944,2,FALSE) | R34: Mapping available data sources to MITRE ATT&CK® data source requirements will help identify gaps in visibility of attack techniques
B36: Comments and/or Remarks
B37: 4.4 | C37: Specify rationale for chosen values or any additional comments | L37: 4.1.1
L38: 4.1.2
B39: [1] The MaGMa Use Case Framework is a framework and tool for use case management created by the Dutch financial sector and can be obtained from the following location: | L39: 4.1.3
L40: 4.1.4
B41: https://www.betaalvereniging.nl/en/safety/magma/ | L41: 4.1.5
B42: [2] For example, using the DeTT&CT tooling: | L42: 4.1.6
B43: https://github.com/rabobank-cdc/DeTTECT | L43: 4.1.7
L44: 4.1.8
L45: 4.1.9
L46: 4.1.10
L47: 4.1.11
L48: 4.2.1
L49: 4.2.2
L50: 4.2.3
L51: 4.2.4
L52: 4.2.5
L53: 4.2.6
L54: 4.3.1
L55: 4.3.2
L56: 4.3.3

Sheet Process - DTE
B1: Process
B3: 1. SOC Management | G3: 5. Detection Engineering & Validation
B4: 2. Operations & Facilities
B5: 3. Reporting & Communication
B6: 4. Use Case Management
A9: 5 | B9: Detection Engineering & Validation | L9: Answer | N9: Importance | P9: Guidance | R9: Remarks
B10: 5.1 Detection Engineering
B11: 5.1.1 | C11: Do you have a detection engineering process in place? | P11: =VLOOKUP(_Output!D1025,_Guidance!B947:C952,2,FALSE) | R11: A detection engineering process supports the creation and deployment of detection rules for security monitoring purposes
B12: 5.1.2 | C12: Is the detection engineering process formally documented? | P12: =VLOOKUP(_Output!D1026,_Guidance!B953:C958,2,FALSE) | R12: Formal documentation supports process standardisation, and allows for faster training of new engineers
B13: 5.1.3 | C13: Are there specific roles and requirements for detection engineers? | P13: =VLOOKUP(_Output!D1027,_Guidance!B959:C10028,2,FALSE) | R13: Detection engineers have a skillset that is different from security analysts and security engineers
B14: 5.1.4 | C14: Is there active cooperation between the SOC analysts and the detection engineers? | P14: =VLOOKUP(_Output!D1028,_Guidance!B965:C10034,2,FALSE) | R14: SOC analyst deal with alerts resulting from detections created by engineers, so a tight interaction is required to optimize the ruleset
B15: 5.1.5 | C15: Is there active cooperation between the Threat Intelligence analysts and detection engineers? | P15: =VLOOKUP(_Output!D1029,_Guidance!B971:C976,2,FALSE) | R15: Threat intelligence is a major input into the creation or updating of detection rules
B16: 5.1.6 | C16: Are there formal hand-over to the analyst team? | P16: =VLOOKUP(_Output!D1030,_Guidance!B977:C982,2,FALSE) | R16: Once the detections are created, they must be operationalized. This should be done with a formal hand-over to production
B17: 5.1.7 | C17: Is there a testing enviroment to test and validate detections before deploying them? | P17: =VLOOKUP(_Output!D1031,_Guidance!B983:C988,2,FALSE) | R17: A testing environment allows for thorough testing of new detections, which ensures a higher level of quality
B18: 5.1.8 | C18: Is there a formal release process in place for new detections? | P18: =VLOOKUP(_Output!D1032,_Guidance!B989:C994,2,FALSE) | R18: A formal release process includes automated deployment of rules and adheres to organizational change management procedures
B19: 5.1.9 | C19: Do you apply a versioning system to detections? | P19: =VLOOKUP(_Output!D1033,_Guidance!B995:C1000,2,FALSE) | R19: A versioning system will allow to revert back to previous versions of detections
B20: 5.1.10 | C20: Do you have a roll-back procedure in place in case of problems with detections? | P20: =VLOOKUP(_Output!D1034,_Guidance!B1001:C1006,2,FALSE) | R20: A roll-back procedure enabled reverting abck to a good state if a deployment has an adverse effect on security monitoring
B22: 5.2 Detection validation
B23: 5.2.1 | C23: Do you perform adversary emulation or automated detection testing? [1] | P23: =VLOOKUP(_Output!D1035,_Guidance!B1007:C1012,2,FALSE) | R23: These validation activities provides insights into how well security monitoring is able to detect certain adversaries or attack techniques
B24: 5.2.2 | C24: Do you test for detection of MITRE ATT&CK® techniques? | P24: =VLOOKUP(_Output!D1036,_Guidance!B1013:C1018,2,FALSE) | R24: Testing for MITRE ATT&CK® techniques can augment mapping of use cases and visibility in Mitre ATT&CK
B25: 5.2.3 | C25: Do you test detection analytics not directly associated with MITRE ATT&CK®? | P25: =VLOOKUP(_Output!D1037,_Guidance!B1019:C1024,2,FALSE) | R25: Not all use cases and risks have a relationship to MITRE ATT&CK®. These use cases should be tested as well
B26: 5.2.4 | C26: Do you test response playbooks? | P26: =VLOOKUP(_Output!D1038,_Guidance!B1025:C1030,2,FALSE) | R26: Testing both detection and response provides a more complete view of SOC capabilities
B27: 5.2.5 | C27: Is detection validation fully integrated in the detection engineering process? | P27: =VLOOKUP(_Output!D1039,_Guidance!B1031:C1036,2,FALSE) | R27: When deploying new or updated detection, automated detection testing should be updated as well
B28: 5.2.6 | C28: Is the outcome from detection validation used as input into monitoring and detection engineering? | P28: =VLOOKUP(_Output!D1040,_Guidance!B1037:C1042,2,FALSE) | R28: Output should lead to updates in detections and new detections, as well as instructions for SOC analysts
B29: 5.2.7 | C29: Do you monitor the data ingestion status for data sources? | P29: =VLOOKUP(_Output!D1133,_Guidance!B1043:C1048,2,FALSE) | R29: Monitoring data ingestion is used to identify data ingestion problems or inactive data sources
B30: 5.2.8 | C30: Do you actively measure and improve data source coverage? | P30: =VLOOKUP(_Output!D1135,_Guidance!B1049:C1054,2,FALSE) | R30: Data source coverage should be optimized to avoid blind spots in monitoring
B32: Comments and/or Remarks
B33: 5.3 | C33: Specify rationale for chosen values or any additional comments | L33: 5.1.1
L34: 5.1.2
C35: [1] example tools / resources include: | L35: 5.1.3
C36: - Atomic red team | L36: 5.1.4
C37: - MITRE Caldera | L37: 5.1.5
C38: - MAAD-AF | L38: 5.1.6
C39: - Breach & Attack Simulation (BAS) tools | L39: 5.1.7
C40: - CTID Adversary Emulation Library | L40: 5.1.8
L41: 5.1.9
L42: 5.1.10
L43: 5.2.1
L44: 5.2.2
L45: 5.2.3
L46: 5.2.4
L47: 5.2.5
L48: 5.2.6
L49: 5.2.7
L50: 5.2.8

Sheet Technology - SIM
B1: Technology
B3: 1. SIEM / UEBA
B4: 2. NDR
B5: 3. EDR
B6: 4. SOAR
A9: 1 | B9: SIEM tooling | L9: Answer | N9: Importance | P9: Guidance | Q9: Remarks
B10: Maturity
B11: 1.1 | C11: Accountability
B12: 1.1.1 | C12: Has functional ownership of the solution been formally assigned? | P12: =VLOOKUP(_Output!D322,_Guidance!B1058:C1063,2,FALSE) | Q12: Functional ownership includes functional accountability
B13: 1.1.2 | C13: Has technical ownership of the solution been formally assigned? | P13: =VLOOKUP(_Output!D323,_Guidance!B1064:C1069,2,FALSE) | Q13: Technical ownership includes technical accountability
B14: 1.2 | C14: Documentation
B15: 1.2.1 | C15: Has the solution been technically documented? | P15: =VLOOKUP(_Output!D325,_Guidance!B1070:C1075,2,FALSE) | Q15: A technical description of the SIEM system components and configuration
B16: 1.2.2 | C16: Has the solution been functionally documented? | P16: =VLOOKUP(_Output!D326,_Guidance!B1076:C1081,2,FALSE) | Q16: A description of the SIEM functional configuration (rules, filters, lists, etc.)
B17: 1.3 | C17: Personnel & support
B18: 1.3.1 | C18: Is there dedicated personnel for support? | P18: =VLOOKUP(_Output!D328,_Guidance!B1082:C1087,2,FALSE) | Q18: Dedicated personnel should be in place to ensure that support is always available. Can also be staff with outsourced provider
B19: 1.3.2 | C19: Is the personnel for support formally trained? | P19: =VLOOKUP(_Output!D329,_Guidance!B1088:C1093,2,FALSE) | Q19: Training helps to jump start new hires, and to learn a proper way of working with the tool
B20: 1.3.3 | C20: Is the personnel for support certified? | P20: =VLOOKUP(_Output!D330,_Guidance!B1094:C1099,2,FALSE) | Q20: Certification demonstrates ability to handle the tooling properly
B21: 1.3.4 | C21: Is there a support contract for the solution? | P21: =VLOOKUP(_Output!D331,_Guidance!B1100:C1105,2,FALSE) | Q21: A support contract may cover on-site support, support availability, response times, escalation and full access to resources
B22: 1.4 | C22: Maintenance & configuration
B23: 1.4.1 | C23: Is the system regularly maintained? | P23: =VLOOKUP(_Output!D1044,_Guidance!B1106:C1111,2,FALSE) | Q23: Systems should be regularly maintained to keep up with the latest features and bug fixes
B24: 1.4.2 | C24: Is remote maintenance on the system managed? | P24: =VLOOKUP(_Output!D1045,_Guidance!B1112:C1117,2,FALSE) | Q24: Remote maintenance by a third party may be part of system maintenance procedures
B25: 1.4.3 | C25: Are maintenance & configuration updates executed through the change management process? | P25: =VLOOKUP(_Output!D1046,_Guidance!B1118:C1123,2,FALSE) | Q25: Maintenance and configuration updates should follow the formal change management process
B26: 1.4.4 | C26: Have you established maintenance windows? | P26: =VLOOKUP(_Output!D1047,_Guidance!B1124:C1129,2,FALSE) | Q26: Setting maintenance windows helps to structure the maintenance process and make it more predictable
B27: 1.4.5 | C27: Is maintenance performed using authorised and trusted tooling? | P27: =VLOOKUP(_Output!D1048,_Guidance!B1130:C1135,2,FALSE) | Q27: Performing maintenance with authorised and trusted tooling helps to ensure security and integrity of the system
B28: 1.5 | C28: Availability & Integrity
B29: 1.5.1 | C29: Is there high availability (HA) in place for the solution? | P29: =VLOOKUP(_Output!D333,_Guidance!B1136:C1141,2,FALSE) | Q29: Can be fully implemented HA, partially implemented, hot spare, etc.
B30: 1.5.2 | C30: Is there data backup / replication in place for the solution? | P30: =VLOOKUP(_Output!D334,_Guidance!B1142:C1147,2,FALSE) | Q30: May not be feasible for all SIEM solutions
B31: 1.5.3 | C31: Is there configuration backup / replication in place for the solution? | P31: =VLOOKUP(_Output!D335,_Guidance!B1148:C1153,2,FALSE) | Q31: Configuration synchronization could be part of a HA setup
B32: 1.5.4 | C32: Is there a Disaster Recovery plan in place for this solution? | P32: =VLOOKUP(_Output!D336,_Guidance!B1154:C1159,2,FALSE) | Q32: A DR plan is required to restore service in case of catastrophic events
B33: 1.5.5 | C33: Is the Disaster Recovery plan regularly tested? | P33: =VLOOKUP(_Output!D337,_Guidance!B1160:C1165,2,FALSE) | Q33: Testing the DR plan is required to ensure that it is complete, functional and tasks and responsibilities for involved personnel are understood
B34: 1.5.6 | C34: Is there a separate development / test environment for this solution? | P34: =VLOOKUP(_Output!D338,_Guidance!B1166:C1171,2,FALSE) | Q34: A separate test environment allows for testing of new configurations before deployment in production
B35: 1.6 | C35: Access management
B36: 1.6.1 | C36: Is access to the solution limited to authorized personnel? | P36: =VLOOKUP(_Output!D340,_Guidance!B1172:C1177,2,FALSE) | Q36: The system will contain confidential information and information that possibly impacts employee privacy
B37: 1.6.2 | C37: Are access rights regularly reviewed and revoked if required? | P37: =VLOOKUP(_Output!D342,_Guidance!B1178:C1183,2,FALSE) | Q37: Revocation is part of normal employee termination. Special emergency revocation should be in place for suspected misuse
B38: 1.6.3 | C38: Is a break glass procedure in place? | P38: =VLOOKUP(_Output!D1138,_Guidance!B1184:C1189,2,FALSE) | Q38: A break glass procedure and account is required to gain access to the tooling even in case of major IT outages
B40: Capability
B41: 1.7 | C41: Specify which technological capabilities and artefacts are present and implemented:
B42: Technical capabilities
B43: 1.7.1 | C43: Subtle event detection | P43: =VLOOKUP(_Output!D1142,_Guidance!$B$2187:$C$2193,2,FALSE) | Q43: Capability to detect slight changes in systems, applications or network that may indicate malicious behavior
B44: 1.7.2 | C44: Automated alerting | P44: =VLOOKUP(_Output!D1143,_Guidance!$B$2187:$C$2193,2,FALSE) | Q44: Alerting based on different alerting mechanisms (SMS, mail, etc.)
B45: 1.7.3 | C45: Alert acknowledgement | P45: =VLOOKUP(_Output!D1144,_Guidance!$B$2187:$C$2193,2,FALSE) | Q45: Capability to acknowledge alerts so other analysts know the alert is being investigated
B46: 1.7.4 | C46: Case management system | P46: =VLOOKUP(_Output!D1145,_Guidance!$B$2187:$C$2193,2,FALSE) | Q46: A case management system that supports SOC analyst workflows
B47: 1.7.5 | C47: Network model | P47: =VLOOKUP(_Output!D1146,_Guidance!$B$2187:$C$2193,2,FALSE) | Q47: A full network model in which zones and segments are defined
B48: 1.7.6 | C48: Detailed audit trail of analyst activities | P48: =VLOOKUP(_Output!D1147,_Guidance!$B$2187:$C$2193,2,FALSE) | Q48: The audit trail can be used to report on analyst activities and to uncover potential abuse of the big data solution
B49: 1.7.7 | C49: Historical activity detection | P49: =VLOOKUP(_Output!D1148,_Guidance!$B$2187:$C$2193,2,FALSE) | Q49: Capability of detecting historical activity for recently uncovered threats
B50: 1.7.8 | C50: Flexible and scalable architecture | P50: =VLOOKUP(_Output!D1149,_Guidance!$B$2187:$C$2193,2,FALSE) | Q50: A flexible and scalable architecture supports the SOC as it grows in size (FTE) and data (coverage)
B51: 1.7.9 | C51: MITRE ATT&CK® identifier tagging | P51: =VLOOKUP(_Output!D1150,_Guidance!$B$2187:$C$2193,2,FALSE) | Q51: Add MITRE ATT&CK® tags to rules / analytics for mapping purposes
B53: Data ingestion and processing
B54: 1.7.10 | C54: Aggregation | P54: =VLOOKUP(_Output!D1151,_Guidance!$B$2187:$C$2193,2,FALSE) | Q54: Capability to aggregate data and optimize the event flow
B55: 1.7.11 | C55: Normalisation | P55: =VLOOKUP(_Output!D1152,_Guidance!$B$2187:$C$2193,2,FALSE) | Q55: Normalization of data is required for advanced searching and comparison of events from different sources
B56: 1.7.12 | C56: Correlation | P56: =VLOOKUP(_Output!D1153,_Guidance!$B$2187:$C$2193,2,FALSE) | Q56: Capability to correlate multiple events
B57: 1.7.13 | C57: Multi-stage correlation | P57: =VLOOKUP(_Output!D1154,_Guidance!$B$2187:$C$2193,2,FALSE) | Q57: Capability to detect attacks across multiple attack stages
B58: 1.7.14 | C58: Custom parsing | P58: =VLOOKUP(_Output!D1155,_Guidance!$B$2187:$C$2193,2,FALSE) | Q58: Capability to create and maintain custom parsers for parsing and normalization needs
B59: 1.7.15 | C59: API Integration | P59: =VLOOKUP(_Output!D1156,_Guidance!$B$2187:$C$2193,2,FALSE) | Q59: Both export of information / commands and import of data from API sources (such as cloud)
B60: 1.7.16 | C60: Secure Event Transfer | P60: =VLOOKUP(_Output!D1157,_Guidance!$B$2187:$C$2193,2,FALSE) | Q60: Support for secure event transfer and the actual implementation of secure transfer (e.g. regular syslog is not secure)
B61: 1.7.17 | C61: Support for multiple event transfer technologies | P61: =VLOOKUP(_Output!D1158,_Guidance!$B$2187:$C$2193,2,FALSE) | Q61: The SIEM should support event transfer technologies for all possible data sources
B63: Integrations (technical & process)
B64: 1.7.18 | C64: Asset management integration | P64: =VLOOKUP(_Output!D1159,_Guidance!$B$2187:$C$2193,2,FALSE) | Q64: Integration into the asset management process for automated adding of assets to the SIEM for monitoring
B65: 1.7.19 | C65: Business context integration | P65: =VLOOKUP(_Output!D1160,_Guidance!$B$2187:$C$2193,2,FALSE) | Q65: Integration of business context (business function, asset classification, etc.)
B66: 1.7.20 | C66: Identity context integration | P66: =VLOOKUP(_Output!D1161,_Guidance!$B$2187:$C$2193,2,FALSE) | Q66: Integration of identity information into the SIEM for enhanced monitoring of users and groups
B67: 1.7.21 | C67: Asset context integration | P67: =VLOOKUP(_Output!D1162,_Guidance!$B$2187:$C$2193,2,FALSE) | Q67: Integration of asset management information into the SIEM (asset owner, asset location, etc.)
B68: 1.7.22 | C68: Vulnerability context integration | P68: =VLOOKUP(_Output!D1163,_Guidance!$B$2187:$C$2193,2,FALSE) | Q68: Integration of vulnerability management information into SIEM assets to determine risk levels for assets
B69: 1.7.23 | C69: Threat Intelligence integration | P69: =VLOOKUP(_Output!D1164,_Guidance!$B$2187:$C$2193,2,FALSE) | Q69: Integration of threat intelligence information (observables / IoCs) into the security monitoring tooling
B70: 1.7.24 | C70: Threat hunting integration | P70: =VLOOKUP(_Output!D1165,_Guidance!$B$2187:$C$2193,2,FALSE) | Q70: Integration of the tooling into the threat hunting process to support threat hunting investigations
B71: 1.7.25 | C71: Security incident management integration | P71: =VLOOKUP(_Output!D1166,_Guidance!$B$2187:$C$2193,2,FALSE) | Q71: Integration of the security incident management process to support incident investigation
B72: 1.7.26 | C72: SOAR integration | P72: =VLOOKUP(_Output!D1167,_Guidance!$B$2187:$C$2193,2,FALSE) | Q72: Integration with the SOAR tooling for automation purposes
B74: Rule-based detection
B75: 1.7.27 | C75: Standard detection rules | P75: =VLOOKUP(_Output!D1168,_Guidance!$B$2187:$C$2193,2,FALSE) | Q75: Use of standard content packs in the security monitoring solution
B76: 1.7.28 | C76: Custom detection rules | P76: =VLOOKUP(_Output!D1169,_Guidance!$B$2187:$C$2193,2,FALSE) | Q76: Use of custom content (correlation rules, etc.) in the security monitoring solution
B78: Anomaly detection
B79: 1.7.29 | C79: User anomalies | P79: =VLOOKUP(_Output!D1170,_Guidance!$B$2187:$C$2193,2,FALSE) | Q79: Anomalous pattern detection for users
B80: 1.7.30 | C80: Application anomalies | P80: =VLOOKUP(_Output!D1173,_Guidance!$B$2187:$C$2193,2,FALSE) | Q80: Anomalous pattern detection for applications
B81: 1.7.31 | C81: Device anomalies | P81: =VLOOKUP(_Output!D1175,_Guidance!$B$2187:$C$2193,2,FALSE) | Q81: Anomalous pattern detection for devices
B82: 1.7.32 | C82: Network anomalies | P82: =VLOOKUP(_Output!D1177,_Guidance!$B$2187:$C$2193,2,FALSE) | Q82: Anomalous pattern detection for network
B84: Visualisation and output
B85: 1.7.33 | C85: Reporting | P85: =VLOOKUP(_Output!D1180,_Guidance!$B$2187:$C$2193,2,FALSE) | Q85: Custom reports for SOC customers and SOC analysts
B86: 1.7.34 | C86: Dashboards | P86: =VLOOKUP(_Output!D1181,_Guidance!$B$2187:$C$2193,2,FALSE) | Q86: Custom dashboards used by analysts and managers
B87: 1.7.35 | C87: Data visualization techniques | P87: =VLOOKUP(_Output!D1182,_Guidance!$B$2187:$C$2193,2,FALSE) | Q87: Graphing capabilities to support analysis
B88: 1.7.36 | C88: Data drilldowns | P88: =VLOOKUP(_Output!D1183,_Guidance!$B$2187:$C$2193,2,FALSE) | Q88: Drilldowns on graphs to quickly 'zoom in' on details of visual anomalies
B89: 1.7.37 | C89: Central analysis console | P89: =VLOOKUP(_Output!D1184,_Guidance!$B$2187:$C$2193,2,FALSE) | Q89: A central console used by SOC analysts
B90: 1.7.38 | C90: Advanced searching and querying | P90: =VLOOKUP(_Output!D1185,_Guidance!$B$2187:$C$2193,2,FALSE) | Q90: Searching capabilities that support finding specific information based on characteristics
C91: Completeness (%) | L91: =IFERROR(ROUND(_Output!K372,0),0) -> 0
B93: Comments and/or Remarks
B94: 1.8 | C94: Specify rationale for chosen values or any additional comments | K94: Maturity | L94: 1.1.1
L95: 1.1.2
L96: 1.2.1
L97: 1.2.2
L98: 1.3.1
L99: 1.3.2
L100: 1.3.3
L101: 1.3.4
L102: 1.4.1
L103: 1.4.2
L104: 1.4.3
L105: 1.4.4
L106: 1.4.5
... L115: 1.6.3
K117: Capability | L117: 1.7.1
L118: 1.7.2
L119: 1.7.3
...

Sheet Technology - NDR
B1: Technology
B3: 1. SIEM / UEBA
B4: 2. NDR
B5: 3. EDR
B6: 4. SOAR
A9: 2 | B9: IDPS Tooling | L9: Answer | N9: Importance | P9: Guidance | Q9: Remarks
B10: Maturity
B11: 2.1 | C11: Accountability
B12: 2.1.1 | C12: Has functional ownership of the solution been formally assigned? | P12: =VLOOKUP(_Output!D378,_Guidance!B1192:C1197,2,FALSE) | Q12: Functional ownership includes functional accountability
B13: 2.1.2 | C13: Has technical ownership of the solution been formally assigned? | P13: =VLOOKUP(_Output!D379,_Guidance!B1198:C1203,2,FALSE) | Q13: Technical ownership includes technical accountability
B14: 2.2 | C14: Documentation
B15: 2.2.1 | C15: Has the solution been technically documented? | P15: =VLOOKUP(_Output!D381,_Guidance!B1204:C1209,2,FALSE) | Q15: A technical description of the NDR system components and configuration
B16: 2.2.2 | C16: Has the solution been functionally documented? | P16: =VLOOKUP(_Output!D382,_Guidance!B1210:C1215,2,FALSE) | Q16: A description of the NDR functional configuration (rules, alerts, thresholds, etc.)
B17: 2.3 | C17: Personnel & support
B18: 2.3.1 | C18: Is there dedicated personnel for support? | P18: =VLOOKUP(_Output!D384,_Guidance!B1216:C1221,2,FALSE) | Q18: Dedicated personnel should be in place to ensure that support is always available. Can also be staff with outsourced provider
B19: 2.3.2 | C19: Is the personnel for support formally trained? | P19: =VLOOKUP(_Output!D385,_Guidance!B1222:C1227,2,FALSE) | Q19: Training helps to jump start new hires, and to learn a proper way of working with the tool
B20: 2.3.3 | C20: Is the personnel for support certified? | P20: =VLOOKUP(_Output!D386,_Guidance!B1228:C1233,2,FALSE) | Q20: Certification demonstrates ability to handle the tooling properly
B21: 2.3.4 | C21: Is there a support contract for the solution? | P21: =VLOOKUP(_Output!D387,_Guidance!B1234:C1239,2,FALSE) | Q21: A support contract may cover on-site support, support availability, response times, escalation and full access to resources
B22: 2.4 | C22: Maintenance & configuration
B23: 2.4.1 | C23: Is the system regularly maintained? | P23: =VLOOKUP(_Output!D1049,_Guidance!B1240:C1245,2,FALSE) | Q23: Systems should be regularly maintained to keep up with the latest features and bug fixes
B24: 2.4.2 | C24: Is remote maintenance on the system managed? | P24: =VLOOKUP(_Output!D1050,_Guidance!B1246:C1251,2,FALSE) | Q24: Remote maintenance by a third party may be part of system maintenance procedures
B25: 2.4.3 | C25: Are maintenance & configuration updates executed through the change management process? | P25: =VLOOKUP(_Output!D1051,_Guidance!B1252:C1257,2,FALSE) | Q25: Maintenance and configuration updates should follow the formal change management process
B26: 2.4.4 | C26: Have you established maintenance windows? | P26: =VLOOKUP(_Output!D1052,_Guidance!B1258:C1263,2,FALSE) | Q26: Setting maintenance windows helps to structure the maintenance process and make it more predictable
B27: 2.4.5 | C27: Is maintenance performed using authorised and trusted tooling? | P27: =VLOOKUP(_Output!D1053,_Guidance!B1264:C1269,2,FALSE) | Q27: Performing maintenance with authorised and trusted tooling helps to ensure security and integrity of the system
B28: 2.5 | C28: Availability & Integrity
B29: 2.5.1 | C29: Is there high availability (HA) in place for the solution? | P29: =VLOOKUP(_Output!D389,_Guidance!B1270:C1275,2,FALSE) | Q29: Can be fully implemented HA, partially implemented, hot spare, etc.
B30: 2.5.2 | C30: Is there data backup / replication in place for the solution? | P30: =VLOOKUP(_Output!D390,_Guidance!B1276:C1281,2,FALSE) | Q30: Data may include logs and PCAP files
B31: 2.5.3 | C31: Is there configuration backup / replication in place for the solution? | P31: =VLOOKUP(_Output!D391,_Guidance!B1282:C1287,2,FALSE) | Q31: Configuration synchronization could be part of a HA setup
B32: 2.5.4 | C32: Is there a Disaster Recovery plan in place for this solution? | P32: =VLOOKUP(_Output!D392,_Guidance!B1288:C1293,2,FALSE) | Q32: A DR plan is required to restore service in case of catastrophic events
B33: 2.5.5 | C33: Is the Disaster Recovery plan regularly tested? | P33: =VLOOKUP(_Output!D393,_Guidance!B1294:C1300,2,FALSE) | Q33: Testing the DR plan is required to ensure that it is complete, functional and tasks and responsibilities for involved personnel are understood
B34: 2.5.6 | C34: Is there a separate development / test environment for this solution? | P34: =VLOOKUP(_Output!D394,_Guidance!B1300:C1305,2,FALSE) | Q34: A separate test environment allows for testing of new configurations before deployment in production
B35: 2.6 | C35: Access Management
B36: 2.6.1 | C36: Is access to the solution limited to authorized personnel? | P36: =VLOOKUP(_Output!D396,_Guidance!B1306:C1311,2,FALSE) | Q36: The IDPS system will contain confidential information and possibly information that impacts employee privacy
B37: 2.6.2 | C37: Are access rights regularly reviewed and revoked if required? | P37: =VLOOKUP(_Output!D398,_Guidance!B1312:C1317,2,FALSE) | Q37: Revocation is part of normal employee termination. Special emergency revocation should be in place for suspected misuse
B38: 2.6.3 | C38: Is a break glass procedure in place? | P38: =VLOOKUP(_Output!D1139,_Guidance!B1318:C1323,2,FALSE) | Q38: A break glass procedure and account is required to gain access to the tooling even in case of major IT outages
B40: Capability
B41: 2.7 | C41: Specify which technological capabilities and artefacts are present and implemented:
B42: Technical capabilities
B43: 2.7.1 | C43: Encrypted traffic analysis | P43: =VLOOKUP(_Output!D1186,_Guidance!$B$2187:$C$2193,2,FALSE) | Q43: Helps to identify potentially malicious traffic in encrypted communications, using fingerprinting or certificate analysis
B44: 2.7.2 | C44: IDS signature matching | P44: =VLOOKUP(_Output!D1187,_Guidance!$B$2187:$C$2193,2,FALSE) | Q44: The ability to use IDS signatures (e.g. YARA) in network monitoring
B45: 2.7.3 | C45: Supervised machine learning | P45: =VLOOKUP(_Output!D1188,_Guidance!$B$2187:$C$2193,2,FALSE) | Q45: Machine learning trained on a predefined data set with known good and bad traffic
B46: 2.7.4 | C46: Unsupervised machine learning | P46: =VLOOKUP(_Output!D1189,_Guidance!$B$2187:$C$2193,2,FALSE) | Q46: Machine learning trained without a predefined data set
B47: 2.7.5 | C47: Traffic blocking | P47: =VLOOKUP(_Output!D1190,_Guidance!$B$2187:$C$2193,2,FALSE) | Q47: In-line appliances can block malicious traffic as part of their response capability
B48: 2.7.6 | C48: Unauthorised device detection | P48: =VLOOKUP(_Output!D1191,_Guidance!$B$2187:$C$2193,2,FALSE) | Q48: Detection of unauthorised devices accessing the network
B49: 2.7.7 | C49: MITRE ATT&CK® identifier tagging | P49: =VLOOKUP(_Output!D1192,_Guidance!$B$2187:$C$2193,2,FALSE) | Q49: Add MITRE ATT&CK® tags to rules / analytics for mapping and hunting purposes
B50: 2.7.8 | C50: Deep packet inspection | P50: =VLOOKUP(_Output!D1193,_Guidance!$B$2187:$C$2193,2,FALSE) | Q50: Detailed inspection of data sent across the network
B51: 2.7.9 | C51: Correlation | P51: =VLOOKUP(_Output!D1194,_Guidance!$B$2187:$C$2193,2,FALSE) | Q51: Correlation of anomalies with previously detected anomalies or detection rules
B53: Data ingestion and processing
B54: 2.7.10 | C54: Full packet capture | P54: =VLOOKUP(_Output!D1195,_Guidance!$B$2187:$C$2193,2,FALSE) | Q54: Full packet capture supports network forensic capabilities
B55: 2.7.11 | C55: Flow data ingestion | P55: =VLOOKUP(_Output!D1196,_Guidance!$B$2187:$C$2193,2,FALSE) | Q55: Flow data (such as NetFlow, IPFIX, etc.) ingestion
B57: Monitoring capabilities
B58: 2.7.12 | C58: Monitoring north - south network traffic | P58: =VLOOKUP(_Output!D1197,_Guidance!$B$2187:$C$2193,2,FALSE) | Q58: Monitoring capabilities for traffic crossing the perimeter
B59: 2.7.13 | C59: Monitoring east - west network traffic | P59: =VLOOKUP(_Output!D1199,_Guidance!$B$2187:$C$2193,2,FALSE) | Q59: Monitoring capabilities for traffic traversing the internal network
B60: 2.7.14 | C60: Monitoring classified network segements | P60: =VLOOKUP(_Output!D1201,_Guidance!$B$2187:$C$2193,2,FALSE) | Q60: Monitoring capabilities for classified network segments
B61: 2.7.15 | C61: Monitoring cloud environments | P61: =VLOOKUP(_Output!D1203,_Guidance!$B$2187:$C$2193,2,FALSE) | Q61: Monitoring capabilities for cloud connections / environments
B62: 2.7.16 | C62: Monitoring ICS/SCADA networks | P62: =VLOOKUP(_Output!D1205,_Guidance!$B$2187:$C$2193,2,FALSE) | Q62: Monitoring capabilities for ISC/SCADA networks
B63: 2.7.17 | C63: Monitoring DNS traffic | P63: =VLOOKUP(_Output!D1207,_Guidance!$B$2187:$C$2193,2,FALSE) | Q63: Monitoring capabilities for DNS queries
B65: Integrations (technical & process)
B66: 2.7.18 | C66: Business context integration | P66: =VLOOKUP(_Output!D1209,_Guidance!$B$2187:$C$2193,2,FALSE) | Q66: Integration of business context (business function, asset classification, etc.)
B67: 2.7.19 | C67: Identity context integration | P67: =VLOOKUP(_Output!D1210,_Guidance!$B$2187:$C$2193,2,FALSE) | Q67: Integration of identity information into the NDR for enhanced monitoring of users and groups
B68: 2.7.20 | C68: Threat Intelligence integration | P68: =VLOOKUP(_Output!D1211,_Guidance!$B$2187:$C$2193,2,FALSE) | Q68: Integration of threat intelligence information (observables / IoCs) into the NDR tooling for reputation-based monitoring
B69: 2.7.21 | C69: Threat hunting integration | P69: =VLOOKUP(_Output!D1212,_Guidance!$B$2187:$C$2193,2,FALSE) | Q69: Integration of the tooling into the threat hunting process to support threat hunting investigations
B70: 2.7.22 | C70: Security incident management integration | P70: =VLOOKUP(_Output!D1213,_Guidance!$B$2187:$C$2193,2,FALSE) | Q70: Integration of the security incident management process to support incident investigation
B71: 2.7.23 | C71: SIEM integration | P71: =VLOOKUP(_Output!D1214,_Guidance!$B$2187:$C$2193,2,FALSE) | Q71: Integration with the SIEM tooling for centralised correlation
B72: 2.7.24 | C72: Malware sandbox integration | P72: =VLOOKUP(_Output!D1215,_Guidance!$B$2187:$C$2193,2,FALSE) | Q72: Detonate potential malware samples in a sandbox environment
B74: Rule-based detection
B75: 2.7.25 | C75: Standard detection rules | P75: =VLOOKUP(_Output!D1216,_Guidance!$B$2187:$C$2193,2,FALSE) | Q75: Use of standard content packs in the security monitoring solution
B76: 2.7.26 | C76: Custom detection rules | P76: =VLOOKUP(_Output!D1217,_Guidance!$B$2187:$C$2193,2,FALSE) | Q76: Use of custom content (correlation rules, etc.) in the security monitoring solution
B78: Anomaly detection
B79: 2.7.27 | C79: Traffic baselining | P79: =VLOOKUP(_Output!D1218,_Guidance!$B$2187:$C$2193,2,FALSE) | Q79: Creation of network baselines for anomaly detection purposes
B80: 2.7.28 | C80: Pattern analysis | P80: =VLOOKUP(_Output!D1219,_Guidance!$B$2187:$C$2193,2,FALSE) | Q80: Detection of anomalous patterns, for example in (encrypted) sessions, using machines learning
B82: Visualisation and output
B83: 2.7.29 | C83: Reporting | P83: =VLOOKUP(_Output!D1220,_Guidance!$B$2187:$C$2193,2,FALSE) | Q83: Custom reports for SOC customers and SOC analysts
B84: 2.7.30 | C84: Dashboards | P84: =VLOOKUP(_Output!D1221,_Guidance!$B$2187:$C$2193,2,FALSE) | Q84: Custom dashboards used by analysts and managers
B85: 2.7.31 | C85: Data visualization techniques | P85: =VLOOKUP(_Output!D1222,_Guidance!$B$2187:$C$2193,2,FALSE) | Q85: Graphing capabilities to support analysis
B86: 2.7.32 | C86: Data drilldowns | P86: =VLOOKUP(_Output!D1223,_Guidance!$B$2187:$C$2193,2,FALSE) | Q86: Drilldowns on graphs to quickly 'zoom in' on details of visual anomalies
B87: 2.7.33 | C87: Central analysis console | P87: =VLOOKUP(_Output!D1224,_Guidance!$B$2187:$C$2193,2,FALSE) | Q87: A central console used by SOC analysts
B88: 2.7.34 | C88: Advanced searching and querying | P88: =VLOOKUP(_Output!D1225,_Guidance!$B$2187:$C$2193,2,FALSE) | Q88: Searching capabilities that support finding specific information based on characteristics, especially useful for network threat hunting
C89: Completeness (%) | L89: =IFERROR(ROUND(_Output!K419,0),0) -> 0
B91: Comments and/or Remarks
B92: 2.8 | C92: Specify rationale for chosen values or any additional comments | K92: Maturity | L92: 2.1.1
L93: 2.1.2
L94: 2.2.1
L95: 2.2.2
L96: 2.3.1
L97: 2.3.2
L98: 2.3.3
L99: 2.3.4
L100: 2.4.1
L101: 2.4.2
L102: 2.4.3
L103: 2.4.4
L104: 2.4.5
... L113: 2.6.3
K115: Capability | L115: 2.7.1
L116: 2.7.2
L117: 2.7.3
L118: 2.7.4
L119: 2.7.5
L120: 2.7.6
...

Sheet Technology - EDR
B1: Technology
B3: 1. SIEM / UEBA
B4: 2. NDR
B5: 3. EDR
B6: 4. SOAR
A9: 3 | B9: Security Analytics Tooling | L9: Answer | N9: Importance | P9: Guidance | Q9: Remarks
B10: Maturity
B11: 3.1 | C11: Accountability
B12: 3.1.1 | C12: Has functional ownership of the solution been formally assigned? | P12: =VLOOKUP(_Output!D425,_Guidance!B1326:C1331,2,FALSE) | Q12: Functional ownership includes functional accountability
B13: 3.1.2 | C13: Has technical ownership of the solution been formally assigned? | P13: =VLOOKUP(_Output!D426,_Guidance!B1332:C1337,2,FALSE) | Q13: Technical ownership includes technical accountability
B14: 3.2 | C14: Documentation
B15: 3.2.1 | C15: Has the solution been technically documented? | P15: =VLOOKUP(_Output!D428,_Guidance!B1338:C1343,2,FALSE) | Q15: A technical description of the security analytics system components and configuration
B16: 3.2.2 | C16: Has the solution been functionally documented? | P16: =VLOOKUP(_Output!D429,_Guidance!B1344:C1349,2,FALSE) | Q16: A description of the EDR functional configuration (rules, alerts, thresholds, etc.)
B17: 3.3 | C17: Personnel & support
B18: 3.3.1 | C18: Is there dedicated personnel for support? | P18: =VLOOKUP(_Output!D431,_Guidance!B1350:C1355,2,FALSE) | Q18: Dedicated personnel should be in place to ensure that support is always available. Can also be staff with outsourced provider
B19: 3.3.2 | C19: Is the personnel for support formally trained? | P19: =VLOOKUP(_Output!D432,_Guidance!B1356:C1361,2,FALSE) | Q19: Training helps to jump start new hires, and to learn a proper way of working with the tool
B20: 3.3.3 | C20: Is the personnel for support certified? | P20: =VLOOKUP(_Output!D433,_Guidance!B1362:C1367,2,FALSE) | Q20: Certification demonstrates ability to handle the tooling properly
B21: 3.3.4 | C21: Is there a support contract for the solution? | P21: =VLOOKUP(_Output!D434,_Guidance!B1368:C1373,2,FALSE) | Q21: A support contract may cover on-site support, support availability, response times, escalation and full access to resources
B22: 3.4 | C22: Maintenance & configuration
B23: 3.4.1 | C23: Is the system regularly maintained? | P23: =VLOOKUP(_Output!D1054,_Guidance!B1374:C1379,2,FALSE) | Q23: Systems should be regularly maintained to keep up with the latest features and bug fixes
B24: 3.4.2 | C24: Is remote maintenance on the system managed? | P24: =VLOOKUP(_Output!D1055,_Guidance!B1380:C1385,2,FALSE) | Q24: Remote maintenance by a third party may be part of system maintenance procedures
B25: 3.4.3 | C25: Are maintenance & configuration updates executed through the change management process? | P25: =VLOOKUP(_Output!D1056,_Guidance!B1386:C1391,2,FALSE) | Q25: Maintenance and configuration updates should follow the formal change management process
B26: 3.4.4 | C26: Have you established maintenance windows? | P26: =VLOOKUP(_Output!D1057,_Guidance!B1392:C1397,2,FALSE) | Q26: Setting maintenance windows helps to structure the maintenance process and make it more predictable
B27: 3.4.5 | C27: Is maintenance performed using authorised and trusted tooling? | P27: =VLOOKUP(_Output!D1058,_Guidance!B1398:C1403,2,FALSE) | Q27: Performing maintenance with authorised and trusted tooling helps to ensure security and integrity of the system
B28: 3.5 | C28: Availability & Integrity
B29: 3.5.1 | C29: Is there high availability (HA) in place for the solution? | P29: =VLOOKUP(_Output!D436,_Guidance!B1404:C1409,2,FALSE) | Q29: Can be fully implemented HA, partially implemented, hot spare, etc. May not be applicable
B30: 3.5.2 | C30: Is there data backup / replication in place for the solution? | P30: =VLOOKUP(_Output!D437,_Guidance!B1410:C1415,2,FALSE) | Q30: May not be applicable to all EDR solutions
B31: 3.5.3 | C31: Is there configuration backup / replication in place for the solution? | P31: =VLOOKUP(_Output!D438,_Guidance!B1416:C1421,2,FALSE) | Q31: Configuration synchronization could be part of a HA setup
B32: 3.5.4 | C32: Is there a Disaster Recovery plan in place for this solution? | P32: =VLOOKUP(_Output!D439,_Guidance!B1422:C1427,2,FALSE) | Q32: A DR plan is required to restore service in case of catastrophic events
B33: 3.5.5 | C33: Is the Disaster Recovery plan regularly tested? | P33: =VLOOKUP(_Output!D440,_Guidance!B1428:C1433,2,FALSE) | Q33: Testing the DR plan is required to ensure that it is complete, functional and tasks and responsibilities for involved personnel are understood
B34: 3.5.6 | C34: Is there a separate development / test environment for this solution? | P34: =VLOOKUP(_Output!D441,_Guidance!B1434:C1439,2,FALSE) | Q34: A separate test environment allows for testing of new configurations before deployment in production
B35: 3.6 | C35: Confidentiality
B36: 3.6.1 | C36: Is access to the solution limited to authorized personnel? | P36: =VLOOKUP(_Output!D443,_Guidance!B1440:C1445,2,FALSE) | Q36: The analytics system will contain confidential information and information that possibly impacts employee privacy
B37: 3.6.2 | C37: Are access rights regularly reviewed and revoked if required? | P37: =VLOOKUP(_Output!D445,_Guidance!B1446:C1451,2,FALSE) | Q37: Revocation is part of normal employee termination. Special emergency revocation should be in place for suspected misuse
B38: 3.6.3 | C38: Is a break glass procedure in place? | P38: =VLOOKUP(_Output!D1140,_Guidance!B1452:C1457,2,FALSE) | Q38: A break glass procedure and account is required to gain access to the tooling even in case of major IT outages
B40: Capability
B41: 3.7 | C41: Specify which technological capabilities and artefacts are present and implemented:
B42: Technical capabilities | P42: =VLOOKUP(_Output!D448,_Guidance!$B$2187:$C$2193,2,FALSE)
B43: 3.7.1 | C43: OS support | P43: =VLOOKUP(_Output!D1226,_Guidance!$B$2187:$C$2193,2,FALSE) | Q43: Support for common OSs (e.g. Windows, Linux, OSX, etc.)
B44: 3.7.2 | C44: Mobile device support | P44: =VLOOKUP(_Output!D1227,_Guidance!$B$2187:$C$2193,2,FALSE) | Q44: Support for mobile devices (e.g. Android, IOS)
B45: 3.7.3 | C45: Physical, virtual & cloud deployment | P45: =VLOOKUP(_Output!D1228,_Guidance!$B$2187:$C$2193,2,FALSE) | Q45: Deployment across physical and virtual devices and cloud-based workloads increases coverage and visibility
B46: 3.7.4 | C46: Vulnerability patching | P46: =VLOOKUP(_Output!D1229,_Guidance!$B$2187:$C$2193,2,FALSE) | Q46: Remote patching of uncovered vulnerabilities. May be fully automated
B47: 3.7.5 | C47: Forensic information preservation | P47: =VLOOKUP(_Output!D1230,_Guidance!$B$2187:$C$2193,2,FALSE) | Q47: Forensic information preservation is a capability that supports security incident management and forensic investigation
B48: 3.7.6 | C48: Attack surface reduction | P48: =VLOOKUP(_Output!D1231,_Guidance!$B$2187:$C$2193,2,FALSE) | Q48: Attack surface reduction can be used as a preventative capability
B49: 3.7.7 | C49: Historic data retention | P49: =VLOOKUP(_Output!D1232,_Guidance!$B$2187:$C$2193,2,FALSE) | Q49: Historic data retention is especially important in threat hunting investigations. Multiple months of data should be retained
B50: 3.7.8 | C50: MITRE ATT&CK® identifier tagging | P50: =VLOOKUP(_Output!D1233,_Guidance!$B$2187:$C$2193,2,FALSE) | Q50: Add MITRE ATT&CK® tags to rules / analytics for mapping and hunting purposes
B51: 3.7.9 | C51: Memory analysis | P51: =VLOOKUP(_Output!D1234,_Guidance!$B$2187:$C$2193,2,FALSE) | Q51: Analysis of end-point memory
B52: 3.7.10 | C52: Correlation | P52: =VLOOKUP(_Output!D1235,_Guidance!$B$2187:$C$2193,2,FALSE) | Q52: Correlation of events with previously detected events
P53: =VLOOKUP(_Output!D452,_Guidance!$B$2187:$C$2193,2,FALSE)
B54: Prevention capabilities
B55: 3.7.11 | C55: Exploit prevention | P55: =VLOOKUP(_Output!D1236,_Guidance!$B$2187:$C$2193,2,FALSE) | Q55: Prevention of exploits being executed on the system
B56: 3.7.12 | C56: Fileless malware protection | P56: =VLOOKUP(_Output!D1237,_Guidance!$B$2187:$C$2193,2,FALSE) | Q56: Protection against malware running only in memory
B57: 3.7.13 | C57: Application whitelisting | P57: =VLOOKUP(_Output!D1239,_Guidance!$B$2187:$C$2193,2,FALSE) | Q57: Prevention of running unauthorised applications by means of allow listing
B58: 3.7.14 | C58: Ransomware protection | P58: =VLOOKUP(_Output!D1240,_Guidance!$B$2187:$C$2193,2,FALSE) | Q58: Protection against ransomware, for example with the used of controlled access to sensitive files and folders
B59: 3.7.15 | C59: Attack surface reduction | P59: =VLOOKUP(_Output!D1241,_Guidance!$B$2187:$C$2193,2,FALSE) | Q59: Attack surface reduction can be used to decrease the likelihood of compromise
B61: Detection capabilities [1] | P61: =VLOOKUP(_Output!D453,_Guidance!$B$2187:$C$2193,2,FALSE)
B62: 3.7.16 | C62: Vulnerability detection | P62: =VLOOKUP(_Output!D1242,_Guidance!$B$2187:$C$2193,2,FALSE) | Q62: Detection of vulnerabilities on the local end-point
B63: 3.7.17 | C63: Process execution monitoring | P63: =VLOOKUP(_Output!D1244,_Guidance!$B$2187:$C$2193,2,FALSE) | Q63: Detection of execution of potentially malicious processes and scripts
B64: 3.7.18 | C64: File system monitoring | P64: =VLOOKUP(_Output!D1246,_Guidance!$B$2187:$C$2193,2,FALSE) | Q64: Detection of file creation, deletion and or modification (including encryption)
B65: 3.7.19 | C65: Task & service monitoring | P65: =VLOOKUP(_Output!D1248,_Guidance!$B$2187:$C$2193,2,FALSE) | Q65: Detection of creation or modification of services and scheduled tasks
B66: 3.7.20 | C66: Network connection monitoring | P66: =VLOOKUP(_Output!D1250,_Guidance!$B$2187:$C$2193,2,FALSE) | Q66: Detection of potentially malicious network traffic
B67: 3.7.21 | C67: Registry monitoring | P67: =VLOOKUP(_Output!D1252,_Guidance!$B$2187:$C$2193,2,FALSE) | Q67: Detection of modifications to the system registry
B68: 3.7.22 | C68: User activity monitoring | P68: =VLOOKUP(_Output!D1254,_Guidance!$B$2187:$C$2193,2,FALSE) | Q68: Detection of user activity, including logon and logoff
B69: 3.7.23 | C69: Configuration monitoring | P69: =VLOOKUP(_Output!D1256,_Guidance!$B$2187:$C$2193,2,FALSE) | Q69: Detection of unauthorised changes to the local end-point configuration, including modifications to registry, files, services, tasks, drivers, etc.
B70: 3.7.24 | C70: Air-gaped end-point monitoring | P70: =VLOOKUP(_Output!D1258,_Guidance!$B$2187:$C$2193,2,FALSE) | Q70: Monitoring capabilities for end-points not connected to the corporate network
B71: 3.7.25 | C71: File reputation service | P71: =VLOOKUP(_Output!D1260,_Guidance!$B$2187:$C$2193,2,FALSE) | Q71: Detection of potentially malicious files using an (online) file reputation service
B72: 3.7.26 | C72: Deception techniques | P72: =VLOOKUP(_Output!D1262,_Guidance!$B$2187:$C$2193,2,FALSE) | Q72: Detection of adversaries by employing deception techniques (such as honey tokens) on end-points
B74: Remediation capabilities
B75: 3.7.27 | C75: URL filtering / blocking | P75: =VLOOKUP(_Output!D1264,_Guidance!$B$2187:$C$2193,2,FALSE) | Q75: Block traffic to specific URL
B76: 3.7.28 | C76: Web content filtering | P76: =VLOOKUP(_Output!D1265,_Guidance!$B$2187:$C$2193,2,FALSE) | Q76: Block specific web content
B77: 3.7.29 | C77: Machine isolation | P77: =VLOOKUP(_Output!D1266,_Guidance!$B$2187:$C$2193,2,FALSE) | Q77: Isolate a machine from the network
B78: 3.7.30 | C78: Process termination / suspension | P78: =VLOOKUP(_Output!D1267,_Guidance!$B$2187:$C$2193,2,FALSE) | Q78: Terminate or suspend a running process
B79: 3.7.31 | C79: File / registry key deletion | P79: =VLOOKUP(_Output!D1268,_Guidance!$B$2187:$C$2193,2,FALSE) | Q79: Delete local files or registry key (in case of Windows)
B80: 3.7.32 | C80: Forced user logoff | P80: =VLOOKUP(_Output!D1269,_Guidance!$B$2187:$C$2193,2,FALSE) | Q80: Force a user to log off to terminate any user-associated processes
B82: Integrations
B83: 3.7.33 | C83: Threat Intelligence integration | P83: =VLOOKUP(_Output!D1270,_Guidance!$B$2187:$C$2193,2,FALSE) | Q83: Integration of threat intelligence information (observables / IoCs) into the EDR tooling for reputation-based monitoring
B84: 3.7.34 | C84: Vulnerability intelligence integration | P84: =VLOOKUP(_Output!D1271,_Guidance!$B$2187:$C$2193,2,FALSE) | Q84: Integration of vulnerability intelligence information into the EDR for vulnerability monitoring purposes
B85: 3.7.35 | C85: Threat hunting integration - TTPs | P85: =VLOOKUP(_Output!D1272,_Guidance!$B$2187:$C$2193,2,FALSE) | Q85: Integration of the tooling into the threat hunting process to support threat hunting investigations on the TTP level
B86: 3.7.36 | C86: Threat hunting integration - Tools & artifacts | P86: =VLOOKUP(_Output!D1273,_Guidance!$B$2187:$C$2193,2,FALSE) | Q86: Integration of the tooling into the threat hunting process to support threat hunting investigations on the Tools & artifacts level
B87: 3.7.37 | C87: Threat hunting integration - Technical indicators | P87: =VLOOKUP(_Output!D1274,_Guidance!$B$2187:$C$2193,2,FALSE) | Q87: Integration of the tooling into the threat hunting process to support threat hunting investigations on the indicator level (IP, domain, hash)
B88: 3.7.38 | C88: Security incident management integration | P88: =VLOOKUP(_Output!D1275,_Guidance!$B$2187:$C$2193,2,FALSE) | Q88: Integration of the security incident management process to support incident investigation
B89: 3.7.39 | C89: SIEM integration | P89: =VLOOKUP(_Output!D1276,_Guidance!$B$2187:$C$2193,2,FALSE) | Q89: Integration with the SIEM tooling for centralised correlation
B90: 3.7.40 | C90: Malware sandbox integration | P90: =VLOOKUP(_Output!D1277,_Guidance!$B$2187:$C$2193,2,FALSE) | Q90: Detonate potential malware samples in a sandbox environment
B92: Rule-based detection
B93: 3.7.41 | C93: Online signature-based detection | P93: =VLOOKUP(_Output!D1278,_Guidance!$B$2187:$C$2193,2,FALSE) | Q93: Signature-based malware detection requiring an active internet connection
B94: 3.7.42 | C94: Offline signature-based detection | P94: =VLOOKUP(_Output!D1279,_Guidance!$B$2187:$C$2193,2,FALSE) | Q94: Signature-based malware detection not requiring an active internet connection
B95: 3.7.43 | C95: Custom rules | P95: =VLOOKUP(_Output!D1280,_Guidance!$B$2187:$C$2193,2,FALSE) | Q95: Creation of custom rules for the detection of specific Indicators of Attack
B97: Anomaly detection
B98: 3.7.44 | C98: Behavioural detection | P98: =VLOOKUP(_Output!D1281,_Guidance!$B$2187:$C$2193,2,FALSE) | Q98: Detection of potentially malicious behaviour using machine learning technologies
B100: Visualisation & output
B101: 3.7.45 | C101: Reporting | P101: =VLOOKUP(_Output!D1282,_Guidance!$B$2187:$C$2193,2,FALSE) | Q101: Custom reports for SOC customers and SOC analysts
B102: 3.7.46 | C102: Dashboards | P102: =VLOOKUP(_Output!D1283,_Guidance!$B$2187:$C$2193,2,FALSE) | Q102: Custom dashboards used by analysts and managers
B103: 3.7.47 | C103: Data visualization techniques | P103: =VLOOKUP(_Output!D1284,_Guidance!$B$2187:$C$2193,2,FALSE) | Q103: Graphing capabilities to support analysis
B104: 3.7.48 | C104: Data drilldowns | P104: =VLOOKUP(_Output!D1285,_Guidance!$B$2187:$C$2193,2,FALSE) | Q104: Drilldowns on graphs to quickly 'zoom in' on details of visual anomalies
B105: 3.7.49 | C105: Central analysis console | P105: =VLOOKUP(_Output!D1286,_Guidance!$B$2187:$C$2193,2,FALSE) | Q105: A central console used by SOC analysts
B106: 3.7.50 | C106: Advanced searching and querying | P106: =VLOOKUP(_Output!D1287,_Guidance!$B$2187:$C$2193,2,FALSE) | Q106: Searching capabilities that support finding specific information based on characteristics, especially useful for end-point threat hunting
C107: Completeness (%) | L107: =IFERROR(ROUND(_Output!K473,0),0) -> 0
B109: Comments and/or Remarks
B110: 3.8 | C110: Specify rationale for chosen values or any additional comments | K110: Maturity | L110: 3.1.1
L111: 3.1.2
...

Sheet Technology - A&O
B1: Technology
B3: 1. SIEM / UEBA
B4: 2. NDR
B5: 3. EDR
B6: 4. SOAR
A9: 4 | B9: Automation & Orchestration Tooling | L9: Answer | N9: Importance | P9: Guidance | Q9: Remarks
B10: Maturity
B11: 4.1 | C11: Accountability
B12: 4.1.1 | C12: Has functional ownership of the solution been formally assigned? | P12: =VLOOKUP(_Output!D479,_Guidance!B1460:C1465,2,FALSE) | Q12: Functional ownership includes functional accountability
B13: 4.1.2 | C13: Has technical ownership of the solution been formally assigned? | P13: =VLOOKUP(_Output!D480,_Guidance!B1466:C1471,2,FALSE) | Q13: Technical ownership includes technical accountability
B14: 4.2 | C14: Documentation
B15: 4.2.1 | C15: Has the solution been technically documented? | P15: =VLOOKUP(_Output!D482,_Guidance!B1472:C1477,2,FALSE) | Q15: A technical description of the automation & orchestration system components and configuration
B16: 4.2.2 | C16: Has the solution been functionally documented? | P16: =VLOOKUP(_Output!D483,_Guidance!B1478:C1483,2,FALSE) | Q16: A description of the automation & orchestration system functional configuration (workflows, integrations, etc.)
B17: 4.3 | C17: Personnel & support
B18: 4.3.1 | C18: Is there dedicated personnel for support? | P18: =VLOOKUP(_Output!D485,_Guidance!B1484:C1489,2,FALSE) | Q18: Dedicated personnel should be in place to ensure that support is always available. Can also be staff with outsourced provider
B19: 4.3.2 | C19: Is the personnel for support formally trained? | P19: =VLOOKUP(_Output!D486,_Guidance!B1490:C1495,2,FALSE) | Q19: Training helps to jump start new hires, and to learn a proper way of working with the tool
B20: 4.3.3 | C20: Is the personnel for support certified? | P20: =VLOOKUP(_Output!D487,_Guidance!B1496:C1501,2,FALSE) | Q20: Certification demonstrates ability to handle the tooling properly
B21: 4.3.4 | C21: Is there a support contract for the solution? | P21: =VLOOKUP(_Output!D488,_Guidance!B1502:C1507,2,FALSE) | Q21: A support contract may cover on-site support, support availability, response times, escalation and full access to resources
B22: 4.4 | C22: Maintenance & configuration
B23: 4.4.1 | C23: Is the system regularly maintained? | P23: =VLOOKUP(_Output!D1059,_Guidance!B1508:C1513,2,FALSE) | Q23: Systems should be regularly maintained to keep up with the latest features and bug fixes
B24: 4.4.2 | C24: Is remote maintenance on the system managed? | P24: =VLOOKUP(_Output!D1060,_Guidance!B1514:C1519,2,FALSE) | Q24: Remote maintenance by a third party may be part of system maintenance procedures
B25: 4.4.3 | C25: Are maintenance & configuration updates executed through the change management process? | P25: =VLOOKUP(_Output!D1061,_Guidance!B1520:C1525,2,FALSE) | Q25: Maintenance and configuration updates should follow the formal change management process
B26: 4.4.4 | C26: Have you established maintenance windows? | P26: =VLOOKUP(_Output!D1062,_Guidance!B1526:C1531,2,FALSE) | Q26: Setting maintenance windows helps to structure the maintenance process and make it more predictable
B27: 4.4.5 | C27: Is maintenance performed using authorised and trusted tooling? | P27: =VLOOKUP(_Output!D1063,_Guidance!B1532:C1537,2,FALSE) | Q27: Performing maintenance with authorised and trusted tooling helps to ensure security and integrity of the system
B28: 4.5 | C28: Availability & Integrity
B29: 4.5.1 | C29: Is there high availability (HA) in place for the solution? | P29: =VLOOKUP(_Output!D490,_Guidance!B1538:C1543,2,FALSE) | Q29: Can be fully implemented HA, partially implemented, hot spare, etc.
B30: 4.5.2 | C30: Is there data backup / replication in place for the solution? | P30: =VLOOKUP(_Output!D491,_Guidance!B1544:C1549,2,FALSE) | Q30: May not be required for this particular solution
B31: 4.5.3 | C31: Is there configuration backup / replication in place for the solution? | P31: =VLOOKUP(_Output!D492,_Guidance!B1550:C1555,2,FALSE) | Q31: Configuration synchronization could be part of a HA setup
B32: 4.5.4 | C32: Is there a Disaster Recovery plan in place for this solution? | P32: =VLOOKUP(_Output!D493,_Guidance!B1556:C1561,2,FALSE) | Q32: A DR plan is required to restore service in case of catastrophic events
B33: 4.5.5 | C33: Is the Disaster Recovery plan regularly tested? | P33: =VLOOKUP(_Output!D494,_Guidance!B1562:C1567,2,FALSE) | Q33: Testing the DR plan is required to ensure that it is complete, functional and tasks and responsibilities for involved personnel are understood
B34: 4.5.6 | C34: Is there a separate development / test environment for this solution? | P34: =VLOOKUP(_Output!D495,_Guidance!B1568:C1573,2,FALSE) | Q34: A separate test environment allows for testing of new configurations before deployment in production
B35: 4.6 | C35: Confidentiality
B36: 4.6.1 | C36: Is access to the solution limited to authorized personnel? | P36: =VLOOKUP(_Output!D497,_Guidance!B1574:C1579,2,FALSE) | Q36: The automation system may have automated actions that can impact the usage of systems and should be restricted
B37: 4.6.2 | C37: Are access rights regularly reviewed and revoked if required? | P37: =VLOOKUP(_Output!D499,_Guidance!B1580:C1585,2,FALSE) | Q37: Revocation is part of normal employee termination. Special emergency revocation should be in place for suspected misuse
B38: 4.6.3 | C38: Is a break glass procedure in place? | P38: =VLOOKUP(_Output!D1141,_Guidance!B1586:C1591,2,FALSE) | Q38: A break glass procedure and account is required to gain access to the tooling even in case of major IT outages
B40: Capability
B41: 4.7 | C41: Specify which technological capabilities and artefacts are present and implemented:
B42: Technical capabilities
B43: 4.7.1 | C43: Historical event matching | P43: =VLOOKUP(_Output!D507,_Guidance!$B$2187:$C$2193,2,FALSE) | Q43: Contextualize potential incidents using similar historical events
B44: 4.7.2 | C44: Risk-based event prioritization | P44: =VLOOKUP(_Output!D509,_Guidance!$B$2187:$C$2193,2,FALSE) | Q44: Risk-based prioritization of security events using contextualized information
B45: 4.7.3 | C45: Ticket workflow support | P45: =VLOOKUP(_Output!D516,_Guidance!$B$2187:$C$2193,2,FALSE) | Q45: Automated ticket creation and workflow support
B47: Data integrations
B48: 4.7.4 | C48: SIEM data integration | P48: =VLOOKUP(_Output!D502,_Guidance!$B$2187:$C$2193,2,FALSE) | Q48: The automation & orchestration tool receives events from the SIEM system
B49: 4.7.5 | C49: Threat intelligence integration | P49: =VLOOKUP(_Output!D503,_Guidance!$B$2187:$C$2193,2,FALSE) | Q49: Contextualize potential incidents using threat intelligence
B50: 4.7.6 | C50: Asset context integration | P50: =VLOOKUP(_Output!D504,_Guidance!$B$2187:$C$2193,2,FALSE) | Q50: Contextualize potential incidents using asset information
B51: 4.7.7 | C51: Identity context integration | P51: =VLOOKUP(_Output!D505,_Guidance!$B$2187:$C$2193,2,FALSE) | Q51: Contextualize potential incidents using user information
B52: 4.7.8 | C52: Vulnerability management integration | P52: =VLOOKUP(_Output!D506,_Guidance!$B$2187:$C$2193,2,FALSE) | Q52: Contextualize potential incidents using vulnerability management information
B54: Response integrations
B55: 4.7.9 | C55: Knowledge base integration | P55: =VLOOKUP(_Output!D508,_Guidance!$B$2187:$C$2193,2,FALSE) | Q55: Automatically update the knowledge base using event information
B56: 4.7.10 | C56: Firewall integration | P56: =VLOOKUP(_Output!D510,_Guidance!$B$2187:$C$2193,2,FALSE) | Q56: Automated remediation by blocking attackers on the firewall
B57: 4.7.11 | C57: NDR integration | P57: =VLOOKUP(_Output!D511,_Guidance!$B$2187:$C$2193,2,FALSE) | Q57: Automated remediation by blocking attackers in the network
B58: 4.7.12 | C58: EDR integration | P58: =VLOOKUP(_Output!D1288,_Guidance!$B$2187:$C$2193,2,FALSE) | Q58: Automated remediation by blocking attackers on the end-point
B59: 4.7.13 | C59: Email protection integration | P59: =VLOOKUP(_Output!D512,_Guidance!$B$2187:$C$2193,2,FALSE) | Q59: Automated remediation by blocking email senders
B60: 4.7.14 | C60: Malware protection integration | P60: =VLOOKUP(_Output!D513,_Guidance!$B$2187:$C$2193,2,FALSE) | Q60: Automated remediation by quarantining malware and scanning end-points for malware threats
B61: 4.7.15 | C61: Sandbox integration | P61: =VLOOKUP(_Output!D514,_Guidance!$B$2187:$C$2193,2,FALSE) | Q61: Automated delivery of malware samples to sandbox environments for extensive analysis
B62: 4.7.16 | C62: Active Directory / IAM integration | P62: =VLOOKUP(_Output!D515,_Guidance!$B$2187:$C$2193,2,FALSE) | Q62: Automated locking and suspension of user accounts or revocation of access rights based on event outcome
B63: 4.7.17 | C63: SIEM integration | P63: =VLOOKUP(_Output!D1289,_Guidance!$B$2187:$C$2193,2,FALSE) | Q63: Querying SIEM to obtain information for ticket context or automated triage
B65: Playbooks
B66: 4.7.18 | C66: Standard playbooks | P66: =VLOOKUP(_Output!D1290,_Guidance!$B$2187:$C$2193,2,FALSE) | Q66: Application of standard (out of the box) response playbooks in the SOAR
B67: 4.7.19 | C67: Customised playbooks | P67: =VLOOKUP(_Output!D1291,_Guidance!$B$2187:$C$2193,2,FALSE) | Q67: Application of customized and fully response customized playbooks in the SOAR
B68: 4.7.20 | C68: Playbook automation | P68: =VLOOKUP(_Output!D1292,_Guidance!B1592:C1598,2,FALSE) | Q68: Application of automation in playbooks
B69: 4.7.21 | C69: Playbook development process | P69: =VLOOKUP(_Output!D1293,_Guidance!$B$2187:$C$2193,2,FALSE) | Q69: A development, refinement and life cycle management process for SOC playbooks for usage in SOAR
B71: Visualisation and ouput
B72: 4.7.22 | C72: Reporting | P72: =VLOOKUP(_Output!D1294,_Guidance!$B$2187:$C$2193,2,FALSE) | Q72: Custom reports for SOC customers and SOC analysts
B73: 4.7.23 | C73: Dashboards | P73: =VLOOKUP(_Output!D1295,_Guidance!$B$2187:$C$2193,2,FALSE) | Q73: Custom dashboards used by analysts and managers
B74: 4.7.24 | C74: Performance tracking | P74: =VLOOKUP(_Output!D520,_Guidance!$B$2187:$C$2193,2,FALSE) | Q74: Application of KPIs and metrics to ticket workflow
C75: Completeness (%) | L75: =IFERROR(ROUND(_Output!K522,0),0) -> 0
B77: Comments and/or Remarks
B78: 4.8 | C78: Specify rationale for chosen values or any additional comments | L78: 4.1.1
L79: 4.1.2
L80: 4.2.1
L81: 4.2.2
L82: 4.3.1
L83: 4.3.2
L84: 4.3.3
L85: 4.3.4
L86: 4.4.1
L87: 4.4.2
L88: 4.4.3
L89: 4.4.4
L90: 4.4.5
... L124: 4.7.24

Sheet Services - SCM
B1: Services
B3: 1. Security Monitoring | G3: 5. Threat Hunting
B4: 2. Security Incident Management | G4: 6. Vulnerability Management
B5: 3. Security Analysis & Forensics | G5: 7. Log Management
B6: 4. Threat Intelligence
A9: 1 | B9: Security Monitoring | L9: Answer | N9: Importance | P9: Guidance | Q9: Remarks
B10: Maturity
B11: 1.1 | C11: Have you formally described the security monitoring service? | P11: =VLOOKUP(_Output!D528,_Guidance!B1602:C1607,2,FALSE) | Q11: A service description should be in place
B12: 1.2 | C12: Please specify elements of the security monitoring service document:
B13: 1.2.1 | C13: Key performance indicators | Q13: Indicators to establish the performance of the service
B14: 1.2.2 | C14: Quality indicators | Q14: Indicators to establish the quality of service delivery
B15: 1.2.3 | C15: Service dependencies | Q15: A clear understanding of which people / process / technologies are required for adequate service delivery
B16: 1.2.4 | C16: Service levels | Q16: Agreements on minimum performance, capacity, availability, etc.
B17: 1.2.5 | C17: Hours of operation | Q17: The operational hours for this service (e.g. 24/7)
B18: 1.2.6 | C18: Service customers and stakeholders | Q18: The customers and stakeholders for this service (e.g. IT management)
B19: 1.2.7 | C19: Purpose | Q19: The purpose and objectives for this service
B20: 1.2.8 | C20: Service input / triggers | Q20: The service input: what triggers this service to run?
B21: 1.2.9 | C21: Service output / deliverables | Q21: The service output: what does the service deliver? Can be tangible (e.g. reports) or intangible (e.g. situational awareness )
B22: 1.2.10 | C22: Service activities | Q22: Which activities are carried out within the scope of the service?
B23: 1.2.11 | C23: Service roles & responsibilities | Q23: Which roles and responsibilities apply to this service?
C24: Completeness | L24: =VLOOKUP(SUM(_Output!D538:D548),_SUM_Completeness!A84:B95,2,FALSE) -> Incomplete | Q24: Use this outcome to determine the score for 1.2
B25: 1.3 | C25: Is the service measured for quality? | P25: =VLOOKUP(_Output!D549,_Guidance!B1608:C1613,2,FALSE) | Q25: Are the quality indicators from the previous questions used for reporting on the service?
B26: 1.4 | C26: Is the service measured for service delivery in accordance with service levels? | P26: =VLOOKUP(_Output!D550,_Guidance!B1614:C1619,2,FALSE) | Q26: Service levels should be used to formally commit the SOC to service delivery
B27: 1.5 | C27: Are customers and/or stakeholders regularly updated about the service? | P27: =VLOOKUP(_Output!D551,_Guidance!B1620:C1625,2,FALSE) | Q27: Changes to the service scope, delivery, etc.
B28: 1.6 | C28: Is there a contractual agreement between the SOC and the customers? | P28: =VLOOKUP(_Output!D552,_Guidance!B1626:C1631,2,FALSE) | Q28: Contractual agreements should also cover penalties
B29: 1.7 | C29: Is sufficient personnel allocated to the process to ensure required service delivery? | P29: =VLOOKUP(_Output!D553,_Guidance!B1632:C1637,2,FALSE) | Q29: Allocation of dedicated personnel will ensure highest service quality
B30: 1.8 | C30: Is the service aligned with other relevant processes? | P30: =VLOOKUP(_Output!D554,_Guidance!B1638:C1643,2,FALSE) | Q30: e.g. alignment with configuration management, incident management, etc.
B31: 1.9 | C31: Is there a incident resolution / service continuity process in place for this service? | P31: =VLOOKUP(_Output!D555,_Guidance!B1644:C1649,2,FALSE) | Q31: Service continuity is important to comply with contractual agreements, even in case of major incidents
B32: 1.10 | C32: Has a set of procedures been created for this service? | P32: =VLOOKUP(_Output!D557,_Guidance!B1650:C1655,2,FALSE) | Q32: Procedures support process standardization and quality. Personnel should be trained to use procedures correctly and structurally
B33: 1.11 | C33: Is there an onboarding and offloading procedure for this service? | P33: =VLOOKUP(_Output!D1065,_Guidance!B1656:C1661,2,FALSE) | Q33: Customer onboarding and offloading procedures support efficient service delivery and ensure customers are (dis)connected properly
B34: 1.12 | C34: Are best practices applied to the service? | P34: =VLOOKUP(_Output!D558,_Guidance!B1662:C1667,2,FALSE) | Q34: Best practices should be used to optimize this service
B35: 1.13 | C35: Are use cases used in the security monitoring service? | P35: =VLOOKUP(_Output!D559,_Guidance!B1668:C1673,2,FALSE) | Q35: e.g. user login brute-force, denial of service, non-compliance, etc.
B36: 1.14 | C36: Is process data gathered for prediction of service performance? | P36: =VLOOKUP(_Output!D568,_Guidance!B1674:C1679,2,FALSE) | Q36: Service performance measurement requires establishment of performance goals
B37: 1.15 | C37: Is the service continuously being improved based on improvement goals? | P37: =VLOOKUP(_Output!D569,_Guidance!B1680:C1685,2,FALSE) | Q37: Improvement based on based evaluation, (maturity) assessment, tests, etc.
B39: Capability
B40: 1.16 | C40: Please specify capabilities of the security monitoring service:
B41: 1.16.1 | C41: Early detection | P41: =VLOOKUP(_Output!D571,_Guidance!$B$2187:$C$2193,2,FALSE) | Q41: Capability to detect incidents in an early stage
B42: 1.16.2 | C42: Intrusion detection | P42: =VLOOKUP(_Output!D572,_Guidance!$B$2187:$C$2193,2,FALSE) | Q42: Capability to detect intrusion attempts
B43: 1.16.3 | C43: Exfiltration detection | P43: =VLOOKUP(_Output!D573,_Guidance!$B$2187:$C$2193,2,FALSE) | Q43: Capability to detect information leaving the organization
B44: 1.16.4 | C44: Subtle event detection | P44: =VLOOKUP(_Output!D574,_Guidance!$B$2187:$C$2193,2,FALSE) | Q44: Capability to detect slight changes in systems, applications or network that may indicate malicious behavior
B45: 1.16.5 | C45: Malware detection | P45: =VLOOKUP(_Output!D575,_Guidance!$B$2187:$C$2193,2,FALSE) | Q45: Capability to detect malware in the infrastructure
B46: 1.16.6 | C46: Anomaly detection | P46: =VLOOKUP(_Output!D577,_Guidance!$B$2187:$C$2193,2,FALSE) | Q46: Capability to detect anomalies
B47: 1.16.7 | C47: Real-time detection | P47: =VLOOKUP(_Output!D578,_Guidance!$B$2187:$C$2193,2,FALSE) | Q47: Can also be near real-time (e.g. 15 minutes delay)
B48: 1.16.8 | C48: Alerting & notification | P48: =VLOOKUP(_Output!D579,_Guidance!$B$2187:$C$2193,2,FALSE) | Q48: Capability to automatically send alerts for all security monitoring components
B49: 1.16.9 | C49: Status monitoring | P49: =VLOOKUP(_Output!D580,_Guidance!$B$2187:$C$2193,2,FALSE) | Q49: Monitoring of the status of the system
B50: 1.16.10 | C50: Perimeter monitoring | P50: =VLOOKUP(_Output!D581,_Guidance!$B$2187:$C$2193,2,FALSE) | Q50: Monitoring of the network perimeter for attempted intrusions and exfiltration
B51: 1.16.11 | C51: Host monitoring | P51: =VLOOKUP(_Output!D582,_Guidance!$B$2187:$C$2193,2,FALSE) | Q51: Monitoring of endpoints in the networks (servers, clients, etc.)
B52: 1.16.12 | C52: Network & traffic monitoring | P52: =VLOOKUP(_Output!D583,_Guidance!$B$2187:$C$2193,2,FALSE) | Q52: Monitoring of network and traffic flows and anomalies
B53: 1.16.13 | C53: Access & usage monitoring | P53: =VLOOKUP(_Output!D584,_Guidance!$B$2187:$C$2193,2,FALSE) | Q53: Monitoring of access attempts
B54: 1.16.14 | C54: User / identity monitoring | P54: =VLOOKUP(_Output!D585,_Guidance!$B$2187:$C$2193,2,FALSE) | Q54: Monitoring of user actions
B55: 1.16.15 | C55: Application & service monitoring | P55: =VLOOKUP(_Output!D586,_Guidance!$B$2187:$C$2193,2,FALSE) | Q55: Monitoring of applications & services
B56: 1.16.16 | C56: Behavior monitoring | P56: =VLOOKUP(_Output!D587,_Guidance!$B$2187:$C$2193,2,FALSE) | Q56: Monitoring of behavior against baselines (can be host, network and user behavior)
B57: 1.16.17 | C57: Database monitoring | P57: =VLOOKUP(_Output!D588,_Guidance!$B$2187:$C$2193,2,FALSE) | Q57: Monitoring of databases
... B64: 1.16.24 | C64: Coverage | P64: =VLOOKUP(_Output!D595,_Guidance!$B$2187:$C$2193,2,FALSE) | Q64: How well does the security monitoring service cover your assets? This includes SIEM asset coverage and IDPS coverage
B65: 1.16.25 | C65: Cloud monitoring | P65: =VLOOKUP(_Output!D973,_Guidance!$B$2187:$C$2193,2,FALSE) | Q65: Monitoring of private and public cloud usage: SAAS, IAAS and PAAS
B66: 1.16.26 | C66: Mobile device monitoring | P66: =VLOOKUP(_Output!D974,_Guidance!$B$2187:$C$2193,2,FALSE) | Q66: Monitoring of corporate owned mobile devices or mobile devices containing corporate information
C67: Completeness (%) | L67: =IFERROR(ROUND(_Output!K597,0),0) -> 0
B69: Comments and/or Remarks
B70: 1.17 | C70: Specify rationale for chosen values or any additional comments | K70: Maturity | L70: 1.1
L71: 1.3
L72: 1.4
L73: 1.5
L74: 1.6
L75: 1.7
L76: 1.8
L77: 1.9
L78: 1.10
L79: 1.11
L80: 1.12
L81: 1.13
L82: 1.14
L83: 1.15
K85: Capability | L85: 1.16.1
L86: 1.16.2
L87: 1.16.3
L88: 1.16.4
L89: 1.16.5
L90: 1.16.6
L91: 1.16.7
L92: 1.16.8
L93: 1.16.9
L94: 1.16.10
L95: 1.16.11
L96: 1.16.12
L97: 1.16.13
... L110: 1.16.26

Sheet Services - SIM
B1: Services
B3: 1. Security Monitoring | G3: 5. Threat Hunting
B4: 2. Security Incident Management | G4: 6. Vulnerability Management
B5: 3. Security Analysis & Forensics | G5: 7. Log Management
B6: 4. Threat Intelligence
A9: 2 | B9: Security Incident Management | L9: Answer | N9: Importance | P9: Guidance | Q9: Remarks
B10: Maturity
B11: 2.1 | C11: Have you adopted a maturity assessment methodology for Security Incident Management?
B12: 2.1.1 | C12: If yes, please specify the methodology | Q12: e.g., SOC-CMM 4CERT, SIM3, CREST, etc.
B13: 2.1.2 | C13: If yes, please specify the maturity level (can have up to 2 digits) | Q13: Please convert to a 5-point scale if required. For example: 3.6 on a 4-point scale = 4.5 on a 5-point scale
C14: If yes, skip directly to 2.17 (capabilities) | Q14: The score in 2.1.2 overrules any maturity scoring in this section
B15: 2.2 | C15: Have you adopted a standard for the Security Incident Management process? | P15: =VLOOKUP(_Output!D605,_Guidance!B1688:C1693,2,FALSE) | Q15: e.g. NIST 800-62r1, CERT handbook, etc.
B16: 2.3 | C16: Have you formally described the security incident management process? | P16: =VLOOKUP(_Output!D606,_Guidance!B1694:C1699,2,FALSE) | Q16: A service description should be in place
B17: 2.4 | C17: Please specify elements of the security incident management document:
B18: 2.4.1 | C18: Security incident definition | Q18: A clear and unambiguous definition of a security incident
B19: 2.4.2 | C19: Service levels | Q19: e.g. response times
B20: 2.4.3 | C20: Workflow | Q20: The process steps that are part of the security incident management process (e.g. detection, triage, etc.)
B21: 2.4.4 | C21: Decision tree | Q21: Decision tree for escalation and starting of the process
B22: 2.4.5 | C22: Hours of operation | Q22: When can the security incident response process be started?
B23: 2.4.6 | C23: Service customers and stakeholders | Q23: The customers and stakeholders for this service (e.g. IT management)
B24: 2.4.7 | C24: Purpose | Q24: The purpose and objectives for this service
B25: 2.4.8 | C25: Service input / triggers | Q25: The service input: what triggers this service to run?
B26: 2.4.9 | C26: Service output / deliverables | Q26: The service output: what does the service deliver? Can be tangible (e.g. reports) or intangible (e.g. situational awareness )
B27: 2.4.10 | C27: Service activities | Q27: Which activities are carried out within the scope of the service?
B28: 2.4.11 | C28: Service roles & responsibilities | Q28: Which roles and responsibilities apply to this service?
C29: Completeness | L29: =VLOOKUP(SUM(_Output!D608:D618),_SUM_Completeness!A113:B124,2,FALSE) -> Incomplete | Q29: Use this outcome to determine the score for 2.4
B30: 2.5 | C30: Is the service measured for quality? | P30: =VLOOKUP(_Output!D619,_Guidance!B1700:C1705,2,FALSE) | Q30: Are the quality indicators from the previous questions used for reporting on the service?
B31: 2.6 | C31: Is the service measured for service delivery in accordance with service levels? | P31: =VLOOKUP(_Output!D620,_Guidance!B1706:C1711,2,FALSE) | Q31: Service levels should be used to formally commit the SOC to service delivery
B32: 2.7 | C32: Are customers and/or stakeholders regularly updated about the service? | P32: =VLOOKUP(_Output!D621,_Guidance!B1712:C1717,2,FALSE) | Q32: Changes to the service scope, delivery, etc.
B33: 2.8 | C33: Is there a contractual agreement between the SOC and the customers? | P33: =VLOOKUP(_Output!D625,_Guidance!B1718:C1723,2,FALSE) | Q33: Contractual agreements should also cover penalties
B34: 2.9 | C34: Is sufficient personnel allocated to the process to ensure required service delivery? | P34: =VLOOKUP(_Output!D626,_Guidance!B1724:C1729,2,FALSE) | Q34: Allocation of dedicated personnel will ensure highest service quality
B35: 2.10 | C35: Is the service aligned with other relevant processes? | P35: =VLOOKUP(_Output!D627,_Guidance!B1730:C1735,2,FALSE) | Q35: e.g. alignment with configuration management, incident management, etc.
B36: 2.11 | C36: Is the incident response team authorized to perform (invasive) actions when required? | P36: =VLOOKUP(_Output!D628,_Guidance!B1736:C1741,2,FALSE) | Q36: This is a mandate issue. The team should have mandate beforehand to optimize incident response times
B37: 2.12 | C37: Is there an onboarding and offloading procedure for this service? | P37: =VLOOKUP(_Output!D1066,_Guidance!B1742:C1747,2,FALSE) | Q37: Customer onboarding and offloading procedures support efficient service delivery and ensure customers are (dis)connected properly
B38: 2.13 | C38: Are best practices applied to the service? | P38: =VLOOKUP(_Output!D631,_Guidance!B1748:C1753,2,FALSE) | Q38: Best practices should be used to optimize this service
B39: 2.14 | C39: Is the service supported by predefined workflows or scenarios? | P39: =VLOOKUP(_Output!D632,_Guidance!B1754:C1759,2,FALSE) | Q39: Workflows and scenario's can be used to structure follow-up and determine expected incident progression
B40: 2.15 | C40: Is process data gathered for prediction of service performance? | P40: =VLOOKUP(_Output!D633,_Guidance!B1760:C1765,2,FALSE) | Q40: Service performance measurement requires establishment of performance goals
B41: 2.16 | C41: Is the service continuously being improved based on improvement goals? | P41: =VLOOKUP(_Output!D634,_Guidance!B1766:C1771,2,FALSE) | Q41: Improvement based on based evaluation, (maturity) assessment, tests, etc.
B42: Capability
B43: 2.17 | C43: Please specify capabilities and artefacts of the security incident management service:
B44: 2.17.1 | C44: Incident logging procedure | P44: =VLOOKUP(_Output!D637,_Guidance!$B$2187:$C$2193,2,FALSE) | Q44: Part of preparation procedures
B45: 2.17.2 | C45: Incident resolution procedure | P45: =VLOOKUP(_Output!D638,_Guidance!$B$2187:$C$2193,2,FALSE) | Q45: Part of preparation procedures. Likely involves a checklist and a workflow for incident handling
B46: 2.17.3 | C46: Incident investigation procedure | P46: =VLOOKUP(_Output!D639,_Guidance!$B$2187:$C$2193,2,FALSE) | Q46: Part of preparation procedures. Includes triage procedure and investigation / analysis procedures
B47: 2.17.4 | C47: Escalation procedure | P47: =VLOOKUP(_Output!D640,_Guidance!$B$2187:$C$2193,2,FALSE) | Q47: Part of preparation procedures
B48: 2.17.5 | C48: Evidence collection procedure | P48: =VLOOKUP(_Output!D641,_Guidance!$B$2187:$C$2193,2,FALSE) | Q48: Part of preparation procedures
B49: 2.17.6 | C49: Incident containment procedures | P49: =VLOOKUP(_Output!D642,_Guidance!$B$2187:$C$2193,2,FALSE) | Q49: Part of preparation procedures. Can be based on RE&CT framework[1]
B50: 2.17.7 | C50: IR Training | P50: =VLOOKUP(_Output!D643,_Guidance!$B$2187:$C$2193,2,FALSE) | Q50: Preparation exercises to determine service effectiveness
B51: 2.17.8 | C51: Table-top exercises | P51: =VLOOKUP(_Output!D644,_Guidance!$B$2187:$C$2193,2,FALSE) | Q51: Preparation exercises to determine service effectiveness
B52: 2.17.9 | C52: Red team / blue team exercises | P52: =VLOOKUP(_Output!D645,_Guidance!$B$2187:$C$2193,2,FALSE) | Q52: Preparation exercises to determine service effectiveness
B53: 2.17.10 | C53: RACI matrix | P53: =VLOOKUP(_Output!D646,_Guidance!$B$2187:$C$2193,2,FALSE) | Q53: Matrix with Responsibility, Accountability and Consulted and Informed entities for the process
B54: 2.17.11 | C54: Response authorization | P54: =VLOOKUP(_Output!D647,_Guidance!$B$2187:$C$2193,2,FALSE) | Q54: Authorization from senior management to take any action required for incident mitigation (e.g. disconnect systems)
B55: 2.17.12 | C55: Incident template | P55: =VLOOKUP(_Output!D648,_Guidance!$B$2187:$C$2193,2,FALSE) | Q55: Templates for security incident management registration
... B58: 2.17.15 | C58: Priority assignment | P58: =VLOOKUP(_Output!D651,_Guidance!$B$2187:$C$2193,2,FALSE) | Q58: Assignment of priority to the incident, part of impact assessment
B59: 2.17.16 | C59: Severity assignment | P59: =VLOOKUP(_Output!D653,_Guidance!$B$2187:$C$2193,2,FALSE) | Q59: Assignment of severity to the incident, part of impact assessment
B60: 2.17.17 | C60: Categorization | P60: =VLOOKUP(_Output!D655,_Guidance!$B$2187:$C$2193,2,FALSE) | Q60: Categorization of the incident. For example, the VERIS framework could be used for classification
B61: 2.17.18 | C61: Critical bridge | P61: =VLOOKUP(_Output!D656,_Guidance!$B$2187:$C$2193,2,FALSE) | Q61: A communication bridge for continuous alignment of employees involved in security incident management
B62: 2.17.19 | C62: War room | P62: =VLOOKUP(_Output!D657,_Guidance!$B$2187:$C$2193,2,FALSE) | Q62: A dedicated facility for coordination of security incidents
B63: 2.17.20 | C63: Communication plan & email templates | P63: =VLOOKUP(_Output!D658,_Guidance!$B$2187:$C$2193,2,FALSE) | Q63: Standardized plans and templates for communication. Includes reachability in case of emergency and outreach to customers
B64: 2.17.21 | C64: Backup communication technology | P64: =VLOOKUP(_Output!D659,_Guidance!$B$2187:$C$2193,2,FALSE) | Q64: Backup communication technology in case of failure of primary means. Includes internet access, email systems and phones
B65: 2.17.22 | C65: Secure communication channels | P65: =VLOOKUP(_Output!D660,_Guidance!$B$2187:$C$2193,2,FALSE) | Q65: Encrypted and secure communications (includes email and phones) that can be used during incident response
B66: 2.17.23 | C66: (dedicated) information sharing platform | P66: =VLOOKUP(_Output!D661,_Guidance!$B$2187:$C$2193,2,FALSE) | Q66: A platform for sharing information regarding the security incident
B67: 2.17.24 | C67: Change management integration | P67: =VLOOKUP(_Output!D662,_Guidance!$B$2187:$C$2193,2,FALSE) | Q67: Integration with the change management process for any actions taken in the security incident management process
B68: 2.17.25 | C68: Malware extraction & analysis | P68: =VLOOKUP(_Output!D663,_Guidance!$B$2187:$C$2193,2,FALSE) | Q68: Extraction and analysis of malware
B69: 2.17.26 | C69: On-site incident response | P69: =VLOOKUP(_Output!D664,_Guidance!$B$2187:$C$2193,2,FALSE) | Q69: Localized incident response capability
B70: 2.17.27 | C70: Remote incident response | P70: =VLOOKUP(_Output!D666,_Guidance!$B$2187:$C$2193,2,FALSE) | Q70: Remote incident response capability
B71: 2.17.28 | C71: Third-party escalation | P71: =VLOOKUP(_Output!D668,_Guidance!$B$2187:$C$2193,2,FALSE) | Q71: Escalation process to third parties (vendors, partners, etc.)
B72: 2.17.29 | C72: Evaluation template | P72: =VLOOKUP(_Output!D670,_Guidance!$B$2187:$C$2193,2,FALSE) | Q72: A template for post-incident evaluation
B73: 2.17.30 | C73: Reporting template | P73: =VLOOKUP(_Output!D671,_Guidance!$B$2187:$C$2193,2,FALSE) | Q73: A template for reporting on the security incident
B74: 2.17.31 | C74: Incident closure | P74: =VLOOKUP(_Output!D672,_Guidance!$B$2187:$C$2193,2,FALSE) | Q74: Formal closure of the incident, including debriefing sessions
B75: 2.17.32 | C75: Lessons learned extraction for process improvement | P75: =VLOOKUP(_Output!D673,_Guidance!$B$2187:$C$2193,2,FALSE) | Q75: Continuous improvement based on previous experiences
B76: 2.17.33 | C76: External security incident support agreements | P76: =VLOOKUP(_Output!D976,_Guidance!$B$2187:$C$2193,2,FALSE) | Q76: Retainer for incident response as a service in case of major breaches
B77: 2.17.34 | C77: Exercises with other incident response teams | P77: =VLOOKUP(_Output!D977,_Guidance!$B$2187:$C$2193,2,FALSE) | Q77: Exercises with other IR teams, for example outsourcing partners and other teams in the sector
B78: 2.17.35 | C78: Root Cause Analysis | P78: =VLOOKUP(_Output!D979,_Guidance!$B$2187:$C$2193,2,FALSE) | Q78: Investigation and reporting on the root cause of the incident. Required for optimizing lessons learned for the organization
C79: Completeness (%) | L79: =IFERROR(ROUND(_Output!K676,0),0) -> 0
B81: Comments and/or Remarks
B82: 2.18 | C82: Specify rationale for chosen values or any additional comments | K82: Maturity | L82: 2.2
L83: 2.3
C84: RE&CT framework: | L84: 2.5
C85: https://atc-project.github.io/atc-react/ | L85: 2.6
L86: 2.7
L87: 2.8
L88: 2.9
L89: 2.10
L90: 2.11
L91: 2.12
L92: 2.13
L93: 2.14
L94: 2.15
L95: 2.16
K97: Capability | L97: 2.17.1
L98: 2.17.2
L99: 2.17.3
L100: 2.17.4
L101: 2.17.5
L102: 2.17.6
L103: 2.17.7
L104: 2.17.8
L105: 2.17.9
L106: 2.17.10
L107: 2.17.11
...

Sheet Services - A&F
B1: Services
B3: 1. Security Monitoring | G3: 5. Threat Hunting
B4: 2. Security Incident Management | G4: 6. Vulnerability Management
B5: 3. Security Analysis & Forensics | G5: 7. Log Management
B6: 4. Threat Intelligence
A9: 3 | B9: Security Analysis & Forensics | L9: Answer | N9: Importance | P9: Guidance | Q9: Remarks
B10: Maturity
B11: 3.1 | C11: Have you formally described the security analysis & forensics service? | P11: =VLOOKUP(_Output!D681,_Guidance!B1774:C1779,2,FALSE) | Q11: A service description should be in place
B12: 3.2 | C12: Please specify elements of the security analysis service document:
B13: 3.2.1 | C13: Key performance indicators | Q13: Indicators to establish the performance of the service
B14: 3.2.2 | C14: Quality indicators | Q14: Indicators to establish the quality of service delivery
B15: 3.2.3 | C15: Service dependencies | Q15: A clear understanding of which people / process / technologies are required for adequate service delivery
B16: 3.2.4 | C16: Service levels | Q16: Agreements on minimum performance, capacity, availability, etc.
B17: 3.2.5 | C17: Hours of operation | Q17: The operational hours for this service (e.g. 24/7)
B18: 3.2.6 | C18: Service customers and stakeholders | Q18: The customers and stakeholders for this service (e.g. IT management)
B19: 3.2.7 | C19: Purpose | Q19: The purpose and objectives for this service
B20: 3.2.8 | C20: Service input / triggers | Q20: The service input: what triggers this service to run?
B21: 3.2.9 | C21: Service output / deliverables | Q21: The service output: what does the service deliver? Can be tangible (e.g. reports) or intangible (e.g. situational awareness )
B22: 3.2.10 | C22: Service activities | Q22: Which activities are carried out within the scope of the service?
B23: 3.2.11 | C23: Service roles & responsibilities | Q23: Which roles and responsibilities apply to this service?
C24: Completeness | L24: =VLOOKUP(SUM(_Output!D686:D696),_SUM_Completeness!A84:B95, 2, FALSE) -> Incomplete | Q24: Use this outcome to determine the score for 3.2
B25: 3.3 | C25: Is the service measured for quality? | P25: =VLOOKUP(_Output!D697,_Guidance!B1780:C1785,2,FALSE) | Q25: Are the quality indicators from the previous questions used for reporting on the service?
B26: 3.4 | C26: Is the service measured for service delivery in accordance with service levels? | P26: =VLOOKUP(_Output!D698,_Guidance!B1786:C1791,2,FALSE) | Q26: Service levels should be used to formally commit the SOC to service delivery
B27: 3.5 | C27: Are customers and/or stakeholders regularly updated about the service? | P27: =VLOOKUP(_Output!D699,_Guidance!B1792:C1797,2,FALSE) | Q27: Changes to the service scope, delivery, etc.
B28: 3.6 | C28: Is there a contractual agreement between the SOC and the customers? | P28: =VLOOKUP(_Output!D700,_Guidance!B1798:C1803,2,FALSE) | Q28: Contractual agreements should also cover penalties
B29: 3.7 | C29: Is sufficient personnel allocated to the process to ensure required service delivery? | P29: =VLOOKUP(_Output!D701,_Guidance!B1804:C1809,2,FALSE) | Q29: Allocation of dedicated personnel will ensure highest service quality
B30: 3.8 | C30: Is the service aligned with other relevant processes? | P30: =VLOOKUP(_Output!D702,_Guidance!B1810:C1815,2,FALSE) | Q30: e.g. alignment with configuration management, incident management, etc.
B31: 3.9 | C31: Is there a incident resolution / service continuity process in place for this service? | P31: =VLOOKUP(_Output!D703,_Guidance!B1816:C1821,2,FALSE) | Q31: Service continuity is important to comply with contractual agreements, even in case of major incidents
B32: 3.10 | C32: Has a set of procedures been created for this service? | P32: =VLOOKUP(_Output!D705,_Guidance!B1822:C1827,2,FALSE) | Q32: Procedures support process standardization and quality. Personnel should be trained to use procedures correctly and structurally
B33: 3.11 | C33: Is there an onboarding and offloading procedure for this service? | P33: =VLOOKUP(_Output!D1067,_Guidance!B1828:C1833,2,FALSE) | Q33: Customer onboarding and offloading procedures support efficient service delivery and ensure customers are (dis)connected properly
B34: 3.12 | C34: Are best practices applied to the service? | P34: =VLOOKUP(_Output!D706,_Guidance!B1834:C1839,2,FALSE) | Q34: Best practices should be used to optimize this service
B35: 3.13 | C35: Is the service supported by predefined workflows or scenarios? | P35: =VLOOKUP(_Output!D707,_Guidance!B1840:C1845,2,FALSE) | Q35: Use cases can be used to guide the analysis workflows
B36: 3.14 | C36: Is process data gathered for prediction of service performance? | P36: =VLOOKUP(_Output!D711,_Guidance!B1846:C1851,2,FALSE) | Q36: Service performance measurement requires establishment of performance goals
B37: 3.15 | C37: Is the service continuously being improved based on improvement goals? | P37: =VLOOKUP(_Output!D712,_Guidance!B1852:C1857,2,FALSE) | Q37: Improvement based on based evaluation, (maturity) assessment, tests, etc.
B38: Capability
B39: 3.16 | C39: Please specify capabilities and artefacts of the security analysis process:
B40: 3.16.1 | C40: Event analysis | P40: =VLOOKUP(_Output!D714,_Guidance!$B$2187:$C$2193,2,FALSE) | Q40: Analysis of detailed events
B41: 3.16.2 | C41: Event analysis toolkit | P41: =VLOOKUP(_Output!D715,_Guidance!$B$2187:$C$2193,2,FALSE) | Q41: A combination of internal and external tools that can be used for security event analysis purposes
B42: 3.16.3 | C42: Trend analysis | P42: =VLOOKUP(_Output!D716,_Guidance!$B$2187:$C$2193,2,FALSE) | Q42: Analysis of trends in events or incidents
B43: 3.16.4 | C43: Incident analysis | P43: =VLOOKUP(_Output!D717,_Guidance!$B$2187:$C$2193,2,FALSE) | Q43: Analysis of security incidents
B44: 3.16.5 | C44: Visual analysis | P44: =VLOOKUP(_Output!D718,_Guidance!$B$2187:$C$2193,2,FALSE) | Q44: Visualization tools for data analysis
B45: 3.16.6 | C45: Static malware analysis | P45: =VLOOKUP(_Output!D719,_Guidance!$B$2187:$C$2193,2,FALSE) | Q45: Reverse engineering and disassembly of malware
B46: 3.16.7 | C46: Dynamic malware analysis | P46: =VLOOKUP(_Output!D720,_Guidance!$B$2187:$C$2193,2,FALSE) | Q46: Running malware in a controlled environment to determine its characteristics
B47: 3.16.8 | C47: Tradecraft analysis | P47: =VLOOKUP(_Output!D721,_Guidance!$B$2187:$C$2193,2,FALSE) | Q47: Analysis of the tradecraft of the attacker. This includes the tools, tactics, techniques and procedures used by attackers
B48: 3.16.9 | C48: Historic analysis | P48: =VLOOKUP(_Output!D722,_Guidance!$B$2187:$C$2193,2,FALSE) | Q48: Analysis of historic information based on new insights. APTs can span multiple months or years
B49: 3.16.10 | C49: Network analysis | P49: =VLOOKUP(_Output!D723,_Guidance!$B$2187:$C$2193,2,FALSE) | Q49: Analysis of network traffic patterns and packets
B50: 3.16.11 | C50: Memory analysis | P50: =VLOOKUP(_Output!D724,_Guidance!$B$2187:$C$2193,2,FALSE) | Q50: Analysis of end-point memory, for example fileless malware
B51: 3.16.12 | C51: Mobile device analysis | P51: =VLOOKUP(_Output!D725,_Guidance!$B$2187:$C$2193,2,FALSE) | Q51: Capability to perform forensic analysis of mobile devices
... B63: 3.16.24 | C63: Chain of custody preservation procedure | P63: =VLOOKUP(_Output!D737,_Guidance!$B$2187:$C$2193,2,FALSE) | Q63: Procedures to correctly process evidence, while preserving the chain of custody
C64: Completeness (%) | L64: =IFERROR(ROUND(_Output!K739,0),0) -> 0
B66: Comments and/or Remarks
B67: 3.17 | C67: Specify rationale for chosen values or any additional comments | K67: Maturity | L67: 3.1
L68: 3.3
L69: 3.4
L70: 3.5
L71: 3.6
L72: 3.7
L73: 3.8
L74: 3.9
L75: 3.10
L76: 3.11
L77: 3.12
L78: 3.13
L79: 3.14
L80: 3.15
K82: Capability | L82: 3.16.1
L83: 3.16.2
L84: 3.16.3
L85: 3.16.4
L86: 3.16.5
L87: 3.16.6
L88: 3.16.7
L89: 3.16.8
L90: 3.16.9
L91: 3.16.10
L92: 3.16.11
L93: 3.16.12
L94: 3.16.13
... L105: 3.16.24

Sheet Services - THR
B1: Services
B3: 1. Security Monitoring | G3: 5. Threat Hunting
B4: 2. Security Incident Management | G4: 6. Vulnerability Management
B5: 3. Security Analysis & Forensics | G5: 7. Log Management
B6: 4. Threat intelligence
A9: 4 | B9: Threat Intelligence | L9: Answer | N9: Importance | P9: Guidance | Q9: Remarks
B10: Maturity
B11: 4.1 | C11: Have you formally described the threat intelligence service? | P11: =VLOOKUP(_Output!D744,_Guidance!B1860:C1865,2,FALSE) | Q11: A service description should be in place
B12: 4.2 | C12: Please specify elements of the threat intelligence service document:
B13: 4.2.1 | C13: Key performance indicators | Q13: Indicators to establish the performance of the service
B14: 4.2.2 | C14: Quality indicators | Q14: Indicators to establish the quality of service delivery
B15: 4.2.3 | C15: Service dependencies | Q15: A clear understanding of which people / process / technologies are required for adequate service delivery
B16: 4.2.4 | C16: Service levels | Q16: Agreements on minimum performance, capacity, availability, etc.
B17: 4.2.5 | C17: Hours of operation | Q17: The operational hours for this service (e.g. 24/7)
B18: 4.2.6 | C18: Service customers and stakeholders | Q18: The customers and stakeholders for this service (e.g. IT management)
B19: 4.2.7 | C19: Purpose | Q19: The purpose and objectives for this service
B20: 4.2.8 | C20: Service input / triggers | Q20: The service input: what triggers this service to run?
B21: 4.2.9 | C21: Service output / deliverables | Q21: The service output: what does the service deliver? Can be tangible (e.g. reports) or intangible (e.g. situational awareness )
B22: 4.2.10 | C22: Service activities | Q22: Which activities are carried out within the scope of the service?
B23: 4.2.11 | C23: Service roles & responsibilities | Q23: Which roles and responsibilities apply to this service?
C24: Completeness | L24: =VLOOKUP(SUM(_Output!D746:D756),_SUM_Completeness!A84:B95,2,FALSE) -> Incomplete | Q24: Use this outcome to determine the score for 4.2
B25: 4.3 | C25: Is the service measured for quality? | P25: =VLOOKUP(_Output!D757,_Guidance!B1866:C1871,2,FALSE) | Q25: Are the quality indicators from the previous questions used for reporting on the service?
B26: 4.4 | C26: Is the service measured for service delivery in accordance with service levels? | P26: =VLOOKUP(_Output!D758,_Guidance!B1872:C1877,2,FALSE) | Q26: Service levels should be used to formally commit the SOC to service delivery
B27: 4.5 | C27: Are customers and/or stakeholders regularly updated about the service? | P27: =VLOOKUP(_Output!D759,_Guidance!B1878:C1883,2,FALSE) | Q27: Changes to the service scope, delivery, etc.
B28: 4.6 | C28: Is there a contractual agreement between the SOC and the customers? | P28: =VLOOKUP(_Output!D760,_Guidance!B1884:C1889,2,FALSE) | Q28: Contractual agreements should also cover penalties
B29: 4.7 | C29: Is sufficient personnel allocated to the process to ensure required service delivery? | P29: =VLOOKUP(_Output!D761,_Guidance!B1890:C1895,2,FALSE) | Q29: Allocation of dedicated personnel will ensure highest service quality
B30: 4.8 | C30: Is the service aligned with other relevant processes? | P30: =VLOOKUP(_Output!D762,_Guidance!B1896:C1901,2,FALSE) | Q30: e.g. the security monitoring process, and mainly the security incident management process
B31: 4.9 | C31: Is there a incident resolution / service continuity process in place for this service? | P31: =VLOOKUP(_Output!D763,_Guidance!B1902:C1907,2,FALSE) | Q31: Service continuity is important to comply with contractual agreements, even in case of major incidents
B32: 4.10 | C32: Has a set of procedures been created for this service? | P32: =VLOOKUP(_Output!D765,_Guidance!B1908:C1913,2,FALSE) | Q32: Procedures support process standardization and quality. Personnel should be trained to use procedures correctly and structurally
B33: 4.11 | C33: Is there an onboarding and offloading procedure for this service? | P33: =VLOOKUP(_Output!D1068,_Guidance!B1914:C1919,2,FALSE) | Q33: Customer onboarding and offloading procedures support efficient service delivery and ensure customers are (dis)connected properly
B34: 4.12 | C34: Are best practices applied to the service? | P34: =VLOOKUP(_Output!D766,_Guidance!B1920:C1925,2,FALSE) | Q34: Best practices should be used to optimize this service
B35: 4.13 | C35: Is process data gathered for prediction of service performance? | P35: =VLOOKUP(_Output!D767,_Guidance!B1926:C1931,2,FALSE) | Q35: Service performance measurement requires establishment of performance goals
B36: 4.14 | C36: Is the service continuously being improved based on improvement goals? | P36: =VLOOKUP(_Output!D768,_Guidance!B1932:C1937,2,FALSE) | Q36: Improvement based on based evaluation, (maturity) assessment, tests, etc.
B37: Capability
B38: 4.15 | C38: Please specify capabilities and artefacts of the threat intelligence process:
B39: Collection
B40: 4.15.1 | C40: Continuous intelligence gathering | P40: =VLOOKUP(_Output!D770,_Guidance!$B$2187:$C$2193,2,FALSE) | Q40: A process for continuously gathering relevant intelligence information
B41: 4.15.2 | C41: Automated intelligence gathering & processing | P41: =VLOOKUP(_Output!D771,_Guidance!$B$2187:$C$2193,2,FALSE) | Q41: An automated system that collects and processes security intelligence information
B42: 4.15.3 | C42: Centralized collection & distribution | P42: =VLOOKUP(_Output!D772,_Guidance!$B$2187:$C$2193,2,FALSE) | Q42: A central 'hub' for distributing indicators of compromise to other systems for further processing
B43: 4.15.4 | C43: Intelligence collection from open / public sources | P43: =VLOOKUP(_Output!D773,_Guidance!$B$2187:$C$2193,2,FALSE) | Q43: The use of public sources in the security intelligence process
B44: 4.15.5 | C44: Intelligence collection from closed communities | P44: =VLOOKUP(_Output!D774,_Guidance!$B$2187:$C$2193,2,FALSE) | Q44: The use of closed trusted communities in the security intelligence process
B45: 4.15.6 | C45: Intelligence collection from intelligence provider | P45: =VLOOKUP(_Output!D775,_Guidance!$B$2187:$C$2193,2,FALSE) | Q45: The use of intelligence providers as a source for the security intelligence process
B46: 4.15.7 | C46: Intelligence collection from business partners | P46: =VLOOKUP(_Output!D776,_Guidance!$B$2187:$C$2193,2,FALSE) | Q46: The use of business partners as a source for the security intelligence process
B47: 4.15.8 | C47: Intelligence collection from mailing lists | P47: =VLOOKUP(_Output!D777,_Guidance!$B$2187:$C$2193,2,FALSE) | Q47: The use of mailing lists as a source for the security intelligence process
B48: 4.15.9 | C48: Intelligence collection from internal sources | P48: =VLOOKUP(_Output!D778,_Guidance!$B$2187:$C$2193,2,FALSE) | Q48: The use of internal intelligence sources for the security intelligence process
B49: Processing
B50: 4.15.10 | C50: Structured data analysis | P50: =VLOOKUP(_Output!D779,_Guidance!$B$2187:$C$2193,2,FALSE) | Q50: The capability to analyze structured information
B51: 4.15.11 | C51: Unstructured data analysis | P51: =VLOOKUP(_Output!D780,_Guidance!$B$2187:$C$2193,2,FALSE) | Q51: The capability to analyze unstructured information
B52: 4.15.12 | C52: Past incident analysis | P52: =VLOOKUP(_Output!D781,_Guidance!$B$2187:$C$2193,2,FALSE) | Q52: The capability of using past incidents in the threat intelligence process. e.g. connecting new IoCs to past threats
B53: 4.15.13 | C53: Trend analysis | P53: =VLOOKUP(_Output!D782,_Guidance!$B$2187:$C$2193,2,FALSE) | Q53: Analyzing trends in the threat intelligence IoCs observed within the company
B54: 4.15.14 | C54: Automated alerting | P54: =VLOOKUP(_Output!D783,_Guidance!$B$2187:$C$2193,2,FALSE) | Q54: Automated alerting of sightings of observables
B55: 4.15.15 | C55: Adversary movement tracking | P55: =VLOOKUP(_Output!D784,_Guidance!$B$2187:$C$2193,2,FALSE) | Q55: Tracking the movement of attackers to keep track of new tools, tactics, techniques and procedures
B56: 4.15.16 | C56: Attacker identification | P56: =VLOOKUP(_Output!D785,_Guidance!$B$2187:$C$2193,2,FALSE) | Q56: Identification of adversaries based on correlating intelligence indicators and incidents
B57: 4.15.17 | C57: Threat identification | P57: =VLOOKUP(_Output!D786,_Guidance!$B$2187:$C$2193,2,FALSE) | Q57: Identification of threats related to attacker groups
B58: 4.15.18 | C58: Threat prediction | P58: =VLOOKUP(_Output!D787,_Guidance!$B$2187:$C$2193,2,FALSE) | Q58: Prediction of threats based on the information gathered in the threat intelligence process
B59: 4.15.19 | C59: TTP extraction | P59: =VLOOKUP(_Output!D788,_Guidance!$B$2187:$C$2193,2,FALSE) | Q59: Extraction of Tactics, Techniques and Procedures (TTP) from observables within the infrastructure
B60: 4.15.20 | C60: Deduplication | P60: =VLOOKUP(_Output!D789,_Guidance!$B$2187:$C$2193,2,FALSE) | Q60: Deduplication of threat intelligence feeds to avoid duplicate events
B61: 4.15.21 | C61: Enrichment | P61: =VLOOKUP(_Output!D790,_Guidance!$B$2187:$C$2193,2,FALSE) | Q61: Enrichment of information with additional sources for a higher level of confidentiality
... B64: 4.15.24 | C64: Threat intelligence reporting | P64: =VLOOKUP(_Output!D793,_Guidance!$B$2187:$C$2193,2,FALSE) | Q64: Reporting on threat intelligence findings and activities
B65: 4.15.25 | C65: Threat landscaping | P65: =VLOOKUP(_Output!D1072,_Guidance!$B$2187:$C$2193,2,FALSE) | Q65: Creation of a landscape of current and emerging threats for strategic purposes
B66: 4.15.26 | C66: Forecasting | P66: =VLOOKUP(_Output!D794,_Guidance!$B$2187:$C$2193,2,FALSE) | Q66: Forecasting based on trends and incidents
B67: Dissemination
B68: 4.15.27 | C68: Sharing within the company | P68: =VLOOKUP(_Output!D795,_Guidance!$B$2187:$C$2193,2,FALSE) | Q68: Sharing of information with relevant parties within the company
B69: 4.15.28 | C69: Sharing with the industry | P69: =VLOOKUP(_Output!D796,_Guidance!$B$2187:$C$2193,2,FALSE) | Q69: Sharing of information with relevant parties within the same industry
B70: 4.15.29 | C70: Sharing outside the industry | P70: =VLOOKUP(_Output!D797,_Guidance!$B$2187:$C$2193,2,FALSE) | Q70: Sharing of information with relevant parties outside the industry
B71: 4.15.30 | C71: Sharing in standardized format (e.g. STIX) | P71: =VLOOKUP(_Output!D798,_Guidance!$B$2187:$C$2193,2,FALSE) | Q71: Sharing of information in standardized exchange formats, such as STIX
B72: Infrastructure Management
