Workbook
Name ValidEval: #REF!
Name ValidEval: #REF!
Name ValidEval: #REF!
Name ValidEval: #REF!
Name ValidEval: #REF!
Name ValidEval: #REF!
Name ValidEval: #REF!
Name ValidEval: #REF!
Name ValidEval: #REF!
Name ValidWeights: #REF!
Name ValidWeights: #REF!
Name ValidWeights: #REF!
Name ValidWeights: #REF!
Name ValidWeights: #REF!
Name ValidWeights: #REF!
Name ValidWeights: #REF!
Name ValidWeights: #REF!
Name ValidWeights: #REF!

Sheet Score Card - Cummulative
A2: Cummulative Score
A3: Domain | B3: Sub-Domain | C3: Assessed Score | D3: Peer | E3: Recommended
A4: 1 - Mission and Governance
B5: ='1 - Mission and Governance'!B51 -> 1.1 - Mission | C5: ='1 - Mission and Governance'!C51 -> 0 | D5: ='1 - Mission and Governance'!G51 -> 0 | E5: ='1 - Mission and Governance'!H51 -> 16
B6: ='1 - Mission and Governance'!B52 -> 1.2 - Service Catalogue | C6: ='1 - Mission and Governance'!C52 -> 0 | D6: ='1 - Mission and Governance'!G52 -> 0 | E6: ='1 - Mission and Governance'!H52 -> 32
B7: ='1 - Mission and Governance'!B53 -> 1.3 - Governance | C7: ='1 - Mission and Governance'!C53 -> 0 | D7: ='1 - Mission and Governance'!G53 -> 0 | E7: ='1 - Mission and Governance'!H53 -> 8
B8: ='1 - Mission and Governance'!B54 -> 1.4 - Repeatability | C8: ='1 - Mission and Governance'!C54 -> 0 | D8: ='1 - Mission and Governance'!G54 -> 0 | E8: ='1 - Mission and Governance'!H54 -> 36
A9: 2 - People
B10: ='2 - People'!B95 -> 2.1 - Resourcing | C10: ='2 - People'!C95 -> 0 | D10: ='2 - People'!G95 -> 0 | E10: ='2 - People'!H95 -> 84
B11: ='2 - People'!B96 -> 2.2 - Training | C11: ='2 - People'!C96 -> 0 | D11: ='2 - People'!G96 -> 0 | E11: ='2 - People'!H96 -> 80
B12: ='2 - People'!B97 -> 2.3 - Certifications | C12: ='2 - People'!C97 -> 0 | D12: ='2 - People'!G97 -> 0 | E12: ='2 - People'!H97 -> 36
B13: ='2 - People'!B98 -> 2.4 - Relevant Experience | C13: ='2 - People'!C98 -> 0 | D13: ='2 - People'!G98 -> 0 | E13: ='2 - People'!H98 -> 32
B14: ='2 - People'!B99 -> 2.5 - Skills Assessment | C14: ='2 - People'!C99 -> 0 | D14: ='2 - People'!G99 -> 0 | E14: ='2 - People'!H99 -> 24
B15: ='2 - People'!B100 -> 2.6 - Career Path | C15: ='2 - People'!C100 -> 0 | D15: ='2 - People'!G100 -> 0 | E15: ='2 - People'!H100 -> 20
B16: ='2 - People'!B101 -> 2.7 - Leadership | C16: ='2 - People'!C101 -> 0 | D16: ='2 - People'!G101 -> 0 | E16: ='2 - People'!H101 -> 48
A17: 3 - Process
B18: ='3 - Process'!B177 -> 3.1 - SOC Threat Management | C18: ='3 - Process'!C177 -> 0 | D18: ='3 - Process'!G167 -> 0 | E18: ='3 - Process'!H167 -> 172
B19: ='3 - Process'!B178 -> 3.2 - SOC Analytical Process | C19: ='3 - Process'!C178 -> 0 | D19: ='3 - Process'!G168 -> 0 | E19: ='3 - Process'!H168 -> 91
B20: ='3 - Process'!B179 -> 3.3 - SOC Engineering Processes | C20: ='3 - Process'!C179 -> 0 | D20: ='3 - Process'!G169 -> 0 | E20: ='3 - Process'!H169 -> 48
B21: ='3 - Process'!B180 -> 3.4 - SOC Operations and Continuity | C21: ='3 - Process'!C180 -> 0 | D21: ='3 - Process'!G170 -> 0 | E21: ='3 - Process'!H170 -> 160
B22: ='3 - Process'!B181 -> 3.5 - SOC Incident Coordination | C22: ='3 - Process'!C181 -> 0 | D22: ='3 - Process'!G171 -> 0 | E22: ='3 - Process'!H171 -> 32
B23: ='3 - Process'!B182 -> 3.6 - SOC Portfolio Management | C23: ='3 - Process'!C182 -> 0 | D23: ='3 - Process'!G172 -> 0 | E23: ='3 - Process'!H172 -> 104
A24: 4 - Technology
B25: ='4 - Technology Functional'!B196 -> 4.1 - Security Information and Event Management | C25: ='4 - Technology Functional'!C196 -> 0 | D25: ='4 - Technology Functional'!D196 -> 0 | E25: ='4 - Technology Functional'!E196 -> 76
B26: ='4 - Technology Functional'!B197 -> 4.2 - Intelligence Correlation | C26: ='4 - Technology Functional'!C197 -> 0 | D26: ='4 - Technology Functional'!D197 -> 0 | E26: ='4 - Technology Functional'!E197 -> 36
B27: ='4 - Technology Functional'!B198 -> 4.3 - Architecture | C27: ='4 - Technology Functional'!C198 -> 0 | D27: ='4 - Technology Functional'!D198 -> 0 | E27: ='4 - Technology Functional'!E198 -> 88
B28: ='4 - Technology Functional'!B199 -> 4.4 - Correlation | C28: ='4 - Technology Functional'!C199 -> 0 | D28: ='4 - Technology Functional'!D199 -> 0 | E28: ='4 - Technology Functional'!E199 -> 152
B29: ='4 - Technology Functional'!B200 -> 4.5 - Reporting | C29: ='4 - Technology Functional'!C200 -> 0 | D29: ='4 - Technology Functional'!D200 -> 0 | E29: ='4 - Technology Functional'!E200 -> 120
B30: ='4 - Technology Functional'!B201 -> 4.6 - SOC Engineering | C30: ='4 - Technology Functional'!C201 -> 0 | D30: ='4 - Technology Functional'!D201 -> 0 | E30: ='4 - Technology Functional'!E201 -> 192
B31: ='4 - Technology Functional'!B202 -> 4.7 - SOC Information Lifecycle Management | C31: ='4 - Technology Functional'!C202 -> 0 | D31: ='4 - Technology Functional'!D202 -> 0 | E31: ='4 - Technology Functional'!E202 -> 24
A32: 5 - Coverage
B33: ='5 - Coverage'!B135 -> 5.1 - Infrastructure Event Coverage | C33: ='5 - Coverage'!C135 -> 0 | D33: ='5 - Coverage'!D135 -> 0 | E33: ='5 - Coverage'!E135 -> 36
B34: ='5 - Coverage'!B136 -> 5.2 - Security Devices Coverage | C34: ='5 - Coverage'!C136 -> 0 | D34: ='5 - Coverage'!D136 -> 0 | E34: ='5 - Coverage'!E136 -> 64
B35: ='5 - Coverage'!B137 -> 5.3 - Advanced Threat Coverage | C35: ='5 - Coverage'!C137 -> 0 | D35: ='5 - Coverage'!D137 -> 0 | E35: ='5 - Coverage'!E137 -> 32
B36: ='5 - Coverage'!B138 -> 5.4 - Network Device Coverage | C36: ='5 - Coverage'!C138 -> 0 | D36: ='5 - Coverage'!D138 -> 0 | E36: ='5 - Coverage'!E138 -> 52
B37: ='5 - Coverage'!B139 -> 5.5 - Application Coverage | C37: ='5 - Coverage'!C139 -> 0 | D37: ='5 - Coverage'!D139 -> 0 | E37: ='5 - Coverage'!E139 -> 16
B38: ='5 - Coverage'!B140 -> 5.6 - Use Case Enablers | C38: ='5 - Coverage'!C140 -> 0 | D38: ='5 - Coverage'!D140 -> 0 | E38: ='5 - Coverage'!E140 -> 152
B39: ='5 - Coverage'!B141 -> 5.7 - Reports | C39: ='5 - Coverage'!C141 -> 0 | D39: ='5 - Coverage'!D141 -> 0 | E39: ='5 - Coverage'!E141 -> 120

Sheet Score Card - Percentage
A2: Score Percentage
A3: Domain | B3: Sub-Domain | C3: Assessed Score | D3: Peer | E3: Recommended
A4: 1 - Mission and Governance
B5: ='1 - Mission and Governance'!B51 -> 1.1 - Mission | C5: 0.12 | D5: ='1 - Mission and Governance'!G60 -> 0 | E5: ='1 - Mission and Governance'!H60 -> 0.8
B6: ='1 - Mission and Governance'!B52 -> 1.2 - Service Catalogue | C6: 0.02 | D6: ='1 - Mission and Governance'!G61 -> 0 | E6: ='1 - Mission and Governance'!H61 -> 0.8
B7: ='1 - Mission and Governance'!B53 -> 1.3 - Governance | C7: 0.13 | D7: ='1 - Mission and Governance'!G62 -> 0 | E7: ='1 - Mission and Governance'!H62 -> 0.8
B8: ='1 - Mission and Governance'!B54 -> 1.4 - Repeatability | C8: 0.9 | D8: ='1 - Mission and Governance'!G63 -> 0 | E8: ='1 - Mission and Governance'!H63 -> 0.8
A9: 2 - People
B10: ='2 - People'!B95 -> 2.1 - Resourcing | C10: ='2 - People'!C106 -> 0 | D10: ='2 - People'!G106 -> 0 | E10: ='2 - People'!H106 -> 0.8
B11: ='2 - People'!B96 -> 2.2 - Training | C11: ='2 - People'!C107 -> 0 | D11: ='2 - People'!G107 -> 0 | E11: ='2 - People'!H107 -> 0.8
B12: ='2 - People'!B97 -> 2.3 - Certifications | C12: ='2 - People'!C108 -> 0 | D12: ='2 - People'!G108 -> 0 | E12: ='2 - People'!H108 -> 0.8
B13: ='2 - People'!B98 -> 2.4 - Relevant Experience | C13: ='2 - People'!C109 -> 0 | D13: ='2 - People'!G109 -> 0 | E13: ='2 - People'!H109 -> 0.8
B14: ='2 - People'!B99 -> 2.5 - Skills Assessment | C14: ='2 - People'!C110 -> 0 | D14: ='2 - People'!G110 -> 0 | E14: ='2 - People'!H110 -> 0.8
B15: ='2 - People'!B100 -> 2.6 - Career Path | C15: ='2 - People'!C111 -> 0 | D15: ='2 - People'!G111 -> 0 | E15: ='2 - People'!H111 -> 0.8
B16: ='2 - People'!B101 -> 2.7 - Leadership | C16: ='2 - People'!C112 -> 0 | D16: ='2 - People'!G112 -> 0 | E16: ='2 - People'!H112 -> 0.8
A17: 3 - Process
B18: ='3 - Process'!B177 -> 3.1 - SOC Threat Management | C18: ='3 - Process'!C187 -> 0 | D18: ='3 - Process'!G177 -> 0 | E18: ='3 - Process'!H177 -> 0.8
B19: ='3 - Process'!B178 -> 3.2 - SOC Analytical Process | C19: ='3 - Process'!C188 -> 0 | D19: ='3 - Process'!G178 -> 0 | E19: ='3 - Process'!H178 -> 0.79130435
B20: ='3 - Process'!B179 -> 3.3 - SOC Engineering Processes | C20: ='3 - Process'!C189 -> 0 | D20: ='3 - Process'!G179 -> 0 | E20: ='3 - Process'!H179 -> 0.8
B21: ='3 - Process'!B180 -> 3.4 - SOC Operations and Continuity | C21: ='3 - Process'!C190 -> 0 | D21: ='3 - Process'!G180 -> 0 | E21: ='3 - Process'!H180 -> 0.8
B22: ='3 - Process'!B181 -> 3.5 - SOC Incident Coordination | C22: ='3 - Process'!C191 -> 0 | D22: ='3 - Process'!G181 -> 0 | E22: ='3 - Process'!H181 -> 0.8
B23: ='3 - Process'!B182 -> 3.6 - SOC Portfolio Management | C23: ='3 - Process'!C192 -> 0 | D23: ='3 - Process'!G182 -> 0 | E23: ='3 - Process'!H182 -> 0.8
A24: 4 - Technology
B25: ='4 - Technology Functional'!B196 -> 4.1 - Security Information and Event Management | C25: ='4 - Technology Functional'!C207 -> 0 | D25: ='4 - Technology Functional'!D207 -> 0 | E25: ='4 - Technology Functional'!E207 -> 0.8
B26: ='4 - Technology Functional'!B197 -> 4.2 - Intelligence Correlation | C26: ='4 - Technology Functional'!C208 -> 0 | D26: ='4 - Technology Functional'!D208 -> 0 | E26: ='4 - Technology Functional'!E208 -> 0.8
B27: ='4 - Technology Functional'!B198 -> 4.3 - Architecture | C27: ='4 - Technology Functional'!C209 -> 0 | D27: ='4 - Technology Functional'!D209 -> 0 | E27: ='4 - Technology Functional'!E209 -> 0.8
B28: ='4 - Technology Functional'!B199 -> 4.4 - Correlation | C28: ='4 - Technology Functional'!C210 -> 0 | D28: ='4 - Technology Functional'!D210 -> 0 | E28: ='4 - Technology Functional'!E210 -> 0.8
B29: ='4 - Technology Functional'!B200 -> 4.5 - Reporting | C29: ='4 - Technology Functional'!C211 -> 0 | D29: ='4 - Technology Functional'!D211 -> 0 | E29: ='4 - Technology Functional'!E211 -> 0.8
B30: ='4 - Technology Functional'!B201 -> 4.6 - SOC Engineering | C30: ='4 - Technology Functional'!C212 -> 0 | D30: ='4 - Technology Functional'!D212 -> 0 | E30: ='4 - Technology Functional'!E212 -> 0.8
B31: ='4 - Technology Functional'!B202 -> 4.7 - SOC Information Lifecycle Management | C31: ='4 - Technology Functional'!C213 -> 0 | D31: ='4 - Technology Functional'!D213 -> 0 | E31: ='4 - Technology Functional'!E213 -> 0.8
A32: 5 - Coverage
B33: ='5 - Coverage'!B135 -> 5.1 - Infrastructure Event Coverage | C33: ='5 - Coverage'!C146 -> 0 | D33: ='5 - Coverage'!D146 -> 0 | E33: ='5 - Coverage'!E146 -> 0.8
B34: ='5 - Coverage'!B136 -> 5.2 - Security Devices Coverage | C34: ='5 - Coverage'!C147 -> 0 | D34: ='5 - Coverage'!D147 -> 0 | E34: ='5 - Coverage'!E147 -> 0.8
B35: ='5 - Coverage'!B137 -> 5.3 - Advanced Threat Coverage | C35: ='5 - Coverage'!C148 -> 0 | D35: ='5 - Coverage'!D148 -> 0 | E35: ='5 - Coverage'!E148 -> 0.8
B36: ='5 - Coverage'!B138 -> 5.4 - Network Device Coverage | C36: ='5 - Coverage'!C149 -> 0 | D36: ='5 - Coverage'!D149 -> 0 | E36: ='5 - Coverage'!E149 -> 0.8
B37: ='5 - Coverage'!B139 -> 5.5 - Application Coverage | C37: ='5 - Coverage'!C150 -> 0 | D37: ='5 - Coverage'!D150 -> 0 | E37: ='5 - Coverage'!E150 -> 0.8
B38: ='5 - Coverage'!B140 -> 5.6 - Use Case Enablers | C38: ='5 - Coverage'!C151 -> 0 | D38: ='5 - Coverage'!D151 -> 0 | E38: ='5 - Coverage'!E151 -> 0.8
B39: ='5 - Coverage'!B141 -> 5.7 - Reports | C39: ='5 - Coverage'!C152 -> 0 | D39: ='5 - Coverage'!D152 -> 0 | E39: ='5 - Coverage'!E152 -> 0.8

Sheet Score Card - Graphs
A2: Score Percentage
A3: Domain | B3: Sub-Domain | C3: Assessed Score | D3: Peer | E3: Recommended
A4: 1 - Mission and Governance
A19: 2 - People
A36: 3 - Process
A56: 4 - Technology
A75: 5 - Coverage

Sheet CoBIT maturity key
A2: CoBIT Metric/Maturity Model
A3: Metric | C3: Activity | D3: Assigned Responsibilities | E3: Documents in place | F3: KPI/KGI
A4: Level 0 - Does not exist | B4: 0 | C4: No awareness of the importance of issues related to the activity. No monitoring is performed. No documentation exists. No activity improvement actions take place. | D4: No RACI relationship assigned | E4: 0 | F4: 0
A5: Level 1 - Initial | B5: 1 | C5: Some awareness of the importance of issues related to the activity. No monitoring is performed. No documentation exists. No activity improvement actions take place. | D5: 25 % of RACI-relationships assigned. | E5: 0.2 | F5: 0.2
A6: Level 2 - Repeatable | B6: 2 | C6: Individuals have knowledge about issues related to the activity and take actions accordingly. No monitoring is performed. No documentation exists. No activity improvement actions take place. | D6: More than 26 % of RACI relationships assigned. 25 % or less of the identified relationships are in line with COBIT. | E6: 0.4 | F6: 0.4
A7: Level 3 - Defined | B7: 3 | C7: Affected personnel are trained in the means and goals of the activity. No monitoring is performed. Documentation is present. No activity improvement actions take place. | D7: More than 26 % of RACIrelationships assigned. 26- 74 % of the identified relationships are in line with COBIT. | E7: 0.6 | F7: 0.6
A8: Level 4 - Managed | B8: 4 | C8: Affected personnel are trained in the means and goals of the activity. Monitoring is performed. Documentation is present. The activity is under constant improvement. Automated tools are employed in a limited and fragmented way | D8: re than 51 % of RACI relationships assigned. 51- 99 % of the identified relationships are in line with COBIT. | E8: 0.8 | F8: 0.8
A9: Level 5 - Optimized | B9: 5 | C9: Affected personnel are trained in the means and goals of the activity. Monitoring is performed. Documentation is present. Automated tools are employed in an integrated way, to improve quality and effectiveness of the activity. | D9: 100 % of RACI-relationships assigned. 100 % of the identified relationships are in line with COBIT. | E9: 1 | F9: 1

Sheet 0 - General Questions
A2: 0 - Roadmap Questionairre
A3: Please enter a response for each question | B3: Response
A4: Business Profile
A5: Client Name | B5: InterGlobe Aviation Pvt. Ltd.
A6: Number of Employees | B6: 26000
A7: Number of Customer (preferrably by region) | B7: 1
A8: Number of Offices | B8: Multiple
A9: Countries of Operations (please specify countries and if possible the approx number of customers by region) | B9: 33
A10: Compliance Drivers
A11: What compliance frameworks are pertitent to the organization? | B11: ISO 27001
A12: What industry standards would the organization wish to consider for the assessment? | B12: ISO 27001
A13: Has internal (or external) audit rendered any audit points on Logging, Monitoring or Reporting? If so, if you can please provide the findings. | B13: Check
A14: Information Security Policy
A15: Please provide any corporate information security policy. | B15: Yes
A16: Is there a policy on data classification? | B16: Check
A17: Is there assets that have been classified as business critical within the governance of this document? If so, where are they located? | B17: Yes, the critical applications are hsoted in the Data Center/ Azure Cloud
A18: Is there a formalized methodology for threat modeling and use case development? | B18: Yes
A19: High level Service Level Objectives
A20: Is there a document that defines the SLO for responding to high severity alarm conditions that may be generated by the future SOC? For example, if an organization is affected by a business critical threat, would the response expectation be 15, 30 minutes, two (2) hours etc.? | B20: Yes, SLAs are defined in the IR plan
A21: Financial model
A22: For the financial model, should Deloitte consider a three, five or other year model? | B22: 3 year multiyear engagement
A23: Should Deloitte use a NPV of 5% for the cost forecast?
A24: Is there a primary IT investment focus (strategic, information, transactional, infrastructure)?
A25: Is there a defined Business Risk Measurement Model?
A26: Has the company allocated Business Risk Financing?
A27: Service Catalogue
A28: Please enter the current service catalogue for the SOC. For example, what functions are being covered by the current SOC (e.g. monitoring, cyber threat intelligence, malware reconstruction etc)?
A29: Is there an enterprise strategy on vulnerability monitoring tracking? | B29: Yes, Tenable VMS in place and all the vulnerabilities are tracked in SNOW
A30: If so, would an organization like Deloitte to include this in the Services Catalogue. | B30: Already included
A31: Typically this is not considered a core SOC service and can result in expanded scope, but some clients have asked that this be included in the extended SOC’s domicile of coverage. | B31: Not included in core SOC services for IndiGo
A32: Is there an enterprise strategy on Cyber Threat Intelligence? If so, are there resources currently allocated to this function? | B32: Yes, basic CTI services are provided by Deloitte
A33: Is there an enterprise strategy on Role and Group Certification? If so, are there resources currently allocated to this function? | B33: Yes, preperation for ISO 27001 certification is in progress
A34: If not, would an organization like Deloitte to include this in the Services Catalogue. | B34: Already included
A35: Typically this is not considered a core SOC service and can result in expanded scope, but some clients have asked that this be included in the extended SOC’s domicile of coverage. | B35: Not included in core SOC services for IndiGo
A36: Is there an enterprise strategy on Malware Analysis? If so, are there resources currently allocated to this function?
A37: If not, would an organization like Deloitte to include this in the Services Catalogue.
A38: Is there an enterprise strategy on Compliance Reporting, Monitoring and Tracking? If so, are there resources currently allocated to this function?
A39: Would an organization like Deloitte to include this in the Services Catalogue?
A40: Would an organization like Deloitte to include Security Advisory Services as part of the SOC’s Services Catalogue? Security Advisory services include monitoring security threat advisories and disseminating it to the applicable teams.
A41: Typically this is not considered a core SOC service and can result in expanded scope, but some clients have asked that this be included in the extended SOC’s domicile of coverage.
A42: Does an organization have an Enterprise Governance Risk and Compliance (GRC) capability? If so, please provide details.
A43: General
A44: What other initiatives could have an impact on the SOC rollout?
A45: What other initiatives could be impacted by the SOC rollout?
A46: Is there an estimate for when an organization will expect the PCN to be integrated into the overall SOC?
A47: Is there an estimate for when an organization will expect the Smart Meter environment to be integrated into the overall SOC?
... A56: Please add any additional questions that are not covered in this tool, below

Sheet Sheet1

Sheet 1 - Mission and Governance
A2: 1 - Mission and Governance
A3: Index | B3: Control Objective | C3: Current | D3: Peer | E3: Recommended | F3: Maximum | G3: Peer | H3: Recommended | I3: Maximum | R3: Comments
A4: 1.1 - Mission
A5: 1.1.1 | B5: Does the SOC have an established Mission? | C5: Level 5 - Optimized | H5: 4 | I5: 5 | J5: Sample Company specific only, with group charter.
A6: 1.1.2 | B6: Is the Mission aligned with the corporate Vision? | C6: Level 5 - Optimized | H6: 4 | I6: 5
A7: 1.1.3 | B7: Is the SOC stakeholder group clearly documented? | C7: Level 5 - Optimized | H7: 4 | I7: 5 | J7: Operation mgmt. IT Security Advisory Board. Moving into ITIL framework.
A8: 1.1.4 | B8: Are staff trained on the Mission and how it needs to aligns with operating procedures? | C8: Level 3 - Defined | H8: 4 | I8: 5 | J8: Operational manual.
A9: 1.1.5 | B9: Does the SOC's metric program evaluate against the Mission? | C9: Level 3 - Defined | H9: 4
A10: 1.1.6 | B10: The SOC has an risk management plan that considers the Governance model?
A11: 1.1.7 | B11: Governance is reviewed on an annual basis to ensure adherence to Mission and Vision? | C11: Level 4 - Managed
A12: 1.2 - Service Catalogue
A13: 1.2.1 | B13: Does the SOC have a documented service catalogue? | C13: Level 5 - Optimized | H13: 4 | I13: 5 | J13: IPS coverage is only very limited to certains clients at the moment.
A14: 1.2.2 | B14: Does the SOC communicate the service catalogue to the lines of business? | C14: Level 5 - Optimized | H14: 4 | I14: 5 | K14: Vulnerability and Threat Management Report (Aaron Morrison). Target state micro/macro designs. Part of the Threat and Vulnerability Pillar
A15: 1.2.3 | B15: Does the SOC provide Service Level Objectives against the service catalogue? | C15: Level 5 - Optimized | H15: 4 | I15: 5
A16: 1.2.4 | B16: Does the SOC evaluate performance and report on metrics against the service catalogue? | C16: Level 5 - Optimized | H16: 4 | I16: 5
A17: 1.2.5 | B17: Does the SOC assess resource loading based on the service catalogue? | H17: 4 | I17: 5
A18: 1.2.6 | B18: Does the SOC evaluate resource utilization by service catalogue on a quarterly basis? | H18: 4 | I18: 5
A19: 1.2.7 | B19: Is the SOC service catalogue evaluated with the business stakeholder on an annual basis? | C19: Level 5 - Optimized | H19: 4 | I19: 5
A20: 1.2.8 | B20: Does the SOC ensure appropriate skills maintenance based on the service catalogue? | C20: Level 5 - Optimized | H20: 4 | I20: 5
A21: 1.3 - Governance
A22: 1.3.1 | B22: Does the SOC have a documented governance model? | C22: Level 3 - Defined | H22: 4 | I22: 5
A23: 1.3.2 | B23: Does the SOC maintain list of policies and due care standards that are unique to SOC operations (and not part of the organization's standard policy documentation)? | C23: Level 3 - Defined | H23: 4 | I23: 5
A24: 1.3.3 | B24: Does the SOC maintain and evaluate a repository of unified control objectives? | C24: Level 2 - Repeatable
A25: 1.3.4 | B25: Are the unified control objectives mapped to the organization's regulatory, compliance and industry standards? | C25: Level 2 - Repeatable
A26: 1.3.5 | B26: Does the reporting structure align with the unified control objectives. | C26: Level 2 - Repeatable
A27: 1.3.6 | B27: The SOC has automated synchronization of compliance meta-data between SIEM and eGRC. | C27: Level 0 - Does not exist
A28: 1.4 - Repeatability
A29: 1.4.1 | B29: Does the SOC have an established performance management program? | C29: Level 5 - Optimized | H29: 4 | I29: 5
A30: 1.4.2 | B30: Has the metrics program been aligned with the overall SOC Mission? | C30: Level 5 - Optimized | H30: 4 | I30: 5
A31: 1.4.3 | B31: Are performance metrics reported to business stakeholder on an annual basis? | C31: Level 5 - Optimized | H31: 4 | I31: 5
A32: 1.4.4 | B32: Are performance metrics communicated to all levels of the SOC? | C32: Level 5 - Optimized | H32: 4 | I32: 5
A33: 1.4.5 | B33: Are the performance metrics aligned with compliance goals? | C33: Level 4 - Managed | H33: 4 | I33: 5
A34: 1.4.6 | B34: Are case management timer metrics retained and reported on? | C34: Level 5 - Optimized | H34: 4 | I34: 5
A35: 1.4.7 | B35: Does the SOC use metrics/performance measures as an input into decision making processes and prioritization of activities, resources and funding? | H35: 4 | I35: 5
A36: 1.4.8 | B36: Are SOC metrics reviewed by independent parties on an annual basis, at a minimum? | H36: 4 | I36: 5
A37: 1.4.9 | B37: Are independent reviews performed of SOC logs/alarms for completeness and consistency with reported performance? | H37: 4 | I37: 5
A38: 1.5 - Intra-organization interfaces
B39: Does the SOC have formalized RACI between dependent organizational functions?
A40: 1.5.1 | B40: Does the SOC have formalized engagement processes and standards to interact with HR, about employee investigations? | C40: Level 3 - Defined | H40: 4 | I40: 5
A41: 1.5.2 | B41: Does the SOC have formalized engagement processes and standards to interact with Operations? | C41: Level 4 - Managed | H41: 4 | I41: 5
A42: 1.5.3 | B42: Does the SOC have formalized engagement processes and standards to interact with the CSIRT? | C42: Level 2 - Repeatable | H42: 4 | I42: 5
A43: 1.5.4 | B43: Have decision tree's and call-outs been established for the CSIRT? | C43: Level 3 - Defined | H43: 4 | I43: 5
A44: 1.5.5 | B44: Does the SOC have formalized engagment processes and standards to interact with unverified users, that contact the SOC? | C44: Level 5 - Optimized | H44: 4 | I44: 5
A45: 1.5.6 | B45: Does the SOC have secure methods for communicating with departments and functions? | C45: Level 5 - Optimized | H45: 4 | I45: 5
A46: 1.5.7 | B46: Does the SOC have formalized engagement processes and standards to interact with Public Relations? | C46: Level 5 - Optimized | H46: 4 | I46: 5
A47: 1.5.8 | B47: Does the SOC have formalized engagement processes and standards to interact with Internal or External Audit? | C47: Level 5 - Optimized | H47: 4 | I47: 5
B50: SUMMARY Score | C50: =#REF! -> #REF! | D50: =#REF! -> #REF! | E50: =#REF! -> #REF! | F50: =#REF! -> #REF! | G50: =#REF! -> #REF! | H50: =#REF! -> #REF! | I50: =#REF! -> #REF!
B51: =A4 -> 1.1 - Mission | C51: =SUM(C5:C8) -> 0 | D51: =SUM(D5:D8) -> 0 | E51: =SUM(E5:E8) -> 0 | F51: =SUM(F5:F8) -> 0 | G51: =SUM(G5:G8) -> 0 | H51: =SUM(H5:H8) -> 16 | I51: =SUM(I5:I8) -> 20
B52: =A12 -> 1.2 - Service Catalogue | C52: =SUM(C13:C20) -> 0 | D52: =SUM(D13:D20) -> 0 | E52: =SUM(E13:E20) -> 0 | F52: =SUM(F13:F20) -> 0 | G52: =SUM(G13:G20) -> 0 | H52: =SUM(H13:H20) -> 32 | I52: =SUM(I13:I20) -> 40
B53: =A21 -> 1.3 - Governance | C53: =SUM(C22:C28) -> 0 | D53: =SUM(D22:D28) -> 0 | E53: =SUM(E22:E28) -> 0 | F53: =SUM(F22:F28) -> 0 | G53: =SUM(G22:G28) -> 0 | H53: =SUM(H22:H28) -> 8 | I53: =SUM(I22:I28) -> 10
B54: =A28 -> 1.4 - Repeatability | C54: =SUM(C29:C37) -> 0 | D54: =SUM(D29:D37) -> 0 | E54: =SUM(E29:E37) -> 0 | F54: =SUM(F29:F37) -> 0 | G54: =SUM(G29:G37) -> 0 | H54: =SUM(H29:H37) -> 36 | I54: =SUM(I29:I37) -> 45
B55: =A38 -> 1.5 - Intra-organization interfaces | C55: =SUM(C40:C47) -> 0 | D55: =SUM(D40:D47) -> 0 | E55: =SUM(E40:E47) -> 0 | F55: =SUM(F40:F47) -> 0 | G55: =SUM(G40:G47) -> 0 | H55: =SUM(H40:H47) -> 32 | I55: =SUM(I40:I47) -> 40
B56: TOTAL | C56: =SUM(C51:C55) -> 0 | D56: =SUM(D51:D55) -> 0 | E56: =SUM(E51:E55) -> 0 | F56: =SUM(F51:F55) -> 0 | G56: =SUM(G51:G55) -> 0 | H56: =SUM(H51:H55) -> 124 | I56: =SUM(I51:I55) -> 155
B59: Summary Percentage | C59: =C50 -> #REF! | D59: =D50 -> #REF! | E59: =E50 -> #REF! | F59: =F50 -> #REF! | G59: =G50 -> #REF! | H59: =H50 -> #REF!
B60: =B51 -> 1.1 - Mission | C60: =C51/$I51 -> 0 | D60: =D51/$I51 -> 0 | E60: =E51/$I51 -> 0 | F60: =F51/$I51 -> 0 | G60: =G51/$I51 -> 0 | H60: =H51/$I51 -> 0.8
B61: =B52 -> 1.2 - Service Catalogue | C61: =C52/$I52 -> 0 | D61: =D52/$I52 -> 0 | E61: =E52/$I52 -> 0 | F61: =F52/$I52 -> 0 | G61: =G52/$I52 -> 0 | H61: =H52/$I52 -> 0.8
B62: =B53 -> 1.3 - Governance | C62: =C53/$I53 -> 0 | D62: =D53/$I53 -> 0 | E62: =E53/$I53 -> 0 | F62: =F53/$I53 -> 0 | G62: =G53/$I53 -> 0 | H62: =H53/$I53 -> 0.8
B63: =B54 -> 1.4 - Repeatability | C63: =C54/$I54 -> 0 | D63: =D54/$I54 -> 0 | E63: =E54/$I54 -> 0 | F63: =F54/$I54 -> 0 | G63: =G54/$I54 -> 0 | H63: =H54/$I54 -> 0.8
B64: =B55 -> 1.5 - Intra-organization interfaces | C64: =C55/$I55 -> 0 | D64: =D55/$I55 -> 0 | E64: =E55/$I55 -> 0 | F64: =F55/$I55 -> 0 | G64: =G55/$I55 -> 0 | H64: =H55/$I55 -> 0.8
B65: TOTAL | C65: =C56/$I56 -> 0 | D65: =D56/$I56 -> 0 | E65: =E56/$I56 -> 0 | F65: =F56/$I56 -> 0 | G65: =G56/$I56 -> 0 | H65: =H56/$I56 -> 0.8
A66: 1.6 - Costing Model
A67: 1.6.1 | B67: Does the SOC have a method for base (core) Threat Monitoring chargeback?
A68: 1.6.2 | B68: Does the SOC have a method for Engineering and Content Development chargeback?
A69: 1.6.3 | B69: Does the SOC have a method for Supplemental service chargeback (e.g. malware analysis)? | C69: Level 5 - Optimized
A70: 1.6.4 | B70: Is the costing model tied to SOC performance? | C70: Level 5 - Optimized

Sheet 2.2 - People Matrix
A2: 2.1 - People Loading Matrix
A3: Please enter the number of resources, role etc., for the current SOC
A4: Role | B4: Function | C4: Number of resources | D4: Peer | E4: Recommended | F4: Maximum
B94: SUMMARY Score | C94: =#REF! -> #REF! | D94: =#REF! -> #REF! | E94: =#REF! -> #REF! | F94: =#REF! -> #REF!
B95: =A5 -> 0 | C95: =SUM(C6:C26) -> 0 | D95: =SUM(D6:D26) -> 0 | E95: =SUM(E6:E26) -> 0 | F95: =SUM(F6:F26) -> 0
B96: =A27 -> 0 | C96: =SUM(C28:C47) -> 0 | D96: =SUM(D28:D47) -> 0 | E96: =SUM(E28:E47) -> 0 | F96: =SUM(F28:F47) -> 0
B97: =A48 -> 0 | C97: =SUM(C49:C57) -> 0 | D97: =SUM(D49:D57) -> 0 | E97: =SUM(E49:E57) -> 0 | F97: =SUM(F49:F57) -> 0
B98: =A58 -> 0 | C98: =SUM(C59:C66) -> 0 | D98: =SUM(D59:D66) -> 0 | E98: =SUM(E59:E66) -> 0 | F98: =SUM(F59:F66) -> 0
B99: =A67 -> 0 | C99: =SUM(C68:C73) -> 0 | D99: =SUM(D68:D73) -> 0 | E99: =SUM(E68:E73) -> 0 | F99: =SUM(F68:F73) -> 0
B100: =A74 -> 0 | C100: =SUM(C75:C79) -> 0 | D100: =SUM(D75:D79) -> 0 | E100: =SUM(E75:E79) -> 0 | F100: =SUM(F75:F79) -> 0
B101: =A80 -> 0 | C101: =SUM(C81:C92) -> 0 | D101: =SUM(D81:D92) -> 0 | E101: =SUM(E81:E92) -> 0 | F101: =SUM(F81:F92) -> 0
B102: TOTAL | C102: =SUM(C95:C99) -> 0 | D102: =SUM(D95:D99) -> 0 | E102: =SUM(E95:E99) -> 0 | F102: =SUM(F95:F99) -> 0
B105: Summary Percentage | C105: =C94 -> #REF! | D105: =D94 -> #REF! | E105: =E94 -> #REF! | F105: =F94 -> #REF!
B106: =B95 -> 0 | C106: =C95/#REF! -> #REF! | D106: =D95/#REF! -> #REF! | E106: =E95/#REF! -> #REF! | F106: =F95/#REF! -> #REF!
B107: =B96 -> 0 | C107: =C96/#REF! -> #REF! | D107: =D96/#REF! -> #REF! | E107: =E96/#REF! -> #REF! | F107: =F96/#REF! -> #REF!
B108: =B97 -> 0 | C108: =C97/#REF! -> #REF! | D108: =D97/#REF! -> #REF! | E108: =E97/#REF! -> #REF! | F108: =F97/#REF! -> #REF!
B109: =B98 -> 0 | C109: =C98/#REF! -> #REF! | D109: =D98/#REF! -> #REF! | E109: =E98/#REF! -> #REF! | F109: =F98/#REF! -> #REF!
B110: =B99 -> 0 | C110: =C99/#REF! -> #REF! | D110: =D99/#REF! -> #REF! | E110: =E99/#REF! -> #REF! | F110: =F99/#REF! -> #REF!
B111: =B100 -> 0 | C111: =C100/#REF! -> #REF! | D111: =D100/#REF! -> #REF! | E111: =E100/#REF! -> #REF! | F111: =F100/#REF! -> #REF!
B112: =B101 -> 0 | C112: =C101/#REF! -> #REF! | D112: =D101/#REF! -> #REF! | E112: =E101/#REF! -> #REF! | F112: =F101/#REF! -> #REF!
B113: TOTAL | C113: =C102/#REF! -> #REF! | D113: =D102/#REF! -> #REF! | E113: =E102/#REF! -> #REF! | F113: =F102/#REF! -> #REF!

Sheet 2.3 - Resource Costing Model
A2: 2.3 - Resource Costing Model
A3: Please enter the fully loaded FTE costing for the existing SOC
A4: Role | B4: Function | C4: Fully loaded cost per resource | D4: Peer | E4: Recommended | F4: Maximum
B94: SUMMARY Score | C94: =#REF! -> #REF! | D94: =#REF! -> #REF! | E94: =#REF! -> #REF! | F94: =#REF! -> #REF!
B95: =A5 -> 0 | C95: =SUM(C6:C26) -> 0 | D95: =SUM(D6:D26) -> 0 | E95: =SUM(E6:E26) -> 0 | F95: =SUM(F6:F26) -> 0
B96: =A27 -> 0 | C96: =SUM(C28:C47) -> 0 | D96: =SUM(D28:D47) -> 0 | E96: =SUM(E28:E47) -> 0 | F96: =SUM(F28:F47) -> 0
B97: =A48 -> 0 | C97: =SUM(C49:C57) -> 0 | D97: =SUM(D49:D57) -> 0 | E97: =SUM(E49:E57) -> 0 | F97: =SUM(F49:F57) -> 0
B98: =A58 -> 0 | C98: =SUM(C59:C66) -> 0 | D98: =SUM(D59:D66) -> 0 | E98: =SUM(E59:E66) -> 0 | F98: =SUM(F59:F66) -> 0
B99: =A67 -> 0 | C99: =SUM(C68:C73) -> 0 | D99: =SUM(D68:D73) -> 0 | E99: =SUM(E68:E73) -> 0 | F99: =SUM(F68:F73) -> 0
B100: =A74 -> 0 | C100: =SUM(C75:C79) -> 0 | D100: =SUM(D75:D79) -> 0 | E100: =SUM(E75:E79) -> 0 | F100: =SUM(F75:F79) -> 0
B101: =A80 -> 0 | C101: =SUM(C81:C92) -> 0 | D101: =SUM(D81:D92) -> 0 | E101: =SUM(E81:E92) -> 0 | F101: =SUM(F81:F92) -> 0
B102: TOTAL | C102: =SUM(C95:C99) -> 0 | D102: =SUM(D95:D99) -> 0 | E102: =SUM(E95:E99) -> 0 | F102: =SUM(F95:F99) -> 0
B105: Summary Percentage | C105: =C94 -> #REF! | D105: =D94 -> #REF! | E105: =E94 -> #REF! | F105: =F94 -> #REF!
B106: =B95 -> 0 | C106: =C95/#REF! -> #REF! | D106: =D95/#REF! -> #REF! | E106: =E95/#REF! -> #REF! | F106: =F95/#REF! -> #REF!
B107: =B96 -> 0 | C107: =C96/#REF! -> #REF! | D107: =D96/#REF! -> #REF! | E107: =E96/#REF! -> #REF! | F107: =F96/#REF! -> #REF!
B108: =B97 -> 0 | C108: =C97/#REF! -> #REF! | D108: =D97/#REF! -> #REF! | E108: =E97/#REF! -> #REF! | F108: =F97/#REF! -> #REF!
B109: =B98 -> 0 | C109: =C98/#REF! -> #REF! | D109: =D98/#REF! -> #REF! | E109: =E98/#REF! -> #REF! | F109: =F98/#REF! -> #REF!
B110: =B99 -> 0 | C110: =C99/#REF! -> #REF! | D110: =D99/#REF! -> #REF! | E110: =E99/#REF! -> #REF! | F110: =F99/#REF! -> #REF!
B111: =B100 -> 0 | C111: =C100/#REF! -> #REF! | D111: =D100/#REF! -> #REF! | E111: =E100/#REF! -> #REF! | F111: =F100/#REF! -> #REF!
B112: =B101 -> 0 | C112: =C101/#REF! -> #REF! | D112: =D101/#REF! -> #REF! | E112: =E101/#REF! -> #REF! | F112: =F101/#REF! -> #REF!
B113: TOTAL | C113: =C102/#REF! -> #REF! | D113: =D102/#REF! -> #REF! | E113: =E102/#REF! -> #REF! | F113: =F102/#REF! -> #REF!

Sheet 4.1 - SIEM
A2: 4 - ArcSight Specific Questions
A3: Index | B3: Control Objective | C3: Response
A4: Architecture
B5: How many SmartConnectors exist?
B6: How many Connector Appliances or SmartConnector servers?
B7: How many Loggers does the organization have and which model?
B8: How many ESM managers does the organization have?
B9: How many ESM databases does the organization have?
A10: Rates
B11: Please document the SmartConnector insertion rate for the Connectors?
B12: Please document the Logger input (receiver) eps per Logger
B13: Please document the ESM input eps?
A14: Version
B15: What are the Connector versions?
B16: What are the Logger version (if separate)?
B17: What is the ESM version?
B18: What is the Oracle DB version?

Sheet 2 - People
A2: 2 - People Control Objectives
A3: Index | B3: Control Objective | C3: Current | D3: Peer | E3: Recommended | F3: Maximum | G3: Peer | H3: Recommended | I3: Maximum | J3: Comments
A4: 2.1 - Resourcing
A5: 2.1.1 | B5: Does the organization have analyst coverage for 24x7x365? | C5: Level 5 - Optimized | H5: 4 | I5: 5 | J5: Yes, 24x7x365 Opertions
A6: 2.1.2 | B6: Does the organization have a minimum of two Level 1 analysts for business hours shifts? | C6: Level 5 - Optimized | H6: 4 | I6: 5
A7: 2.1.3 | B7: Does the organization have a minimum of two resources (L1 - L2 mix) for graveyard shifts? | C7: Level 5 - Optimized | H7: 4 | I7: 5
A8: 2.1.4 | B8: Does the organization have a minimum of 1:4 leverage for L1 versus L2? | C8: Level 5 - Optimized | H8: 4 | I8: 5
A9: 2.1.5 | B9: Does the organization have resources that provide overlap between shifts? | C9: Level 5 - Optimized | H9: 4 | I9: 5
A10: 2.1.6 | B10: Does the organization have contingency resources for shifts? | C10: Level 3 - Defined | H10: 4 | I10: 5
A11: 2.1.7 | B11: Does the organization have defined roles and responsibilies? | C11: Level 1 - Initial | H11: 4 | I11: 5
A12: 2.1.8 | B12: Does the SOC have a minimum of four shifts per week | C12: Level 5 - Optimized | H12: 4 | I12: 5
A13: 2.1.9 | B13: Do you evaluate analysts against those defined R&R? | H13: 4 | I13: 5
A14: 2.1.10 | B14: Does the organization have documented R&R for teams you interact with? | H14: 4 | I14: 5
A15: 2.1.11 | B15: Does the organization have a dedicated SOC engineer? | C15: Level 5 - Optimized | H15: 4 | I15: 5
A16: 2.1.12 | B16: Does the SOC engineer have an assigned backup? | C16: Level 5 - Optimized | H16: 4 | I16: 5
A17: 2.1.13 | B17: Does the organization have a management issue escalation process? | C17: Level 5 - Optimized | H17: 4 | I17: 5
A18: 2.1.14 | B18: Do all key positions have designated backups? | C18: Level 5 - Optimized | H18: 4 | I18: 5
A19: 2.1.15 | B19: Does the organization have a contact list and procedure for engaging other areas? | C19: Level 5 - Optimized | H19: 4 | I19: 5
A20: 2.1.16 | B20: Is there a defined audience and method for all SOC reports? | C20: Level 5 - Optimized | H20: 4 | I20: 5
A21: 2.1.17 | B21: Is there a dedicated SOC manager? | C21: Level 5 - Optimized | H21: 4 | I21: 5
A22: 2.1.18 | B22: Where in the Security Org, does the SOC manager report? | C22: Level 5 - Optimized | H22: 4 | I22: 5
A23: 2.1.19 | B23: Is there a defined organizational stucture for the SOC? | C23: Level 4 - Managed | H23: 4 | I23: 5
A24: 2.1.20 | B24: Is there a defined organizational structure for teams interfacing with the SOC on a regular basis? | C24: Level 4 - Managed | H24: 4 | I24: 5
A25: 2.1.21 | B25: Is there a defined escalation path for SOC incidents? | C25: Level 4 - Managed | H25: 4 | I25: 5
A26: 2.1.22 | B26: Are any current security capabilities provided by outsourced vendors or managed security service providers? | C26: Level 4 - Managed
A27: 2.2 - Training
A28: 2.2.1 | B28: Is there a defined annual training plan for SOC analysts? | C28: Level 5 - Optimized | H28: 4 | I28: 5
A29: 2.2.2 | B29: Is there a training budget allocated for SOC training? | C29: Level 5 - Optimized | H29: 4 | I29: 5
A30: 2.2.3 | B30: Is a list of preferred training documented? | C30: Level 5 - Optimized | H30: 4 | I30: 5
A31: 2.2.4 | B31: How regular are SOC analysts trained on threat scenarios? | C31: Level 5 - Optimized | H31: 4 | I31: 5
A32: 2.2.5 | B32: How regular are SOC analysts trained on SOC tools? | C32: Level 5 - Optimized | H32: 4 | I32: 5
A33: 2.2.6 | B33: How regular are SOC analysts refreshed on evidence handling and maintaining chain of custody? | C33: Level 5 - Optimized | H33: 4 | I33: 5
A34: 2.2.7 | B34: Are SOC analysts allowed to attend security conferences to expand knowledge on emerging threats? | C34: Level 5 - Optimized | H34: 4 | I34: 5
A35: 2.2.8 | B35: Is there a reference library in the SOC? | C35: Level 5 - Optimized | H35: 4 | I35: 5
A36: 2.2.9 | B36: Is there required training for all new analysts? | C36: Level 5 - Optimized | H36: 4 | I36: 5
A37: 2.2.10 | B37: Is there a system in place to evaluate analyst comprehension of new training? | C37: Level 5 - Optimized | H37: 4 | I37: 5
A38: 2.2.11 | B38: Is there any process in place to revisit analysts training as a refresher? | C38: Level 5 - Optimized | H38: 4 | I38: 5
A39: 2.2.12 | B39: Is any research done to find external training that may be beneficial to the SOC? | C39: Level 5 - Optimized | H39: 4 | I39: 5
... A47: 2.2.20 | B47: Is there formal training on critical business processes? Change Control, Time Tracking, etc… | C47: Level 5 - Optimized | H47: 4 | I47: 5
A48: 2.3 - Certifications
A49: 2.3.1 | B49: Does the SOC have a certification program for analysts and management? | C49: Level 5 - Optimized | H49: 4 | I49: 5
A50: 2.3.2 | B50: Is there any preference among Security Certifications? (GCIA, GCIH, CISSP, Security+) | C50: Level 5 - Optimized | H50: 4 | I50: 5
A51: 2.3.3 | B51: Is there a published career path for Certifications? Security+ - GCIA - GCIH - CCNA - CISSP - CISM | C51: Level 5 - Optimized | H51: 4 | I51: 5
A52: 2.3.4 | B52: Are at least 2 analysts who are SANS certified? | H52: 4 | I52: 5
A53: 2.3.5 | B53: Are at least 2 analysts CISSP certified? | H53: 4 | I53: 5
A54: 2.3.6 | B54: Are at least 2 analysts certified in SIEM tools? | H54: 4 | I54: 5
A55: 2.3.7 | B55: Are at least 2 analysts certified in OS' used in the organization? | C55: Level 5 - Optimized | H55: 4 | I55: 5
A56: 2.3.8 | B56: Is there a budget allocated for annual certifications and annual? | C56: Level 5 - Optimized | H56: 4 | I56: 5
A57: 2.3.9 | B57: Is there an incentive program for analysts certifications that are relevant for the associated function? | C57: Level 5 - Optimized | H57: 4 | I57: 5
A58: 2.4 - Relevant Experience
A59: 2.4.1 | B59: Do your senior analysts have a minimum of 6 years of IT Security experience? | C59: Level 5 - Optimized | H59: 4 | I59: 5
A60: 2.4.2 | B60: Do your senior analysts have a minimum of 10 years of IT experience? | C60: Level 5 - Optimized | H60: 4 | I60: 5
A61: 2.4.3 | B61: Do your junior analysts have a minimum of 2 years of IT Security experience? | C61: Level 5 - Optimized | H61: 4 | I61: 5
A62: 2.4.4 | B62: Do your junior analysts have a minimum of 5 years of IT experience? | C62: Level 5 - Optimized | H62: 4 | I62: 5
A63: 2.4.5 | B63: Does the retention of the junior analyst exceed 3 years? | C63: Level 5 - Optimized | H63: 4 | I63: 5
A64: 2.4.6 | B64: Does the retention of the senior analyst exceed 5 years? | C64: Level 5 - Optimized | H64: 4 | I64: 5
A65: 2.4.7 | B65: What percentage of analysts hold post secondary degrees? | C65: Level 5 - Optimized | H65: 4 | I65: 5 | J65: 0.35
A66: 2.4.8 | B66: What percentage of analysts hold technical degrees? | C66: Level 5 - Optimized | H66: 4 | I66: 5 | J66: 1
A67: 2.5 - Skills Assessment
A68: 2.5.1 | B68: Is there a formally documented list of analysts skills? | C68: Level 5 - Optimized | H68: 4 | I68: 5
A69: 2.5.2 | B69: Are there any periodic skills assessments done? | C69: Level 5 - Optimized | H69: 4 | I69: 5
A70: 2.5.3 | B70: Are skills assessments used to improve training programs? | C70: Level 5 - Optimized | H70: 4 | I70: 5
A71: 2.5.4 | B71: Are the results of any periodic skill assessments used in the appraisal process? | C71: Level 5 - Optimized | H71: 4 | I71: 5
A72: 2.5.5 | B72: Is there any form of annual SOC response exercise? | H72: 4 | I72: 5
A73: 2.5.6 | B73: Are the results of a group training exercise used to improve SOC Operations? | C73: Level 5 - Optimized | H73: 4 | I73: 5
A74: 2.6 - Career Path
A75: 2.6.1 | B75: What is the feeder pool for SOC Analysts? NOC, Deskside support, External hires | C75: Level 5 - Optimized | H75: 4 | I75: 5
A76: 2.6.2 | B76: Are over 50% of the SOC analysts hired for their SOC expertise? | C76: Level 5 - Optimized | H76: 4 | I76: 5
A77: 2.6.3 | B77: Does the organization have a documented SOC analyst career progression plan? | C77: Level 5 - Optimized | H77: 4 | I77: 5
A78: 2.6.4 | B78: Are SOC analysts promoted into other internal security positions? | C78: Level 5 - Optimized | H78: 4 | I78: 5
A79: 2.6.5 | B79: Is there a SOC internal internship program? Job shadowing, into the SOC and from the SOC. | C79: Level 5 - Optimized | H79: 4 | I79: 5
A80: 2.7 - Leadership
A81: 2.7.1 | B81: Is there a maximum of 4:1 leverage of Level 1:2 analysts? | C81: Level 5 - Optimized | H81: 4 | I81: 5
A82: 2.7.2 | B82: Does the SOC have a four year strategic plan? | C82: Level 5 - Optimized | H82: 4 | I82: 5
A83: 2.7.3 | B83: Does the SOC have a dedicated manager? | C83: Level 5 - Optimized | H83: 4 | I83: 5
A84: 2.7.4 | B84: Do all analysts report to the SOC manager? | C84: Level 5 - Optimized | H84: 4 | I84: 5
A85: 2.7.5 | B85: Does the SOC manager have a weekly cadence with the SOC team? | C85: Level 5 - Optimized | H85: 4 | I85: 5
A86: 2.7.6 | B86: Does the SOC manager have formal annual metoring program for the SOC? | C86: Level 5 - Optimized | H86: 4 | I86: 5
A87: 2.7.7 | B87: Does the SOC manager participate in major security initiatives at the organization? | C87: Level 5 - Optimized | H87: 4 | I87: 5
A88: 2.7.8 | B88: Does the SOC manager have the ability to influence the SOC budget? | C88: Level 0 - Does not exist | H88: 4 | I88: 5
A89: 2.7.9 | B89: Is a night manager assigned in the SOC? | C89: Level 5 - Optimized | H89: 4 | I89: 5
A90: 2.7.10 | B90: Does the SOC manager report to the CISO or Security aparatus in the organization? | C90: Level 0 - Does not exist | H90: 4 | I90: 5
A91: 2.7.11 | B91: Does the SOC have a 360 degree feedback process? | C91: Level 5 - Optimized | H91: 4 | I91: 5
A92: 2.7.12 | B92: Does the SOC manager have annual team strategy sessions with the team? | C92: Level 5 - Optimized | H92: 4 | I92: 5
B94: SUMMARY Score | C94: =#REF! -> #REF! | D94: =#REF! -> #REF! | E94: =#REF! -> #REF! | F94: =#REF! -> #REF! | G94: =#REF! -> #REF! | H94: =#REF! -> #REF! | I94: =#REF! -> #REF!
B95: =A4 -> 2.1 - Resourcing | C95: =SUM(C5:C25) -> 0 | D95: =SUM(D5:D25) -> 0 | E95: =SUM(E5:E25) -> 0 | F95: =SUM(F5:F25) -> 0 | G95: =SUM(G5:G25) -> 0 | H95: =SUM(H5:H25) -> 84 | I95: =SUM(I5:I25) -> 105
B96: =A27 -> 2.2 - Training | C96: =SUM(C28:C47) -> 0 | D96: =SUM(D28:D47) -> 0 | E96: =SUM(E28:E47) -> 0 | F96: =SUM(F28:F47) -> 0 | G96: =SUM(G28:G47) -> 0 | H96: =SUM(H28:H47) -> 80 | I96: =SUM(I28:I47) -> 100
B97: =A48 -> 2.3 - Certifications | C97: =SUM(C49:C57) -> 0 | D97: =SUM(D49:D57) -> 0 | E97: =SUM(E49:E57) -> 0 | F97: =SUM(F49:F57) -> 0 | G97: =SUM(G49:G57) -> 0 | H97: =SUM(H49:H57) -> 36 | I97: =SUM(I49:I57) -> 45
B98: =A58 -> 2.4 - Relevant Experience | C98: =SUM(C59:C66) -> 0 | D98: =SUM(D59:D66) -> 0 | E98: =SUM(E59:E66) -> 0 | F98: =SUM(F59:F66) -> 0 | G98: =SUM(G59:G66) -> 0 | H98: =SUM(H59:H66) -> 32 | I98: =SUM(I59:I66) -> 40
B99: =A67 -> 2.5 - Skills Assessment | C99: =SUM(C68:C73) -> 0 | D99: =SUM(D68:D73) -> 0 | E99: =SUM(E68:E73) -> 0 | F99: =SUM(F68:F73) -> 0 | G99: =SUM(G68:G73) -> 0 | H99: =SUM(H68:H73) -> 24 | I99: =SUM(I68:I73) -> 30
B100: =A74 -> 2.6 - Career Path | C100: =SUM(C75:C79) -> 0 | D100: =SUM(D75:D79) -> 0 | E100: =SUM(E75:E79) -> 0 | F100: =SUM(F75:F79) -> 0 | G100: =SUM(G75:G79) -> 0 | H100: =SUM(H75:H79) -> 20 | I100: =SUM(I75:I79) -> 25
B101: =A80 -> 2.7 - Leadership | C101: =SUM(C81:C92) -> 0 | D101: =SUM(D81:D92) -> 0 | E101: =SUM(E81:E92) -> 0 | F101: =SUM(F81:F92) -> 0 | G101: =SUM(G81:G92) -> 0 | H101: =SUM(H81:H92) -> 48 | I101: =SUM(I81:I92) -> 60
B102: TOTAL | C102: =SUM(C95:C99) -> 0 | D102: =SUM(D95:D99) -> 0 | E102: =SUM(E95:E99) -> 0 | F102: =SUM(F95:F99) -> 0 | G102: =SUM(G95:G99) -> 0 | H102: =SUM(H95:H99) -> 256 | I102: =SUM(I95:I99) -> 320
B105: Summary Percentage | C105: =C94 -> #REF! | D105: =D94 -> #REF! | E105: =E94 -> #REF! | F105: =F94 -> #REF! | G105: =G94 -> #REF! | H105: =H94 -> #REF!
B106: =B95 -> 2.1 - Resourcing | C106: =C95/$I95 -> 0 | D106: =D95/$I95 -> 0 | E106: =E95/$I95 -> 0 | F106: =F95/$I95 -> 0 | G106: =G95/$I95 -> 0 | H106: =H95/$I95 -> 0.8
B107: =B96 -> 2.2 - Training | C107: =C96/$I96 -> 0 | D107: =D96/$I96 -> 0 | E107: =E96/$I96 -> 0 | F107: =F96/$I96 -> 0 | G107: =G96/$I96 -> 0 | H107: =H96/$I96 -> 0.8
B108: =B97 -> 2.3 - Certifications | C108: =C97/$I97 -> 0 | D108: =D97/$I97 -> 0 | E108: =E97/$I97 -> 0 | F108: =F97/$I97 -> 0 | G108: =G97/$I97 -> 0 | H108: =H97/$I97 -> 0.8
B109: =B98 -> 2.4 - Relevant Experience | C109: =C98/$I98 -> 0 | D109: =D98/$I98 -> 0 | E109: =E98/$I98 -> 0 | F109: =F98/$I98 -> 0 | G109: =G98/$I98 -> 0 | H109: =H98/$I98 -> 0.8
B110: =B99 -> 2.5 - Skills Assessment | C110: =C99/$I99 -> 0 | D110: =D99/$I99 -> 0 | E110: =E99/$I99 -> 0 | F110: =F99/$I99 -> 0 | G110: =G99/$I99 -> 0 | H110: =H99/$I99 -> 0.8
B111: =B100 -> 2.6 - Career Path | C111: =C100/$I100 -> 0 | D111: =D100/$I100 -> 0 | E111: =E100/$I100 -> 0 | F111: =F100/$I100 -> 0 | G111: =G100/$I100 -> 0 | H111: =H100/$I100 -> 0.8
...

Sheet 3 - Process
A2: 3 - Process Control Objectives
A3: Index | B3: Control Objective | C3: Current | D3: Peer | E3: Recommended | F3: Maximum | G3: Peer | H3: Recommended | I3: Maximum | R3: Comments
A4: 3.1 - SOC Threat Management
A5: 3.1.1 | B5: Does the organization have a capability to real time capability to monitor for perimeter threats? | C5: Level 4 - Managed | H5: 4 | I5: 5 | J5: IPS coverage is only very limited to certains clients at the moment. | R5: Firewall logs being forwarded to SIEM. Rules configured to monitor network based attacks. Prevention mechanisms (e.g. IPS) does not exists.
A6: 3.1.2 | B6: Does the organization have a capability to real time capability to monitor for insider threats? | C6: Level 4 - Managed | H6: 4 | I6: 5 | K6: Vulnerability and Threat Management Report (Aaron Morrison). Target state micro/macro designs. Part of the Threat and Vulnerability Pillar
A7: 3.1.3 | B7: Does the organization have a capability to real time capability to monitor for DDoS threats? | C7: Level 4 - Managed | H7: 4 | I7: 5 | R7: Firewall logs being forwarded to SIEM. Rules configured to monitor DDoS attacks. Prevention mechanisms (e.g. DDoS devices) does not exists.
A8: 3.1.4 | B8: Does the organization have a capability to real time capability to monitor for Persistent Threats? | C8: Level 4 - Managed | H8: 4 | I8: 5 | R8: EDR agents installed on all the systems to prevent/ detect persistent attacks. EDR logs are currently not forwarded to SIEM (integration is in progress).
A9: 3.1.5 | B9: Does the organization have a capability to real time capability to monitor for Supply Chain Threats? | C9: Level 3 - Defined | H9: 4 | I9: 5
A10: 3.1.6 | B10: Does a formalized CSIRT exist? | C10: Level 2 - Repeatable | H10: 4 | I10: 5 | J10: CSIRT function is defined as part of the Enterprise Incidenet Management function | K10: Adhoc at this stage. No real documentation. ESCF shows evidence but no documentation found. Security Incident Handling Procedure Document?
A11: 3.1.7 | B11: Does the Threat Monitoring capability have formalized integration with CSIRT? | C11: Level 3 - Defined | H11: 4 | I11: 5
A12: 3.1.8 | B12: Does the organization have a formalized threat determination and development methodology that is used by the Threat Monitoring capability? | C12: Level 4 - Managed | H12: 4 | I12: 5 | K12: Speak to Aaron Morrison. | R12: New usecases are created and configured based on threat intelligence inputs
A13: 3.1.9 | B13: Testing for unvalidated input | C13: Level 4 - Managed | H13: 4 | I13: 5 | J13: The security o[perations team has a tool to run scans against new websites. | R13: Detected and Prevented by AKAMAI WAF
A14: 3.1.10 | B14: Testing for broken access control | C14: Level 4 - Managed | H14: 4 | I14: 5 | R14: Detected and Prevented by AKAMAI WAF
A15: 3.1.11 | B15: Testing for broken authentication control and session management | C15: Level 4 - Managed | H15: 4 | I15: 5 | R15: Detected and Prevented by AKAMAI WAF
A16: 3.1.12 | B16: Testing for secure communications | C16: Level 4 - Managed | H16: 4 | I16: 5 | R16: Detected and Prevented by AKAMAI WAF
A17: 3.1.13 | B17: Testing for cross site scripting attacks | C17: Level 4 - Managed | H17: 4 | I17: 5 | J17: The security o[perations team has a tool to run scans against new websites. | R17: Detected and Prevented by AKAMAI WAF
A18: 3.1.14 | B18: Perform monthly review of PRA process effectiveness | H18: 4 | I18: 5 | K18: Peronnel Risk Assessment. Yes to access reviews on quarterly basis. Not specific to Personnel risk based on roles. Network access specific only. All done by ETS for Service Operations (Paul Barry). Information Security Framework.
A19: 3.1.15 | B19: Perform monthly review of Cyber Training process effectiveness | C19: Level 5 - Optimized | H19: 4 | I19: 5 | K19: Rivka might refer to induction material
A20: 3.1.16 | B20: Does the SOC provide role based access to audit logs based on a "need to know" basis | C20: Level 5 - Optimized | H20: 4 | I20: 5 | J20: Security Operations currently does not collect logs.
A21: 3.1.17 | B21: Does the SOC generate alarm conditions based on Sample Company risk/threat use cases in real time | C21: Level 5 - Optimized | H21: 4 | I21: 5 | J21: Threat management process has no direct links to real time monitoring.
A22: 3.1.18 | B22: Does the SOC generate alarm conditions based on Sample Company specfied ESCF risk/threat use cases in real time | C22: Level 5 - Optimized | H22: 4 | I22: 5 | J22: Security Operations currently aligns with a Security framework, and is only just trying to more to ESCF.
A23: 3.1.19 | B23: Does the SOC generate an alarm condition for new vulnerability detected on critical/sensitive networks | C23: Level 3 - Defined | H23: 4 | I23: 5 | J23: No logs are collected for real time monitoring. | R23: VMS solution is not integrated with SOC
A24: 3.1.20 | B24: Does the SOC generate an alarm condition for new port and service detected on critical/sensitive networks | C24: Level 3 - Defined | H24: 4 | I24: 5 | J24: No logs are collected for real time monitoring. | R24: Network scanning solution is not integrated with SOC
A25: 3.1.21 | B25: Does the SOC correlate configuration changes against change management approved tickets | C25: Level 2 - Repeatable | H25: 4 | I25: 5 | J25: No logs are collected for real time monitoring. | R25: SOC team does not receive the change approved tickets
A26: 3.1.22 | B26: Does the SOC generate an alarm condition when a default/vendor account has been used | C26: Level 0 - Does not exist | H26: 4 | I26: 5 | J26: No logs are collected for real time monitoring.
A27: 3.1.23 | B27: Does the SOC generate an alarm condition when an account has been shared | C27: Level 0 - Does not exist | H27: 4 | I27: 5 | J27: No logs are collected for real time monitoring.
A28: 3.1.24 | B28: Does the SOC generate an alarm condition when an expired/disabled user account has been accessed | C28: Level 5 - Optimized | H28: 4 | I28: 5 | J28: No logs are collected for real time monitoring.
A29: 3.1.25 | B29: Does the SOC generate an alarm condition when a previous employees user account has been accessed | C29: Level 5 - Optimized | H29: 4 | I29: 5 | J29: No logs are collected for real time monitoring.
A30: 3.1.26 | B30: Does the SOC prioritize alarming based on value to the business | C30: Level 5 - Optimized | H30: 4 | I30: 5 | J30: No logs are collected for real time monitoring.
A31: 3.1.27 | B31: Does the SOC generate alarm in instances of unauthorized configuration changes | C31: Level 2 - Repeatable | H31: 4 | I31: 5 | J31: No logs are collected for real time monitoring.
A32: 3.1.28 | B32: Does the SOC generate an alarm for anomolous or unauthorized access controls | C32: Level 4 - Managed | H32: 4 | I32: 5 | J32: No logs are collected for real time monitoring.
A33: 3.1.29 | B33: Does the SOC generate an alarm for anomolous network flow | C33: Level 5 - Optimized | H33: 4 | I33: 5 | J33: No logs are collected for real time monitoring.
A34: 3.1.30 | B34: Does the SOC generate an alarm for unauthorized maintenance or mis-use of privilege | C34: Level 4 - Managed | H34: 4 | I34: 5 | J34: No logs are collected for real time monitoring. | R34: Usecases enabled for privileged user login
A35: 3.1.31 | B35: Does the SOC generate an alarm on deviation from segregation of duties | C35: Level 0 - Does not exist | H35: 4 | I35: 5 | J35: No logs are collected for real time monitoring.
A36: 3.1.32 | B36: Does the SOC alarm on any failed log into the ESP | C36: Level 0 - Does not exist | H36: 4 | I36: 5 | R36: EP are not monitored for failed/ unauthorised login
A37: 3.1.33 | B37: Does the SOC alarm on any login attempt to the ESP that is not authorized | C37: Level 0 - Does not exist | H37: 4 | I37: 5 | R37: EP are not monitored for failed/ unauthorised login
A38: 3.1.34 | B38: SOC will alarm on attempts at or actual unauthorized accesses. | C38: Level 5 - Optimized | H38: 4 | I38: 5
A39: 3.1.35 | B39: Does the SOC alarm if a physical door, gate or window is opened outside of normal activity | C39: Level 0 - Does not exist | H39: 4 | I39: 5
A40: 3.1.36 | B40: Does the SOC alarm under unsual network flow or worm type activitity | C40: Level 5 - Optimized | H40: 4 | I40: 5
A41: 3.1.37 | B41: Does the SOC monitor unusual activity from AV and anti-malware devices | C41: Level 3 - Defined | H41: 4 | I41: 5 | J41: Security Operations has AV responsibilities. Some alarms are in place but no real time monitoring is in place.
A42: 3.1.38 | B42: Does the SOC detect unauthorized use of indivudual or shared system accounts | C42: Level 3 - Defined | H42: 4 | I42: 5 | R42: System accounts/ service accounts are not monitored
A43: 3.1.39 | B43: Does the SOC detect if user accounts are created without approval from designated personnel | C43: Level 5 - Optimized | H43: 4 | I43: 5
A44: 3.1.40 | B44: Does the SOC detect use of unauthorized ports and services required for operations | C44: Level 5 - Optimized | H44: 4 | I44: 5 | R44: RDP access not from CyberArk
A45: 3.1.41 | B45: Does the SOC have a documented exception handling process? | C45: Level 2 - Repeatable | H45: 4 | I45: 5
A46: 3.1.42 | B46: Does the SOC have documented threat management daily quality assurance measures? | C46: Level 5 - Optimized | H46: 4 | I46: 5 | R46: Daily / Weekly reports are shared
A47: 3.1.43 | B47: Does the SOC have documented threat management weekly quality assurance measures? | C47: Level 5 - Optimized | H47: 4 | I47: 5 | R47: Daily / Weekly reports are shared
A48: 3.2 - SOC Analytical Process
A49: 3.2.1 | B49: Does the SOC have a documented process for SOC Base Event Analysis? | C49: Level 5 - Optimized | H49: 4 | I49: 5
A50: 3.2.2 | B50: Does the SOC have a documented process for SOC Alarm Event Analysis? | C50: Level 5 - Optimized | H50: 4 | I50: 5
A51: 3.2.3 | B51: Does the SOC have documented threat playbooks and decision trees for critical use cases? | C51: Level 5 - Optimized | H51: 4 | I51: 5
A52: 3.2.4 | B52: Does the SOC have documented procedures for detecting low and slow attacks? | C52: Level 3 - Defined | H52: 4 | I52: 5 | R52: UEBA not enabled
A53: 3.2.5 | B53: Does the SOC have documented procedures for detecting anomolies and outliers? | C53: Level 5 - Optimized | H53: 4 | I53: 5
A54: 3.2.6 | B54: Does the SOC have a documented procedure for case handover for high severity alarms? | C54: Level 5 - Optimized | H54: 4 | I54: 5
A55: 3.2.7 | B55: Does the SOC have a documented Intrusion Analysis procedure? | C55: Level 5 - Optimized | H55: 4 | I55: 5
A56: 3.2.8 | B56: Do process/plan?s exist for scheduled mock threat scenarios? | C56: Level 2 - Repeatable | H56: 4 | I56: 5
A57: 3.2.9 | B57: Do process/plan?s exist for ad-hoc mock threat scenarios? | C57: Level 2 - Repeatable | H57: 3 | I57: 5
A58: 3.2.10 | B58: Does a process/plan?exist to develop new threat scenarios (use cases)? | C58: Level 5 - Optimized | H58: 5 | I58: 5
A59: 3.2.11 | B59: Is there a structured process/plan?for developing these threat scenarios? | C59: Level 5 - Optimized | H59: 4 | I59: 5
A60: 3.2.12 | B60: How are unknown events diagnosed? | C60: Level 4 - Managed | H60: 3 | I60: 5
A61: 3.2.13 | B61: Does the SOC have a documented Subtle event detection procedure? | C61: Level 2 - Repeatable | H61: 4 | I61: 5
A62: 3.2.14 | B62: Does the SOC have subtle event tools and training? | C62: Level 2 - Repeatable | H62: 4 | I62: 5
A63: 3.2.15 | B63: Is there a comprehensive listing of reports, their audience and business purpose? | C63: Level 5 - Optimized | H63: 4 | I63: 5 | J63: Security operations currently provide reporting for various teams.
A64: 3.2.16 | B64: How is operational and analytical security information shared? | C64: Level 5 - Optimized | H64: 4 | I64: 5
A65: 3.2.17 | B65: How is external situational awareness maintained? CERT/CC, NIPC, Information Fusion Procedure | C65: Level 5 - Optimized | H65: 4 | I65: 5
A66: 3.2.18 | B66: Does the SOC have a focused monitoring procedure? | C66: Level 5 - Optimized | H66: 4 | I66: 5
A67: 3.2.19 | B67: Does the SOC have a new analyst boarding procedure? | C67: Level 5 - Optimized | H67: 4 | I67: 5
A68: 3.2.20 | B68: Does the SOC subscribe to external Intelligence services? iDefense, Symantec, ISS, etc... | C68: Level 5 - Optimized | H68: 4 | I68: 5
A69: 3.2.21 | B69: Is there a documented process/plan?for filtering out known false positives? | C69: Level 5 - Optimized | H69: 4 | I69: 5
A70: 3.2.22 | B70: Are all correlation logic and rules documented? | C70: Level 5 - Optimized | H70: 4 | I70: 5
A71: 3.2.23 | B71: Does the SOC have up-to-date network diagrams and information? | C71: Level 3 - Defined | H71: 4 | I71: 5
A72: 3.3 - SOC Engineering Processes
A73: 3.3.1 | B73: Does the SOC have a documented process for onboarding new event sources? | C73: Level 5 - Optimized | H73: 4 | I73: 5
A74: 3.3.2 | B74: Does the SOC have a documented process for onboarding new requests? | C74: Level 5 - Optimized | H74: 4 | I74: 5
A75: 3.3.3 | B75: Does the SOC have a documented process for the structure, hierachy and work instructions for implementing SIEM content? | C75: Level 5 - Optimized | H75: 4 | I75: 5
A76: 3.3.4 | B76: Does the SOC have a documented process for conducting capacity analysis and forcasting on an annual (or on new request for coverage from LoB's) cycle? | C76: Level 5 - Optimized | H76: 4 | I76: 5
A77: 3.3.5 | B77: Does the SOC have configuration playbooks for common SOC tasks? | C77: Level 5 - Optimized | H77: 4 | I77: 5
A78: 3.3.6 | B78: Does the SOC have maintenance handbooks for maintenance of SOC technology? | C78: Level 5 - Optimized | H78: 4 | I78: 5
A79: 3.3.7 | B79: Does the SOC have maintenance handbooks for failure recovery of SOC technology? | C79: Level 5 - Optimized | H79: 4 | I79: 5
A80: 3.3.8 | B80: Does the SOC have a timetable (and procedures) for scheduled update and patching of SOC technology? | C80: Level 5 - Optimized | H80: 4 | I80: 5
A81: 3.3.9 | B81: Does the SOC have a timetable (and procedures) for security context updates (e.g. geocode, connector updates etc)? | C81: Level 5 - Optimized | H81: 4 | I81: 5
A82: 3.3.10 | B82: Does the SOC have templates to provide to requestors for SOC services (e.g. requesting new creports or SOC review processes)? | C82: Level 5 - Optimized | H82: 4 | I82: 5
A83: 3.3.11 | B83: Are service requests handled by a dedicated SOC Engineer? | C83: Level 5 - Optimized | H83: 4 | I83: 5
A84: 3.3.12 | B84: Does the SOC have a documented process for priotizing and providing SLO for service requests? | C84: Level 5 - Optimized | H84: 4 | I84: 5
A85: 3.4 - SOC Operations and Continuity
A86: 3.4.1 | B86: Does the SOC have a documented change management process/plan (for the SOC)? | C86: Level 5 - Optimized | H86: 4 | I86: 5 | K86: Yes they do. Yes it is documented.
A87: 3.4.2 | B87: Does the SOC have a documented capacity planning process/plan (for the SOC)? | C87: Level 5 - Optimized | H87: 4 | I87: 5 | K87: Yes but part of ETS.
A88: 3.4.3 | B88: Does the SOC have a documented release management process/plan (for the SOC)? | C88: Level 5 - Optimized | H88: 4 | I88: 5 | K88: Part of the greater release management process.
A89: 3.4.4 | B89: Does the SOC have a documented configuration management process/plan? | C89: Level 5 - Optimized | H89: 4 | I89: 5 | K89: Implemented as part of the greater change management process. No evidence to show that they review that the configuration is implemented.
A90: 3.4.5 | B90: Does the SOC have a documented availability management process/plan? | C90: Level 5 - Optimized | H90: 4 | I90: 5 | K90: Service level management is implemented and is customer driven. Nothing specific for security for availability management.
A91: 3.4.6 | B91: Does the SOC have a documented quality management process/plan? | C91: Level 5 - Optimized | H91: 4 | I91: 5 | K91: Nothing found in ESCF.
A92: 3.4.7 | B92: Does the SOC have a documented threat management process/plan?and handbook? | C92: Level 5 - Optimized | H92: 4 | I92: 5 | J92: Threat management is currently done, with intelligence reports used, but it is not fully documented. | K92: Part of the vulnerability and threat management ETS Pillar.
A93: 3.4.8 | B93: Does the SOC have a documented Incident handling process/plan? | C93: Level 5 - Optimized | H93: 4 | I93: 5 | K93: Ad-hoc only. Security Incident Management Procedure Document. Aaron Ta to follow-up.
A94: 3.4.9 | B94: Does the SOC have interdepartment process/plan?s for routing of calls from non authenticated sources? | C94: Level 0 - Does not exist | H94: 4 | I94: 5 | K94: No known hotline process.
A95: 3.4.10 | B95: Does the SOC have interdepartment process/plan?s for employee handling? | C95: Level 0 - Does not exist | H95: 4 | I95: 5
A96: 3.4.11 | B96: Does the SOC have a documented Case management process/plan? | C96: Level 5 - Optimized | H96: 4 | I96: 5 | K96: Remedy BMC Tool used as case management tool. Documentation
A97: 3.4.12 | B97: Does the SOC create cases within your SIEM implementation or Does the SOC use an external case management system? | C97: Level 5 - Optimized | H97: 4 | I97: 5 | R97: Tickets are created on central ITSM tool (SNOW)
A98: 3.4.13 | B98: Does the SOC have a formal shift log process/plan? | C98: Level 5 - Optimized | H98: 4 | I98: 5 | J98: Security operations is currently not a SOC and has no shifts. Monitoring is only during business hours.
A99: 3.4.14 | B99: Does the SOC have the capability to review old shift logs with ease? | C99: Level 5 - Optimized | H99: 4 | I99: 5 | J99: No logs are currently collected.
A100: 3.4.15 | B100: Does the SOC have a daily meeting to review SOC activity? | C100: Level 5 - Optimized | H100: 4 | I100: 5 | J100: Security operations is currently not a SOC and has no shifts. Monitoring is only during business hours.
A101: 3.4.16 | B101: Does the SOC have a documented shift turn-over process/plan? | C101: Level 5 - Optimized | H101: 4 | I101: 5 | J101: Security operations is currently not a SOC and has no shifts. Monitoring is only during business hours.
...

Sheet 4 - Technology Functional
A2: 4 - Technology Control Objectives
A3: Index | B3: Control Objective | C3: Current | D3: Peer | E3: Recommended | F3: Maximum | G3: Comments
A4: 4.1 - Security Information and Event Management
A5: 4.1.1 | B5: Does a production SIEM capability exist? | C5: Level 5 - Optimized | E5: 4 | F5: 5
A6: 4.1.2 | B6: Does the SIEM address SOC availability requirements? | C6: Level 5 - Optimized | E6: 4 | F6: 5
A7: 4.1.3 | B7: Does a dev and sandbox environment for SIEM exist? | C7: Level 5 - Optimized | E7: 4 | F7: 5
A8: 4.1.4 | B8: How do you monitor infrastructure performance? (availability, throughout, latency, average > peak > surge) | C8: Level 5 - Optimized | E8: 4 | F8: 5
A9: 4.1.5 | B9: Do you monitor any of the product vendor monitoring consoles to supplement your SIEM? | C9: Level 0 - Does not exist | E9: 4 | F9: 5
A10: 4.1.6 | B10: Does the organization have a support contract with your vendor? | C10: Level 5 - Optimized | E10: 4 | F10: 5
A11: 4.1.7 | B11: Does the organization have remote access to the SIEM? VPN, web console, etc… | C11: Level 5 - Optimized | E11: 4 | F11: 5
A12: 4.1.8 | B12: Is your SIEM in a hardened data center? | C12: Level 5 - Optimized | E12: 4 | F12: 5
A13: 4.1.9 | B13: Is SIEM RBAC configured based on role and function for SOC analysts? | C13: Level 5 - Optimized | E13: 4 | F13: 5
A14: 4.1.10 | B14: Is RBAC reviewed and approved by the SOC management on an annual basis, at a minimum? | C14: Level 5 - Optimized | E14: 4 | F14: 5
A15: 4.1.11 | B15: Does the organization have a documented upgrade procedure? | C15: Level 5 - Optimized | E15: 4 | F15: 5
A16: 4.1.12 | B16: Are all internal data streams encrypted? (Network connections) | C16: Level 5 - Optimized | E16: 4 | F16: 5
... A23: 4.1.19 | B23: Has the case management system been updated with SOC specific fields | C23: Level 5 - Optimized | E23: 4 | F23: 5
A24: 4.1.20 | B24: Are the SIEM assets/services classified as critical and listed accordingly? | C24: Level 5 - Optimized
A25: 4.1.21 | B25: Is there a support model in place for SIEM users? | C25: Level 5 - Optimized
A26: 4.1.22 | B26: Is there a defined role and process for SIEM account/access management? | C26: Level 5 - Optimized
A27: 4.2 - Intelligence Correlation
A28: 4.2.1 | B28: Does the organization integrate and correlate against emerging threat intelligence? | C28: Level 5 - Optimized | E28: 4 | F28: 5
A29: 4.2.2 | B29: Does the organization integrate and correlate against exploit intelligence? | C29: Level 5 - Optimized | E29: 4 | F29: 5
A30: 4.2.3 | B30: Does the organization integrate and correlate against domain reputation? | C30: Level 5 - Optimized | E30: 4 | F30: 5
A31: 4.2.4 | B31: Does the organization integrate brand intelligence? | C31: Level 5 - Optimized | E31: 4 | F31: 5
A32: 4.2.5 | B32: Does the organization integrate and correlate against Malware Drone IP intelligence? | C32: Level 5 - Optimized | E32: 4 | F32: 5
A33: 4.2.6 | B33: Does the organization integrate and correlate against MX intelligence? | C33: Level 5 - Optimized | E33: 4 | F33: 5
A34: 4.2.7 | B34: Does the organization integrate and correlate against Tor Exit Node intelligence? | C34: Level 5 - Optimized | E34: 4 | F34: 5
A35: 4.2.8 | B35: Does the organization integrate and correlate against vulnerability context intelligence? | C35: Level 0 - Does not exist | E35: 4 | F35: 5 | G35: No integration with VMS
A36: 4.2.9 | B36: Does the organization integrate and correlate against malware binary intelligence? | C36: Level 5 - Optimized | E36: 4 | F36: 5
A37: 4.3 - Architecture
A38: 4.3.1 | B38: Is the SOC environment in an access control environment? | C38: Level 5 - Optimized | E38: 4 | F38: 5
A39: 4.3.2 | B39: Does IDS exist at the ingress of the Corporate network into the SOC? | C39: Level 5 - Optimized | E39: 4 | F39: 5
A40: 4.3.3 | B40: Does the SOC have an out of band Internet connection (e.g. cable or ADSL)? | C40: Level 5 - Optimized | E40: 4 | F40: 5
A41: 4.3.4 | B41: Does the SOC have dedicated situational awareness screens? | C41: Level 5 - Optimized | E41: 4 | F41: 5
A42: 4.3.5 | B42: Are these situational awareness screens visible from all SOC Level 1 analyst workstations? | C42: Level 5 - Optimized | E42: 4 | F42: 5
A43: 4.3.6 | B43: Are measures put in place that the main situational awareness screen cannot be tampered with? | C43: Level 5 - Optimized | E43: 4 | F43: 5
A44: 4.3.7 | B44: Does the organization have detailed and current architecture diagrams? | C44: Level 5 - Optimized | E44: 4 | F44: 5
A45: 4.3.8 | B45: Describe security measures for architecture: SIM/SEM, collection servers and endpoints. | C45: Level 5 - Optimized | E45: 4 | F45: 5
A46: 4.3.9 | B46: How do you provide high availability? Facilities (network, power, system redundancy). | C46: Level 5 - Optimized | E46: 4 | F46: 5
A47: 4.3.10 | B47: How is Information Security implemented for the entire architecture? | C47: Level 5 - Optimized | E47: 4 | F47: 5
A48: 4.3.11 | B48: Are architecure changes strictly controlled by change management? Configuration management | C48: Level 5 - Optimized | E48: 4 | F48: 5
A49: 4.3.12 | B49: Does the organization have a documented list of all end point security devices that report to the SIEM? | C49: Level 5 - Optimized | E49: 4 | F49: 5
... A58: 4.3.21 | B58: Does the SOC have a documentation repository? | C58: Level 5 - Optimized | E58: 4 | F58: 5
A59: 4.3.22 | B59: Does the SOC have a DSL? | C59: Level 5 - Optimized | E59: 4 | F59: 5 | G59: MPLS lines are available
A60: 4.3.23 | B60: Corporate logging standards are adhered to across all the Business Units (BU's). | C60: Level 3 - Defined
A61: 4.3.24 | B61: There exist specific standards on logging and/or instrumentation for the IT infrastructure (including servers, databases, mainframes, mini, PC, SAN/NAS,.etc) | C61: Level 3 - Defined
A62: 4.3.25 | B62: There exist specific standards on logging and/or instrumentation for your Network infrastructure. | C62: Level 3 - Defined
A63: 4.3.26 | B63: There are documented corporate-level logging requirements or standards in place today which includes but not limited to location, retention, content, format. | C63: Level 3 - Defined
A64: 4.4 - Correlation
A65: 4.4.1 | B65: Are raw events monitored or are correlated events monitored? | C65: Level 5 - Optimized | E65: 4 | F65: 5
A66: 4.4.2 | B66: What types of events are correlated? | C66: Level 5 - Optimized | E66: 4 | F66: 5 | G66: All the security related events are correlated
A67: 4.4.3 | B67: How well are events correlated? Metrics? | C67: Level 5 - Optimized | E67: 4 | F67: 5
A68: 4.4.4 | B68: Does the organization have cross device type correlation? | C68: Level 5 - Optimized | E68: 4 | F68: 5
A69: 4.4.5 | B69: Does the organization have inter device type correlation? | C69: Level 5 - Optimized | E69: 4 | F69: 5
A70: 4.4.6 | B70: Does the organization have aggregation? | C70: Level 5 - Optimized | E70: 4 | F70: 5
A71: 4.4.7 | B71: Are all rules documented and explained? | C71: Level 5 - Optimized | E71: 4 | F71: 5
A72: 4.4.8 | B72: Does the organization have automatic notification rules? | C72: Level 5 - Optimized | E72: 4 | F72: 5
A73: 4.4.9 | B73: Does the organization have long-term subtle event rules? | C73: Level 5 - Optimized | E73: 4 | F73: 5
A74: 4.4.10 | B74: SOC should generate an alarm condition for any custom use cases | C74: Level 5 - Optimized | E74: 4 | F74: 5
A75: 4.4.11 | B75: SOC should generate an alarm condition for new vulnerability detected on critical/sensitive networks | C75: Level 3 - Defined | E75: 4 | F75: 5 | G75: VMS solution is not integrated
A76: 4.4.12 | B76: SOC should generate an alarm condition for new port and service detected on critical/sensitive networks | C76: Level 3 - Defined | E76: 4 | F76: 5 | G76: Network scanning solution is not integrated with SOC
A77: 4.4.13 | B77: SOC should correlate configuration changes against change management approved tickets | C77: Level 2 - Repeatable | E77: 4 | F77: 5 | G77: SOC team does not receive the change approved tickets
A78: 4.4.14 | B78: SOC should generate an alarm condition when a default/vendor account has been used | C78: Level 0 - Does not exist | E78: 4 | F78: 5
A79: 4.4.15 | B79: SOC should generate an alarm condition when an account has been shared | C79: Level 0 - Does not exist | E79: 4 | F79: 5
A80: 4.4.16 | B80: SOC should generate an alarm condition when an expired/disabled user account has been accessed | C80: Level 5 - Optimized | E80: 4 | F80: 5
A81: 4.4.17 | B81: SOC should generate an alarm condition when a previous employees user account has been accessed | C81: Level 5 - Optimized | E81: 4 | F81: 5
A82: 4.4.18 | B82: SOC should prioritize alarming based on value to the business | C82: Level 5 - Optimized | E82: 4 | F82: 5
A83: 4.4.19 | B83: SOC should generate alarm in instances of unauthorized configuration changes | C83: Level 2 - Repeatable | E83: 4 | F83: 5
A84: 4.4.20 | B84: SOC should generate an alarm for anomolous or unauthorized access controls | C84: Level 4 - Managed | E84: 4 | F84: 5
A85: 4.4.21 | B85: SOC should generate an alarm for anomolous network flow | C85: Level 5 - Optimized | E85: 4 | F85: 5
A86: 4.4.22 | B86: SOC should generate an alarm for unauthorized maintenance or mis-use of privilege | C86: Level 4 - Managed | E86: 4 | F86: 5 | G86: usecase enabled for privilege user login
A87: 4.4.23 | B87: SOC should generate an alarm on deviation from segregation of duties | C87: Level 0 - Does not exist | E87: 4 | F87: 5
A88: 4.4.24 | B88: SOC should alarm on any failed log into the ESP | C88: Level 0 - Does not exist | E88: 4 | F88: 5
A89: 4.4.25 | B89: SOC should alarm on any login attempt to the ESP that is not authorized | C89: Level 0 - Does not exist | E89: 4 | F89: 5
A90: 4.4.26 | B90: SOC will alarm on attempts at or actual unauthorized accesses. | C90: Level 5 - Optimized | E90: 4 | F90: 5
A91: 4.4.27 | B91: SOC should alarm if a physical door, gate or window is opened outside of normal activity | C91: Level 0 - Does not exist | E91: 4 | F91: 5 | G91: Physical security related alerts are not monitored on SOC. A separate monitoring process in place.
A92: 4.4.28 | B92: SOC should alarm under unsual network flow or worm type activitity | C92: Level 5 - Optimized | E92: 4 | F92: 5
A93: 4.4.29 | B93: SOC should monitor unusual activity from AV and anti-malware devices | C93: Level 3 - Defined | E93: 4 | F93: 5
A94: 4.4.30 | B94: SOC should detect unauthorized use of indivudual or shared system accounts | C94: Level 3 - Defined | E94: 4 | F94: 5 | G94: System accounts/ service accounts are not monitored
A95: 4.4.31 | B95: SOC should detect if user accounts are created without approval from designated personnel | C95: Level 5 - Optimized | E95: 4 | F95: 5
A96: 4.4.32 | B96: SOC should detect use of unauthorized ports and services required for operations | C96: Level 5 - Optimized | E96: 4 | F96: 5 | G96: RDP access without CyberArk
A97: 4.4.33 | B97: SOC should allow updates of authorized ports and services on an on demand basis | C97: Level 3 - Defined | E97: 4 | F97: 5 | G97: Monthly update is done for network hierarchy
A98: 4.4.34 | B98: SOC should escalate Severity 1 within 30 minutes (L1 escalation) | C98: Level 5 - Optimized | E98: 4 | F98: 5
A99: 4.4.35 | B99: SOC should escalate Severity 2 within 60 minutes (L2 escalation) | C99: Level 5 - Optimized | E99: 4 | F99: 5
A100: 4.4.36 | B100: SOC should escalate Severity 3 within 180 minutes (L3 escalation) | C100: Level 5 - Optimized | E100: 4 | F100: 5
A101: 4.4.37 | B101: SOC should update case management notes as required by the CSIRT | C101: Level 5 - Optimized | E101: 4 | F101: 5
A102: 4.4.38 | B102: SOC should have a separate escalation routing meschanism for Cyber Security Incidents | C102: Level 3 - Defined | E102: 4 | F102: 5 | G102: SNOW SIR module under implementation
A103: 4.4.39 | B103: What other types of events are monitored? (i.e. compliance, fraud, legal, HR, etc.) | C103: Level 0 - Does not exist | G103: Only security related events are monitored
A104: 4.5 - Reporting
A105: 4.5.1 | B105: SOC should provide Security Risk Metric Reports | C105: Level 5 - Optimized | E105: 4 | F105: 5
A106: 4.5.2 | B106: SOC should provide Monitoring Performance Metric Reports | C106: Level 5 - Optimized | E106: 4 | F106: 5
A107: 4.5.3 | B107: SOC should provide Security Trending Reports | C107: Level 5 - Optimized | E107: 4 | F107: 5
A108: 4.5.4 | B108: SOC should review audit logs of top high priority IDS events on a weekly basis | C108: Level 0 - Does not exist | E108: 4 | F108: 5
A109: 4.5.5 | B109: SOC should review audit logs of failure activity on a weekly basis | C109: Level 0 - Does not exist | E109: 4 | F109: 5
A110: 4.5.6 | B110: SOC should review logs and alarm conditions as defined by the Alarm section in this document on a weekly basis | C110: Level 5 - Optimized | E110: 4 | F110: 5
A111: 4.5.7 | B111: SOC should review all scheduled reports on a weekly basis prior to the Security Operational call | C111: Level 5 - Optimized | E111: 4 | F111: 5
A112: 4.5.8 | B112: SOC should provide provide reports of failed access to critical assets | C112: Level 5 - Optimized | E112: 4 | F112: 5
A113: 4.5.9 | B113: SOC should provide reports on Segregation of Duties violation | C113: Level 0 - Does not exist | E113: 4 | F113: 5
A114: 4.5.10 | B114: SOC should provide reports on role violation | C114: Level 0 - Does not exist | E114: 4 | F114: 5
A115: 4.5.11 | B115: SOC should provide metric reports on compliance effectiveness | C115: Level 0 - Does not exist | E115: 4 | F115: 5
...

Sheet 5 - Coverage
A2: 5 - Coverage
A3: Index | B3: Control Objective | C3: Current | D3: Peer | E3: Recommended | F3: Maximum | G3: Comments
A4: 5.1 - Infrastructure Event Coverage
A5: 5.1.1 | B5: Does the organization collect logs from File and Print Servers? | C5: Level 0 - Does not exist | E5: 4 | F5: 5
A6: 5.1.2 | B6: Does the organization collect logs from Application Servers? | C6: Level 4 - Managed | E6: 4 | F6: 5
A7: 5.1.3 | B7: Does the organization collect logs from NOS Authentication Servers (e.g. AD)? | C7: Level 5 - Optimized | E7: 4 | F7: 5
A8: 5.1.4 | B8: Does the organization classify and collect logs from critical servers? | C8: Level 5 - Optimized | E8: 4 | F8: 5
A9: 5.1.5 | B9: Does the organization classify and collect logs from servers that have classified data sets? | C9: Level 5 - Optimized | E9: 4 | F9: 5
A10: 5.1.6 | B10: Does the organization distinguish between classification between data sets (within the SOC)? | C10: Level 5 - Optimized | E10: 4 | F10: 5
A11: 5.1.7 | B11: Does the organization collect syslog from *NIX servers? | C11: Level 5 - Optimized | E11: 4 | F11: 5
A12: 5.1.8 | B12: Does the organization collect logs from enhanced auditing sub-sytems from *NIX (e.g. Solaris BSM)? | C12: Level 0 - Does not exist | E12: 4 | F12: 5
A13: 5.1.9 | B13: Does the organization collect logs from super user access control sub-systems? | C13: Level 5 - Optimized | E13: 4 | F13: 5
A14: 5.2 - Security Devices Coverage
A15: 5.2.1 | B15: Does the organization collect logs from firewall inspection points? | C15: Level 5 - Optimized | E15: 4 | F15: 5
A16: 5.2.2 | B16: Does the organization collect logs from management of firewalls (e.g. firewall admin logging)? | C16: Level 5 - Optimized | E16: 4 | F16: 5
A17: 5.2.3 | B17: Does the organization collect logs from the firewall OS (if applicable)? Please allocate 5 points if not applicable)? | C17: Level 5 - Optimized | E17: 4 | F17: 5
A18: 5.2.4 | B18: Does the organization collect logs from IDS/IPS? | C18: Level 0 - Does not exist | E18: 4 | F18: 5
A19: 5.2.5 | B19: Does the organization collect scan context from vulnerability scanners and use it for correlation)? | C19: Level 3 - Defined | E19: 4 | F19: 5 | G19: VMS Solution is not integrated
A20: 5.2.6 | B20: Does the organization collect port context from port scanners (and use it for correlation)? | C20: Level 5 - Optimized | E20: 4 | F20: 5
A21: 5.2.7 | B21: Does the organization collect web security context from web scanners (and use it for correlation)? | C21: Level 0 - Does not exist | E21: 4 | F21: 5
A22: 5.2.8 | B22: Does the organization collect logs from authentication servers? | C22: Level 5 - Optimized | E22: 4 | F22: 5
A23: 5.2.9 | B23: Does the organization collect logs from token authentication servers? | C23: Level 5 - Optimized | E23: 4 | F23: 5
A24: 5.2.10 | B24: Does the organization collect logs from Site to Site VPN's? | C24: Level 5 - Optimized | E24: 4 | F24: 5
A25: 5.2.11 | B25: Does the organization collect logs from SSL VPN's? | C25: Level 5 - Optimized | E25: 4 | F25: 5
A26: 5.2.12 | B26: Does the organization collect logs from external terminal servers (e.g. Citrix)? | C26: Level 5 - Optimized | E26: 4 | F26: 5
A27: 5.2.13 | B27: Does the organization collect logs from internal terminal servers? | C27: Level 5 - Optimized | E27: 4 | F27: 5
A28: 5.2.14 | B28: Does the organization collect logs from Wireless IDS and Rogue device detectors? | C28: Level 5 - Optimized | E28: 4 | F28: 5
A29: 5.2.15 | B29: Does the organization collect logs from file integrity sensors (e.g. Tripwire)? | C29: Level 0 - Does not exist | E29: 4 | F29: 5
A30: 5.2.16 | B30: Does the organization collect logs from Password Vaulting systems? | C30: Level 5 - Optimized | E30: 4 | F30: 5
A31: 5.3 - Advanced Threat Coverage
A32: 5.3.1 | B32: Does the organization collect logs from web content inspection devices? | C32: Level 0 - Does not exist | E32: 4 | F32: 5
A33: 5.3.2 | B33: Does the organization collect logs from SMTP content inspection devices? | C33: Level 5 - Optimized | E33: 4 | F33: 5
A34: 5.3.3 | B34: Does the organization collect logs from network forensic devices? | C34: Level 0 - Does not exist | E34: 4 | F34: 5
A35: 5.3.4 | B35: Does the organization collect logs from malware analysis devices? | C35: Level 5 - Optimized | E35: 4 | F35: 5
A36: 5.3.5 | B36: Does the organization collect logs from proxy servers? | C36: Level 5 - Optimized | E36: 4 | F36: 5
A37: 5.3.6 | B37: Does the organization collect logs from DHCP servers? | C37: Level 5 - Optimized | E37: 4 | F37: 5
A38: 5.3.7 | B38: Does the organization collect logs from forwarding DNS? | C38: Level 5 - Optimized | E38: 4 | F38: 5
A39: 5.3.8 | B39: Does the organization collect logs from authoritative DNS? | C39: Level 5 - Optimized | E39: 4 | F39: 5
A40: 5.4 - Network Device Coverage
A41: 5.4.1 | B41: Does the organization collect logs from access level switches? | C41: Level 5 - Optimized | E41: 4 | F41: 5
A42: 5.4.2 | B42: Does the organization collect logs from distribution level switches? | C42: Level 5 - Optimized | E42: 4 | F42: 5
A43: 5.4.3 | B43: Does the organization collect logs from WAN routers/switches? | C43: Level 5 - Optimized | E43: 4 | F43: 5
A44: 5.4.4 | B44: Does the organizaiton collect logs from Core routers/switches? | C44: Level 5 - Optimized | E44: 4 | F44: 5
A45: 5.4.5 | B45: Does the organization collect logs from perimeter network devices? | C45: Level 5 - Optimized | E45: 4 | F45: 5
A46: 5.4.6 | B46: Does the organization collect logs from assynchronize terminals? | C46: Level 0 - Does not exist | E46: 4 | F46: 5
A47: 5.4.7 | B47: Does the organization collect flows from network devices? | C47: Level 5 - Optimized | E47: 4 | F47: 5
A48: 5.4.8 | B48: Does the organization collect logs from AAA systems (e.g. SecureACS)? | C48: Level 0 - Does not exist | E48: 4 | F48: 5
A49: 5.4.9 | B49: Does the organization collect logs from Network Management Systems) | C49: Level 0 - Does not exist | E49: 4 | F49: 5
A50: 5.4.10 | B50: Does the organization collect logs from DHCP servers? | C50: Level 5 - Optimized | E50: 4 | F50: 5
A51: 5.4.11 | B51: Does the organization collect logs from Wireless Access Points? | C51: Level 0 - Does not exist | E51: 4 | F51: 5
A52: 5.4.12 | B52: Does the organization collect logs from Wireless Control Systems? | C52: Level 4 - Managed | E52: 4 | F52: 5
A53: 5.4.13 | B53: Does the organization collect logs from VoIP call center servers? | C53: Level 0 - Does not exist | E53: 4 | F53: 5
A54: 5.5 - Application Coverage
A55: 5.5.1 | B55: Are there specific standards on logging and/or instrumentation for your applications? These may either be COTS (Customn Off the Shelf) or Custom. | C55: Level 1 - Initial | E55: 4 | F55: 5
A56: 5.5.2 | B56: Does the organization have a portfolio of applications that require monitoring and review? | C56: Level 4 - Managed | E56: 4 | F56: 5
A57: 5.5.3 | B57: Are there currently, or there is planned, an adoption of Enterprise Service Bus or SOA (Service Oriented Architecture)? | C57: Level 1 - Initial | E57: 4 | F57: 5
A58: 5.5.4 | B58: Does the organization collect logs from critical database servers? | C58: Level 5 - Optimized | E58: 4 | F58: 5
A59: 5.5.5 | B59: Does the organization collect logs from critical application servers? | C59: Level 5 - Optimized | E59: 4 | F59: 5
A60: 5.5.6 | B60: Does the organization collect logs from critical web servers? | C60: Level 5 - Optimized | E60: 4 | F60: 5
A61: 5.5.7 | B61: Does the organzation collect logs from perimeter application/web servers? | C61: Level 5 - Optimized | E61: 4 | F61: 5
A62: 5.6 - Use Case Enablers
A63: 5.6.1 | B63: Are raw events monitored or are correlated events monitored? | C63: Level 5 - Optimized | E63: 4 | F63: 5
A64: 5.6.2 | B64: What types of events are correlated? | C64: Level 5 - Optimized | E64: 4 | F64: 5 | G64: Events are correlated on the basis of same attributes
A65: 5.6.3 | B65: How well are events correlated? Metrics? | C65: Level 5 - Optimized | E65: 4 | F65: 5
A66: 5.6.4 | B66: Does the organization have cross device type correlation? | C66: Level 5 - Optimized | E66: 4 | F66: 5
A67: 5.6.5 | B67: Does the organization have inter device type correlation? | C67: Level 5 - Optimized | E67: 4 | F67: 5
A68: 5.6.6 | B68: Does the organization have aggregation? | C68: Level 5 - Optimized | E68: 4 | F68: 5
A69: 5.6.7 | B69: Are all rules documented and explained? | C69: Level 5 - Optimized | E69: 4 | F69: 5
A70: 5.6.8 | B70: Does the organization have automatic notification rules? | C70: Level 3 - Defined | E70: 4 | F70: 5 | G70: Yes
A71: 5.6.9 | B71: Does the organization have long-term subtle event rules? | C71: Level 3 - Defined | E71: 4 | F71: 5 | G71: Yes
A72: 5.6.10 | B72: SOC should generate an alarm condition for any custom use cases | C72: Level 5 - Optimized | E72: 4 | F72: 5
A73: 5.6.11 | B73: SOC should generate an alarm condition for new vulnerability detected on critical/sensitive networks | C73: Level 5 - Optimized | E73: 4 | F73: 5
A74: 5.6.12 | B74: SOC should generate an alarm condition for new port and service detected on critical/sensitive networks | C74: Level 5 - Optimized | E74: 4 | F74: 5
A75: 5.6.13 | B75: SOC should correlate configuration changes against change management approved tickets | C75: Level 5 - Optimized | E75: 4 | F75: 5
A76: 5.6.14 | B76: SOC should generate an alarm condition when a default/vendor account has been used | C76: Level 3 - Defined | E76: 4 | F76: 5
A77: 5.6.15 | B77: SOC should generate an alarm condition when an account has been shared | C77: Level 3 - Defined | E77: 4 | F77: 5
A78: 5.6.16 | B78: SOC should generate an alarm condition when an expired/disabled user account has been accessed | C78: Level 5 - Optimized | E78: 4 | F78: 5
A79: 5.6.17 | B79: SOC should generate an alarm condition when a previous employees user account has been accessed | C79: Level 5 - Optimized | E79: 4 | F79: 5
A80: 5.6.18 | B80: SOC should prioritize alarming based on value to the business | C80: Level 5 - Optimized | E80: 4 | F80: 5
A81: 5.6.19 | B81: SOC should generate alarm in instances of unauthorized configuration changes | C81: Level 5 - Optimized | E81: 4 | F81: 5
A82: 5.6.20 | B82: SOC should generate an alarm for anomolous or unauthorized access controls | C82: Level 5 - Optimized | E82: 4 | F82: 5
A83: 5.6.21 | B83: SOC should generate an alarm for anomolous network flow | C83: Level 5 - Optimized | E83: 4 | F83: 5
... A100: 5.6.38 | B100: SOC should have a separate escalation routing meschanism for Cyber Security Incidents | C100: Level 5 - Optimized | E100: 4 | F100: 5
A101: 5.7 - Reports
A102: 5.6.40 | B102: SOC should provide Security Risk Metric Reports | C102: Level 5 - Optimized | E102: 4 | F102: 5
A103: 5.6.41 | B103: SOC should provide Monitoring Performance Metric Reports | C103: Level 5 - Optimized | E103: 4 | F103: 5
A104: 5.6.42 | B104: SOC should provide Security Trending Reports | C104: Level 5 - Optimized | E104: 4 | F104: 5
A105: 5.6.43 | B105: SOC should review audit logs of top high priority IDS events on a weekly basis | C105: Level 2 - Repeatable | E105: 4 | F105: 5
A106: 5.6.44 | B106: SOC should review audit logs of failure activity on a weekly basis | C106: Level 5 - Optimized | E106: 4 | F106: 5
A107: 5.6.45 | B107: SOC should review logs and alarm conditions as defined by the Alarm section in this document on a weekly basis | C107: Level 5 - Optimized | E107: 4 | F107: 5
A108: 5.6.46 | B108: SOC should review all scheduled reports on a weekly basis prior to the Security Operational call | C108: Level 5 - Optimized | E108: 4 | F108: 5
A109: 5.6.47 | B109: SOC should provide provide reports of failed access to critical assets | C109: Level 3 - Defined | E109: 4 | F109: 5
A110: 5.6.48 | B110: SOC should provide reports on Segregation of Duties violation | C110: Level 3 - Defined | E110: 4 | F110: 5
A111: 5.6.49 | B111: SOC should provide reports on role violation | C111: Level 3 - Defined | E111: 4 | F111: 5
A112: 5.6.50 | B112: SOC should provide metric reports on compliance effectiveness | C112: Level 3 - Defined | E112: 4 | F112: 5
A113: 5.6.51 | B113: SOC should provide reports on policy violation | C113: Level 5 - Optimized | E113: 4 | F113: 5
... A127: 5.6.65 | B127: SOC should provide reports on vulnerability trending by platform | C127: Level 5 - Optimized | E127: 4 | F127: 5
A128: 5.6.66 | B128: SOC should provide reports on vulnerability trending by network zone | E128: 4 | F128: 5
A129: 5.6.67 | B129: SOC should report and review user accounts to verify access privileges | E129: 4 | F129: 5
A130: 5.6.68 | B130: SOC should provide reports of shared accounts | E130: 4 | F130: 5
...

Sheet 5.2 - SOC covered event sources
A2: 5.2 - Event Source Coverage
A3: Please enter the current devices/event sources that are incorporated into the SOC
A4: Device vendor | B4: Device Product | C4: Region | D4: Coverage % | G4: Maximum
A5: Business Critical Assets (Assests should be identified in the Asset Model within SIEM)
G6: 5
G7: 5
G8: 5
G9: 5
G10: 5
G11: 5
G12: 5
G13: 5
G14: 5
G16: 5
G17: 5
G18: 5
... G20: 5
A21: Unclassified Assets
G22: 5
G23: 5
G24: 5
G25: 5
G26: 5
G27: 5
G28: 5
G29: 5
G30: 5
G31: 5
G33: 5
G34: 5
... G129: 5
B132: SUMMARY Score | D132: =#REF! -> #REF! | E132: =#REF! -> #REF! | F132: =#REF! -> #REF! | G132: =#REF! -> #REF!
B133: =A5 -> Business Critical Assets (Assests should be identified in the Asset Model within SIEM) | D133: =SUM(D6:D14) -> 0 | E133: =SUM(E6:E14) -> 0 | F133: =SUM(F6:F14) -> 0 | G133: =SUM(G6:G14) -> 45
B134: =A15 -> 0 | D134: =SUM(D16:D31) -> 0 | E134: =SUM(E16:E31) -> 0 | F134: =SUM(F16:F31) -> 0 | G134: =SUM(G16:G31) -> 75
B135: =A32 -> 0 | D135: =SUM(D33:D40) -> 0 | E135: =SUM(E33:E40) -> 0 | F135: =SUM(F33:F40) -> 0 | G135: =SUM(G33:G40) -> 40
B136: =A41 -> 0 | D136: =SUM(D42:D54) -> 0 | E136: =SUM(E42:E54) -> 0 | F136: =SUM(F42:F54) -> 0 | G136: =SUM(G42:G54) -> 65
B137: =A55 -> 0 | D137: =SUM(D56:D59) -> 0 | E137: =SUM(E56:E59) -> 0 | F137: =SUM(F56:F59) -> 0 | G137: =SUM(G56:G59) -> 20
B138: =A60 -> 0 | D138: =SUM(D61:D98) -> 0 | E138: =SUM(E61:E98) -> 0 | F138: =SUM(F61:F98) -> 0 | G138: =SUM(G61:G98) -> 190
B139: =A99 -> 0 | D139: =SUM(D100:D129) -> 0 | E139: =SUM(E100:E129) -> 0 | F139: =SUM(F100:F129) -> 0 | G139: =SUM(G100:G129) -> 150
B140: TOTAL | D140: =SUM(D133:D139) -> 0 | E140: =SUM(E133:E139) -> 0 | F140: =SUM(F133:F139) -> 0 | G140: =SUM(G133:G139) -> 585
B143: Summary Percentage | D143: =D132 -> #REF! | E143: =E132 -> #REF! | F143: =F132 -> #REF! | G143: =G132 -> #REF!
B144: =B133 -> Business Critical Assets (Assests should be identified in the Asset Model within SIEM) | D144: =D133/$G133 -> 0 | E144: =E133/$G133 -> 0 | F144: =F133/$G133 -> 0 | G144: =G133/$G133 -> 1
B145: =B134 -> 0 | D145: =D134/$G134 -> 0 | E145: =E134/$G134 -> 0 | F145: =F134/$G134 -> 0 | G145: =G134/$G134 -> 1
B146: =B135 -> 0 | D146: =D135/$G135 -> 0 | E146: =E135/$G135 -> 0 | F146: =F135/$G135 -> 0 | G146: =G135/$G135 -> 1
B147: =B136 -> 0 | D147: =D136/$G136 -> 0 | E147: =E136/$G136 -> 0 | F147: =F136/$G136 -> 0 | G147: =G136/$G136 -> 1
B148: =B137 -> 0 | D148: =D137/$G137 -> 0 | E148: =E137/$G137 -> 0 | F148: =F137/$G137 -> 0 | G148: =G137/$G137 -> 1
B149: =B138 -> 0 | D149: =D138/$G138 -> 0 | E149: =E138/$G138 -> 0 | F149: =F138/$G138 -> 0 | G149: =G138/$G138 -> 1
B150: =B139 -> 0 | D150: =D139/$G139 -> 0 | E150: =E139/$G139 -> 0 | F150: =F139/$G139 -> 0 | G150: =G139/$G139 -> 1
B151: =B140 -> TOTAL | D151: =D140/$G140 -> 0 | E151: =E140/$G140 -> 0 | F151: =F140/$G140 -> 0 | G151: =G140/$G140 -> 1

Sheet 5.3 - Overall Inventory
A2: 5.3 - Overall Inventory
A3: Please enter numbers of the complete inventory at the organization. Typical this can be obtained from a CMDB, Asset Management etc.. It is recommended that this information should be gathered from non SOC sources (e.g. Operational Teams). Please refer to the worksheet "Sample Event Scope" for sample event sources.
A4: Device vendor | B4: Device Product | C4: Region | D4: Coverage % | G4: Maximum
A5: Business Critical Assets
G6: 5
G7: 5
G8: 5
G9: 5
G10: 5
G11: 5
G12: 5
G13: 5
G14: 5
G16: 5
G17: 5
G18: 5
... G20: 5
A21: Unclassified Assets
G22: 5
G23: 5
G24: 5
G25: 5
G26: 5
G27: 5
G28: 5
G29: 5
G30: 5
G31: 5
G33: 5
G34: 5
... G129: 5
B132: SUMMARY Score | D132: =#REF! -> #REF! | E132: =#REF! -> #REF! | F132: =#REF! -> #REF! | G132: =#REF! -> #REF!
B133: =A5 -> Business Critical Assets | D133: =SUM(D6:D14) -> 0 | E133: =SUM(E6:E14) -> 0 | F133: =SUM(F6:F14) -> 0 | G133: =SUM(G6:G14) -> 45
B134: =A15 -> 0 | D134: =SUM(D16:D31) -> 0 | E134: =SUM(E16:E31) -> 0 | F134: =SUM(F16:F31) -> 0 | G134: =SUM(G16:G31) -> 75
B135: =A32 -> 0 | D135: =SUM(D33:D40) -> 0 | E135: =SUM(E33:E40) -> 0 | F135: =SUM(F33:F40) -> 0 | G135: =SUM(G33:G40) -> 40
B136: =A41 -> 0 | D136: =SUM(D42:D54) -> 0 | E136: =SUM(E42:E54) -> 0 | F136: =SUM(F42:F54) -> 0 | G136: =SUM(G42:G54) -> 65
B137: =A55 -> 0 | D137: =SUM(D56:D59) -> 0 | E137: =SUM(E56:E59) -> 0 | F137: =SUM(F56:F59) -> 0 | G137: =SUM(G56:G59) -> 20
B138: =A60 -> 0 | D138: =SUM(D61:D98) -> 0 | E138: =SUM(E61:E98) -> 0 | F138: =SUM(F61:F98) -> 0 | G138: =SUM(G61:G98) -> 190
B139: =A99 -> 0 | D139: =SUM(D100:D129) -> 0 | E139: =SUM(E100:E129) -> 0 | F139: =SUM(F100:F129) -> 0 | G139: =SUM(G100:G129) -> 150
B140: TOTAL | D140: =SUM(D133:D139) -> 0 | E140: =SUM(E133:E139) -> 0 | F140: =SUM(F133:F139) -> 0 | G140: =SUM(G133:G139) -> 585
B143: Summary Percentage | D143: =D132 -> #REF! | E143: =E132 -> #REF! | F143: =F132 -> #REF! | G143: =G132 -> #REF!
B144: =B133 -> Business Critical Assets | D144: =D133/$G133 -> 0 | E144: =E133/$G133 -> 0 | F144: =F133/$G133 -> 0 | G144: =G133/$G133 -> 1
B145: =B134 -> 0 | D145: =D134/$G134 -> 0 | E145: =E134/$G134 -> 0 | F145: =F134/$G134 -> 0 | G145: =G134/$G134 -> 1
B146: =B135 -> 0 | D146: =D135/$G135 -> 0 | E146: =E135/$G135 -> 0 | F146: =F135/$G135 -> 0 | G146: =G135/$G135 -> 1
B147: =B136 -> 0 | D147: =D136/$G136 -> 0 | E147: =E136/$G136 -> 0 | F147: =F136/$G136 -> 0 | G147: =G136/$G136 -> 1
B148: =B137 -> 0 | D148: =D137/$G137 -> 0 | E148: =E137/$G137 -> 0 | F148: =F137/$G137 -> 0 | G148: =G137/$G137 -> 1
B149: =B138 -> 0 | D149: =D138/$G138 -> 0 | E149: =E138/$G138 -> 0 | F149: =F138/$G138 -> 0 | G149: =G138/$G138 -> 1
B150: =B139 -> 0 | D150: =D139/$G139 -> 0 | E150: =E139/$G139 -> 0 | F150: =F139/$G139 -> 0 | G150: =G139/$G139 -> 1
B151: =B140 -> TOTAL | D151: =D140/$G140 -> 0 | E151: =E140/$G140 -> 0 | F151: =F140/$G140 -> 0 | G151: =G140/$G140 -> 1

Sheet Sample Event Scope
K2: Phase 1 | P2: Phase 2
A3: Phase | B3: Devices | C3: Identify Vendors if needed | D3: Versions (kernel if relative) | E3: Quantity | F3: Datacenter#1 | G3: Datacenter#2 | H3: Datacenter#3 | K3: Phase 1 Scope | L3: Phase 1 Count | M3: =F3 -> Datacenter#1 | N3: =G3 -> Datacenter#2 | O3: =H3 -> Datacenter#3 | P3: Phase 2 Scope | Q3: Phase 2 Count | R3: =F3 -> Datacenter#1 | S3: =G3 -> Datacenter#2 | T3: =H3 -> Datacenter#3
A4: INF | B4: Windows Servers | E4: =SUM(H4,G4,F4) -> 1973 | F4: 398 | G4: 773 | H4: 802 | K4: 0 | L4: =E4*K4 -> 0 | M4: =F4*$K4 -> 0 | N4: =G4*$K4 -> 0 | O4: =H4*$K4 -> 0 | P4: 0 | Q4: =P4*E4 -> 0 | R4: =$P4*F4 -> 0 | S4: =$P4*G4 -> 0 | T4: =$P4*H4 -> 0
A5: INF | B5: Windows Servers | C5: 2000 | E5: =SUM(H5,G5,F5) -> 132 | F5: 46 | G5: 50 | H5: 36 | L5: =E5*K5 -> 0 | M5: =F5*$K5 -> 0 | N5: =G5*$K5 -> 0 | O5: =H5*$K5 -> 0 | P5: 0.05 | Q5: =P5*E5 -> 6.6 | R5: =$P5*F5 -> 2.3 | S5: =$P5*G5 -> 2.5 | T5: =$P5*H5 -> 1.8
A6: INF | B6: Windows Servers | C6: 2003 | E6: =SUM(H6,G6,F6) -> 1324 | F6: 234 | G6: 509 | H6: 581 | L6: =E6*K6 -> 0 | M6: =F6*$K6 -> 0 | N6: =G6*$K6 -> 0 | O6: =H6*$K6 -> 0 | P6: 0.05 | Q6: =P6*E6 -> 66.2 | R6: =$P6*F6 -> 11.7 | S6: =$P6*G6 -> 25.45 | T6: =$P6*H6 -> 29.05
A7: INF | B7: Windows Servers | C7: 2008 | E7: =SUM(H7,G7,F7) -> 517 | F7: 118 | G7: 214 | H7: 185 | L7: =E7*K7 -> 0 | M7: =F7*$K7 -> 0 | N7: =G7*$K7 -> 0 | O7: =H7*$K7 -> 0 | P7: 0.05 | Q7: =P7*E7 -> 25.85 | R7: =$P7*F7 -> 5.9 | S7: =$P7*G7 -> 10.7 | T7: =$P7*H7 -> 9.25
A8: INF | B8: Unix Server | C8: HPUX | D8: 11.11, 11.23 | E8: =SUM(H8,G8,F8) -> 108 | F8: 33 | G8: 64 | H8: 11 | K8: 0.05 | L8: =E8*K8 -> 5.4 | M8: =F8*$K8 -> 1.65 | N8: =G8*$K8 -> 3.2 | O8: =H8*$K8 -> 0.55 | P8: 0.95 | Q8: =P8*E8 -> 102.6 | R8: =$P8*F8 -> 31.35 | S8: =$P8*G8 -> 60.8 | T8: =$P8*H8 -> 10.45
A9: INF | B9: Unix Server | C9: Solaris | D9: 7, 8, 9, 10 | E9: =SUM(H9,G9,F9) -> 34 | F9: 0 | G9: 0 | H9: 34 | L9: =E9*K9 -> 0 | M9: =F9*$K9 -> 0 | N9: =G9*$K9 -> 0 | O9: =H9*$K9 -> 0 | P9: 0.05 | Q9: =P9*E9 -> 1.7 | R9: =$P9*F9 -> 0 | S9: =$P9*G9 -> 0 | T9: =$P9*H9 -> 1.7
A10: INF | B10: Unix Server | C10: AIX | D10: 5.2, 6.1 | E10: =SUM(H10,G10,F10) -> 50 | F10: 0 | G10: 48 | H10: 2 | L10: =E10*K10 -> 0 | M10: =F10*$K10 -> 0 | N10: =G10*$K10 -> 0 | O10: =H10*$K10 -> 0 | P10: 0.05 | Q10: =P10*E10 -> 2.5 | R10: =$P10*F10 -> 0 | S10: =$P10*G10 -> 2.4 | T10: =$P10*H10 -> 0.1
A11: 2 | B11: DNS Server (BIND) | C11: BIND | E11: =SUM(H11,G11,F11) -> 3 | F11: 1 | G11: 1 | H11: 1 | L11: =E11*K11 -> 0 | M11: =F11*$K11 -> 0 | N11: =G11*$K11 -> 0 | O11: =H11*$K11 -> 0 | P11: 1 | Q11: =P11*E11 -> 3 | R11: =$P11*F11 -> 1 | S11: =$P11*G11 -> 1 | T11: =$P11*H11 -> 1
A12: INF | B12: Mail Filtering (IronMail) | E12: =SUM(H12,G12,F12) -> 4 | F12: 0 | G12: 2 | H12: 2 | L12: =E12*K12 -> 0 | M12: =F12*$K12 -> 0 | N12: =G12*$K12 -> 0 | O12: =H12*$K12 -> 0 | P12: 1 | Q12: =P12*E12 -> 4 | R12: =$P12*F12 -> 0 | S12: =$P12*G12 -> 2 | T12: =$P12*H12 -> 2
A13: INF | B13: Load Balancers (Cisco) | E13: =SUM(H13,G13,F13) -> 5 | F13: 2 | G13: 3 | H13: 0 | L13: =E13*K13 -> 0 | M13: =F13*$K13 -> 0 | N13: =G13*$K13 -> 0 | O13: =H13*$K13 -> 0 | P13: 1 | Q13: =P13*E13 -> 5 | R13: =$P13*F13 -> 2 | S13: =$P13*G13 -> 3 | T13: =$P13*H13 -> 0
A14: INF | B14: Load Balancers (F5) | E14: =SUM(H14,G14,F14) -> 7 | F14: 1 | G14: 4 | H14: 2 | L14: =E14*K14 -> 0 | M14: =F14*$K14 -> 0 | N14: =G14*$K14 -> 0 | O14: =H14*$K14 -> 0 | P14: 1 | Q14: =P14*E14 -> 7 | R14: =$P14*F14 -> 1 | S14: =$P14*G14 -> 4 | T14: =$P14*H14 -> 2
A15: INF | B15: Linux Servers | D15: multiple (please review comments) | E15: =SUM(H15,G15,F15) -> 196 | F15: 33 | G15: 44 | H15: 119 | L15: =E15*K15 -> 0 | M15: =F15*$K15 -> 0 | N15: =G15*$K15 -> 0 | O15: =H15*$K15 -> 0 | P15: 1 | Q15: =P15*E15 -> 196 | R15: =$P15*F15 -> 33 | S15: =$P15*G15 -> 44 | T15: =$P15*H15 -> 119
A16: 2 | B16: VMWare Servers | E16: =SUM(H16,G16,F16) -> 105 | F16: 30 | G16: 44 | H16: 31 | L16: =E16*K16 -> 0 | M16: =F16*$K16 -> 0 | N16: =G16*$K16 -> 0 | O16: =H16*$K16 -> 0 | P16: 1 | Q16: =P16*E16 -> 105 | R16: =$P16*F16 -> 30 | S16: =$P16*G16 -> 44 | T16: =$P16*H16 -> 31
A17: INF | B17: WAN Acceleration | C17: riverbed | E17: =SUM(H17,G17,F17) -> 1 | F17: 0 | G17: 0 | H17: 1 | L17: =E17*K17 -> 0 | M17: =F17*$K17 -> 0 | N17: =G17*$K17 -> 0 | O17: =H17*$K17 -> 0 | P17: 1 | Q17: =P17*E17 -> 1 | R17: =$P17*F17 -> 0 | S17: =$P17*G17 -> 0 | T17: =$P17*H17 -> 1
A18: INF | B18: Network Routers (TBC) | C18: Cisco | E18: =SUM(H18,G18,F18) -> 68 | F18: 16 | G18: 29 | H18: 23 | L18: =E18*K18 -> 0 | M18: =F18*$K18 -> 0 | N18: =G18*$K18 -> 0 | O18: =H18*$K18 -> 0 | P18: 1 | Q18: =P18*E18 -> 68 | R18: =$P18*F18 -> 16 | S18: =$P18*G18 -> 29 | T18: =$P18*H18 -> 23
A19: INF | B19: Network Switches (TBC) | C19: Cisco | E19: =SUM(H19,G19,F19) -> 228 | F19: 89 | G19: 61 | H19: 78 | L19: =E19*K19 -> 0 | M19: =F19*$K19 -> 0 | N19: =G19*$K19 -> 0 | O19: =H19*$K19 -> 0 | P19: 1 | Q19: =P19*E19 -> 228 | R19: =$P19*F19 -> 89 | S19: =$P19*G19 -> 61 | T19: =$P19*H19 -> 78
A20: INF | B20: Network Switches (TBC) | C20: HP | E20: =SUM(H20,G20,F20) -> 46 | F20: 0 | G20: 0 | H20: 46 | L20: =E20*K20 -> 0 | M20: =F20*$K20 -> 0 | N20: =G20*$K20 -> 0 | O20: =H20*$K20 -> 0 | P20: 1 | Q20: =P20*E20 -> 46 | R20: =$P20*F20 -> 0 | S20: =$P20*G20 -> 0 | T20: =$P20*H20 -> 46
A21: INF | B21: Network Switches (TBC) | C21: Nortel | E21: =SUM(H21,G21,F21) -> 4 | F21: 0 | G21: 4 | H21: 0 | L21: =E21*K21 -> 0 | M21: =F21*$K21 -> 0 | N21: =G21*$K21 -> 0 | O21: =H21*$K21 -> 0 | P21: 1 | Q21: =P21*E21 -> 4 | R21: =$P21*F21 -> 0 | S21: =$P21*G21 -> 4 | T21: =$P21*H21 -> 0
A22: 1 | B22: Network Firewalls | C22: Cisco ASA | E22: =SUM(H22,G22,F22) -> 4 | F22: 2 | G22: 0 | H22: 2 | K22: 1 | L22: =E22*K22 -> 4 | M22: =F22*$K22 -> 2 | N22: =G22*$K22 -> 0 | O22: =H22*$K22 -> 2 | P22: 0 | Q22: =P22*E22 -> 0 | R22: =$P22*F22 -> 0 | S22: =$P22*G22 -> 0 | T22: =$P22*H22 -> 0
A23: 2 | B23: Network VPN Site-to-Site VPN | E23: =SUM(H23,G23,F23) -> 20 | F23: 2 | G23: 3 | H23: 15 | K23: 1 | L23: =E23*K23 -> 20 | M23: =F23*$K23 -> 2 | N23: =G23*$K23 -> 3 | O23: =H23*$K23 -> 15 | P23: 0 | Q23: =P23*E23 -> 0 | R23: =$P23*F23 -> 0 | S23: =$P23*G23 -> 0 | T23: =$P23*H23 -> 0
A24: INF | B24: Email Servers (Exchange/w Scanmail) | E24: =SUM(H24,G24,F24) -> 62 | F24: 15 | G24: 17 | H24: 30 | L24: =E24*K24 -> 0 | M24: =F24*$K24 -> 0 | N24: =G24*$K24 -> 0 | O24: =H24*$K24 -> 0 | Q24: =P24*E24 -> 0 | R24: =$P24*F24 -> 0 | S24: =$P24*G24 -> 0 | T24: =$P24*H24 -> 0
A25: INF | B25: Domain Users | E25: =SUM(H25,G25,F25) -> 0 | K25: 1 | L25: =E25*K25 -> 0 | M25: =F25*$K25 -> 0 | N25: =G25*$K25 -> 0 | O25: =H25*$K25 -> 0 | Q25: =P25*E25 -> 0 | R25: =$P25*F25 -> 0 | S25: =$P25*G25 -> 0 | T25: =$P25*H25 -> 0
A26: INF | B26: Database Servers (MS SQL) | C26: MS SQL | E26: =SUM(H26,G26,F26) -> 1 | F26: 0 | G26: 0 | H26: 1 | L26: =E26*K26 -> 0 | M26: =F26*$K26 -> 0 | N26: =G26*$K26 -> 0 | O26: =H26*$K26 -> 0 | Q26: =P26*E26 -> 0 | R26: =$P26*F26 -> 0 | S26: =$P26*G26 -> 0 | T26: =$P26*H26 -> 0
A27: 2 | B27: Microsoft ISA 2004 and 2006 | C27: ISA | E27: =SUM(H27,G27,F27) -> 3 | F27: 0 | G27: 0 | H27: 3 | L27: =E27*K27 -> 0 | M27: =F27*$K27 -> 0 | N27: =G27*$K27 -> 0 | O27: =H27*$K27 -> 0 | P27: 1 | Q27: =P27*E27 -> 3 | R27: =$P27*F27 -> 0 | S27: =$P27*G27 -> 0 | T27: =$P27*H27 -> 3
A28: 1 | B28: Microsoft OCS Access Proxy | C28: OCS | E28: =SUM(H28,G28,F28) -> 18 | F28: 2 | G28: 8 | H28: 8 | K28: 1 | L28: =E28*K28 -> 18 | M28: =F28*$K28 -> 2 | N28: =G28*$K28 -> 8 | O28: =H28*$K28 -> 8 | Q28: =P28*E28 -> 0 | R28: =$P28*F28 -> 0 | S28: =$P28*G28 -> 0 | T28: =$P28*H28 -> 0
A29: 2 | B29: Web Servers (BEA Weblogic) | C29: BEA Weblogic | E29: =SUM(H29,G29,F29) -> 2 | F29: 0 | G29: 0 | H29: 2 | L29: =E29*K29 -> 0 | M29: =F29*$K29 -> 0 | N29: =G29*$K29 -> 0 | O29: =H29*$K29 -> 0 | P29: 1 | Q29: =P29*E29 -> 2 | R29: =$P29*F29 -> 0 | S29: =$P29*G29 -> 0 | T29: =$P29*H29 -> 2
A30: 2 | B30: Web Servers (Apache) | C30: Apache | E30: =SUM(H30,G30,F30) -> 1 | F30: 0 | G30: 0 | H30: 1 | L30: =E30*K30 -> 0 | M30: =F30*$K30 -> 0 | N30: =G30*$K30 -> 0 | O30: =H30*$K30 -> 0 | P30: 1 | Q30: =P30*E30 -> 1 | R30: =$P30*F30 -> 0 | S30: =$P30*G30 -> 0 | T30: =$P30*H30 -> 1
A31: 2 | B31: Web Servers (IIS) | C31: IIS | E31: =SUM(H31,G31,F31) -> 10 | F31: 0 | G31: 0 | H31: 10 | L31: =E31*K31 -> 0 | M31: =F31*$K31 -> 0 | N31: =G31*$K31 -> 0 | O31: =H31*$K31 -> 0 | P31: 1 | Q31: =P31*E31 -> 10 | R31: =$P31*F31 -> 0 | S31: =$P31*G31 -> 0 | T31: =$P31*H31 -> 10
A32: 1 | B32: Network Firewalls | C32: Cisco ASA | E32: =SUM(H32,G32,F32) -> 4 | F32: 2 | G32: 0 | H32: 2 | K32: 1 | L32: =E32*K32 -> 4 | M32: =F32*$K32 -> 2 | N32: =G32*$K32 -> 0 | O32: =H32*$K32 -> 2 | Q32: =P32*E32 -> 0 | R32: =$P32*F32 -> 0 | S32: =$P32*G32 -> 0 | T32: =$P32*H32 -> 0
A33: 1 | B33: Network Firewalls | C33: McAfee | E33: =SUM(H33,G33,F33) -> 13 | F33: 3 | G33: 4 | H33: 6 | K33: 1 | L33: =E33*K33 -> 13 | M33: =F33*$K33 -> 3 | N33: =G33*$K33 -> 4 | O33: =H33*$K33 -> 6 | Q33: =P33*E33 -> 0 | R33: =$P33*F33 -> 0 | S33: =$P33*G33 -> 0 | T33: =$P33*H33 -> 0
A34: 1 | B34: Web Filter Blue Coat | E34: =SUM(H34,G34,F34) -> 11 | F34: 1 | G34: 5 | H34: 5 | K34: 1 | L34: =E34*K34 -> 11 | M34: =F34*$K34 -> 1 | N34: =G34*$K34 -> 5 | O34: =H34*$K34 -> 5 | Q34: =P34*E34 -> 0 | R34: =$P34*F34 -> 0 | S34: =$P34*G34 -> 0 | T34: =$P34*H34 -> 0
A35: 1 | B35: Web Filter | C35: 8e6 | E35: =SUM(H35,G35,F35) -> 2 | F35: 0 | G35: 1 | H35: 1 | K35: 1 | L35: =E35*K35 -> 2 | M35: =F35*$K35 -> 0 | N35: =G35*$K35 -> 1 | O35: =H35*$K35 -> 1 | Q35: =P35*E35 -> 0 | R35: =$P35*F35 -> 0 | S35: =$P35*G35 -> 0 | T35: =$P35*H35 -> 0
A36: 1 | B36: Network Firewalls | C36: Cisco Pix | E36: =SUM(H36,G36,F36) -> 2 | F36: 0 | G36: 0 | H36: 2 | K36: 1 | L36: =E36*K36 -> 2 | M36: =F36*$K36 -> 0 | N36: =G36*$K36 -> 0 | O36: =H36*$K36 -> 2 | Q36: =P36*E36 -> 0 | R36: =$P36*F36 -> 0 | S36: =$P36*G36 -> 0 | T36: =$P36*H36 -> 0
A37: 1 | B37: Network Firewalls | C37: Cisco FWSA | E37: =SUM(H37,G37,F37) -> 21 | F37: 3 | G37: 10 | H37: 8 | K37: 1 | L37: =E37*K37 -> 21 | M37: =F37*$K37 -> 3 | N37: =G37*$K37 -> 10 | O37: =H37*$K37 -> 8 | Q37: =P37*E37 -> 0 | R37: =$P37*F37 -> 0 | S37: =$P37*G37 -> 0 | T37: =$P37*H37 -> 0
A38: 1 | B38: AAA | C38: ACS 3.3 | E38: =SUM(H38,G38,F38) -> 2 | F38: 0 | G38: 0 | H38: 2 | K38: 1 | L38: =E38*K38 -> 2 | M38: =F38*$K38 -> 0 | N38: =G38*$K38 -> 0 | O38: =H38*$K38 -> 2 | Q38: =P38*E38 -> 0 | R38: =$P38*F38 -> 0 | S38: =$P38*G38 -> 0 | T38: =$P38*H38 -> 0
A39: 1 | B39: AAA | C39: ACS 5.2 | E39: =SUM(H39,G39,F39) -> 2 | F39: 0 | G39: 1 | H39: 1 | K39: 1 | L39: =E39*K39 -> 2 | M39: =F39*$K39 -> 0 | N39: =G39*$K39 -> 1 | O39: =H39*$K39 -> 1 | Q39: =P39*E39 -> 0 | R39: =$P39*F39 -> 0 | S39: =$P39*G39 -> 0 | T39: =$P39*H39 -> 0
A40: 1 | B40: Network IPS | C40: HP TippingPoint | D40: 2.5.4.6948 | E40: =SUM(H40,G40,F40) -> 20 | F40: 7 | G40: 9 | H40: 4 | K40: 1 | L40: =E40*K40 -> 20 | M40: =F40*$K40 -> 7 | N40: =G40*$K40 -> 9 | O40: =H40*$K40 -> 4 | Q40: =P40*E40 -> 0 | R40: =$P40*F40 -> 0 | S40: =$P40*G40 -> 0 | T40: =$P40*H40 -> 0
A41: 1 | B41: Host IDS | C41: Windows Server (Industrial Defender HIDS) | E41: =SUM(H41,G41,F41) -> 6 | F41: 0 | G41: 0 | H41: 6 | K41: 1 | L41: =E41*K41 -> 6 | M41: =F41*$K41 -> 0 | N41: =G41*$K41 -> 0 | O41: =H41*$K41 -> 6 | Q41: =P41*E41 -> 0 | R41: =$P41*F41 -> 0 | S41: =$P41*G41 -> 0 | T41: =$P41*H41 -> 0
A42: 1 | B42: Host IDS | C42: Linux Server (Industrial Defender HIDS ) | E42: =SUM(H42,G42,F42) -> 4 | F42: 0 | G42: 4 | H42: 0 | K42: 1 | L42: =E42*K42 -> 4 | M42: =F42*$K42 -> 0 | N42: =G42*$K42 -> 4 | O42: =H42*$K42 -> 0 | Q42: =P42*E42 -> 0 | R42: =$P42*F42 -> 0 | S42: =$P42*G42 -> 0 | T42: =$P42*H42 -> 0
A43: 1 | B43: Domain Controllers (Active Directory) | E43: =SUM(H43,G43,F43) -> 62 | F43: 18 | G43: 22 | H43: 22 | K43: 1 | L43: =E43*K43 -> 62 | M43: =F43*$K43 -> 18 | N43: =G43*$K43 -> 22 | O43: =H43*$K43 -> 22 | Q43: =P43*E43 -> 0 | R43: =$P43*F43 -> 0 | S43: =$P43*G43 -> 0 | T43: =$P43*H43 -> 0
A44: 1 | B44: HP WebInspect Scanner | C44: WebInspect | E44: =SUM(H44,G44,F44) -> 6 | F44: 1 | G44: 1 | H44: 4 | K44: 1 | L44: =E44*K44 -> 6 | M44: =F44*$K44 -> 1 | N44: =G44*$K44 -> 1 | O44: =H44*$K44 -> 4 | Q44: =P44*E44 -> 0 | R44: =$P44*F44 -> 0 | S44: =$P44*G44 -> 0 | T44: =$P44*H44 -> 0
A45: 1 | B45: RSA ACE (Authentication Manager 6.1.2 on Windows 2003)) | C45: ACE | E45: =SUM(H45,G45,F45) -> 5 | F45: 1 | G45: 2 | H45: 2 | K45: 1 | L45: =E45*K45 -> 5 | M45: =F45*$K45 -> 1 | N45: =G45*$K45 -> 2 | O45: =H45*$K45 -> 2 | Q45: =P45*E45 -> 0 | R45: =$P45*F45 -> 0 | S45: =$P45*G45 -> 0 | T45: =$P45*H45 -> 0
A46: 1 | B46: RSA ACE (Authentication Manager 7.1, Appliance 3.0) | C46: ACE 7.1 | E46: =SUM(H46,G46,F46) -> 4 | F46: 1 | G46: 1 | H46: 2 | K46: 1 | L46: =E46*K46 -> 4 | M46: =F46*$K46 -> 1 | N46: =G46*$K46 -> 1 | O46: =H46*$K46 -> 2 | Q46: =P46*E46 -> 0 | R46: =$P46*F46 -> 0 | S46: =$P46*G46 -> 0 | T46: =$P46*H46 -> 0
A47: 1 | B47: SSL VPN - Juniper Netscreen SA-6500 | C47: SSL VPN | E47: =SUM(H47,G47,F47) -> 1 | F47: 0 | G47: 0 | H47: 1 | K47: 1 | L47: =E47*K47 -> 1 | M47: =F47*$K47 -> 0 | N47: =G47*$K47 -> 0 | O47: =H47*$K47 -> 1 | Q47: =P47*E47 -> 0 | R47: =$P47*F47 -> 0 | S47: =$P47*G47 -> 0 | T47: =$P47*H47 -> 0
A48: 1 | B48: Client-VPN | E48: =SUM(H48,G48,F48) -> 7 | F48: 2 | G48: 3 | H48: 2 | K48: 1 | L48: =E48*K48 -> 7 | M48: =F48*$K48 -> 2 | N48: =G48*$K48 -> 3 | O48: =H48*$K48 -> 2 | Q48: =P48*E48 -> 0 | R48: =$P48*F48 -> 0 | S48: =$P48*G48 -> 0 | T48: =$P48*H48 -> 0
A49: 1 | B49: Vulnerability Scanners (n-circle) | C49: ISA | E49: =SUM(H49,G49,F49) -> 3 | F49: 0 | G49: 0 | H49: 3 | K49: 1 | L49: =E49*K49 -> 3 | M49: =F49*$K49 -> 0 | N49: =G49*$K49 -> 0 | O49: =H49*$K49 -> 3 | Q49: =P49*E49 -> 0 | R49: =$P49*F49 -> 0 | S49: =$P49*G49 -> 0 | T49: =$P49*H49 -> 0
A50: 1 | B50: Wirless LAN Controller | C50: Cisco | E50: =SUM(H50,G50,F50) -> 130 | F50: 95 | G50: 3 | H50: 32 | K50: 1 | L50: =E50*K50 -> 130 | M50: =F50*$K50 -> 95 | N50: =G50*$K50 -> 3 | O50: =H50*$K50 -> 32 | Q50: =P50*E50 -> 0 | R50: =$P50*F50 -> 0 | S50: =$P50*G50 -> 0 | T50: =$P50*H50 -> 0
A51: 3 | B51: GBY Critical Unix Application Hosts | C51: W2K3 | E51: =SUM(H51,G51,F51) -> 54 | F51: 0 | G51: 54 | H51: 0 | K51: 0 | L51: =E51*K51 -> 0 | M51: =F51*$K51 -> 0 | N51: =G51*$K51 -> 0 | O51: =H51*$K51 -> 0 | Q51: =P51*E51 -> 0 | R51: =$P51*F51 -> 0 | S51: =$P51*G51 -> 0 | T51: =$P51*H51 -> 0
A52: 3 | B52: GBY Critical Windows 2003 Application Hosts | C52: Unix | E52: =SUM(H52,G52,F52) -> 26 | F52: 0 | G52: 26 | H52: 0 | K52: 0 | L52: =E52*K52 -> 0 | M52: =F52*$K52 -> 0 | N52: =G52*$K52 -> 0 | O52: =H52*$K52 -> 0 | Q52: =P52*E52 -> 0 | R52: =$P52*F52 -> 0 | S52: =$P52*G52 -> 0 | T52: =$P52*H52 -> 0
A53: 3 | B53: ICT Critical Windows 2003 Application Hosts | C53: W2K3 | E53: =SUM(H53,G53,F53) -> 159 | F53: 0 | G53: 0 | H53: 159 | K53: 0 | L53: =E53*K53 -> 0 | M53: =F53*$K53 -> 0 | N53: =G53*$K53 -> 0 | O53: =H53*$K53 -> 0 | Q53: =P53*E53 -> 0 | R53: =$P53*F53 -> 0 | S53: =$P53*G53 -> 0 | T53: =$P53*H53 -> 0
A54: 3 | B54: ICT Critical Unix Application Hosts | C54: Unix | E54: =SUM(H54,G54,F54) -> 11 | F54: 0 | G54: 0 | H54: 11 | K54: 0 | L54: =E54*K54 -> 0 | M54: =F54*$K54 -> 0 | N54: =G54*$K54 -> 0 | O54: =H54*$K54 -> 0 | Q54: =P54*E54 -> 0 | R54: =$P54*F54 -> 0 | S54: =$P54*G54 -> 0 | T54: =$P54*H54 -> 0
F55: =SUM(F4:F54) -> 1156 | G55: =SUM(G4:G54) -> 2024 | H55: =SUM(H4:H54) -> 2301 | L55: =SUM(L4:L54) -> 352.4 | M55: =SUM(M4:M54) -> 141.65 | N55: =SUM(N4:N54) -> 80.2 | O55: =SUM(O4:O54) -> 130.55 | Q55: =SUM(Q4:Q54) -> 888.45 | R55: =SUM(R4:R54) -> 223.25 | S55: =SUM(S4:S54) -> 293.85 | T55: =SUM(T4:T54) -> 371.35
O56: =SUM(M55:O55) -> 352.4 | T56: =SUM(R55:T55) -> 888.45
A62: Suggested SIEM Architecture Phase Organization
A63: Phase 1: Focus initially on perimeter, authentication and critical server logs:Firewalls
A64: · NIDS/NIPS
A65: · HIDS/HIPS
A66: · AAA server (e.g. TACACS+, Radius, SecurID etc)
A67: · Domain Controllers
A68: · Critical File and Print
A69: · Critical Business/Infrastructure Servers (OS logs). This may include:
A70: o Collaboration Servers (e.g. Exchange, Call Manager)
A71: o DMZ servers
A72: o Other critical business servers
A73: · NetFlow at key ingress points (for detecting DoS)
... A101: · PCN/SCADA devices
